Workbook

Sheet main-data
B1: Year | C1: Code | D1: Company Name | E1: SIC-2 | F1: Sub Sector | G1: Current’s shares price | H1: Investment | I1: Fixed Assets | J1: Total Assets | K1: Long-Term Liabilities | L1: Total Liabilities | M1: Total Equity | N1: Total outstanding shares | O1: Total Sales/ Revenue | P1: COGS/ Cost of Revenues | Q1: delta sales | R1: delta COGS | S1: ITSE | T1: Expenses (Income) | U1: Net Income | V1: PBV | W1: DAR | X1: DER | Y1: ROA | Z1: ROE | AA1: OPM | AB1: NPM | AC1: ROS | AD1: TI Investment - Hardware | AE1: TI Investment - Software | AF1: Pertamakali/ lanjutan | AG1: TI Investment - Networking | AH1: TI Investment - Datastorage | AI1: TI Investment - License | AJ1: TI Investment - Others | AK1: IT Expenditure | AL1: R&D Expenditures | AM1: Advertising Expenditures
A2: 280 | B2: 2018 | C2: LINK | D2: Link Net Tbk | E2: 9.4 | F2: Sub Sektor Advertising Printing dan Media | I2: 4568443000000 | J2: 6023611000000 | K2: 176933000000 | L2: 1272512000000 | M2: 4751099000000 | N2: 8040000000 | O2: 3728364000000 | P2: 744797000000 | T2: =222697000000+869579000000+59597000000 -> 1151873000000 | U2: 788918000000 | V2: =M2 -> 4751099000000 | W2: =L2/J2 -> 0.21125401 | X2: =L2/M2 -> 0.26783529 | Y2: =U2/J2 -> 0.13097094 | Z2: =U2/M2 -> 0.16604958 | AA2: =(O2-P2)/O2 -> 0.8002349 | AB2: =U2/O2 -> 0.21159897 | AC2: =AA2 -> 0.8002349
A3: 281 | B3: 2019 | C3: LINK | D3: Link Net Tbk | E3: 9.4 | F3: Sub Sektor Advertising Printing dan Media | I3: 4993913000000 | J3: 6652974000000 | K3: 183236000000 | L3: 1996559000000 | M3: 4656415000000 | N3: 8040000000 | O3: 3755262000000 | P3: 747703000000 | T3: =301334000000+528656000000+11231000000 -> 841221000000 | U3: 894531000000 | V3: =M3 -> 4656415000000 | W3: =L3/J3 -> 0.30010023 | X3: =L3/M3 -> 0.428776 | Y3: =U3/J3 -> 0.13445581 | Z3: =U3/M3 -> 0.19210723 | AA3: =(O3-P3)/O3 -> 0.80089192 | AB3: =U3/O3 -> 0.23820735 | AC3: =AA3 -> 0.80089192
A4: 282 | B4: 2020 | C4: LINK | D4: Link Net Tbk | E4: 9.4 | F4: Sub Sektor Advertising Printing dan Media | I4: 5641224000000 | J4: 7799803000000 | K4: 359078000000 | L4: 3177089800000 | M4: 7799803000000 | N4: 8040000000 | O4: 4047964000000 | P4: 868743000000 | T4: =364242000000+505765000000+8171000000 -> 878178000000 | U4: 941707000000 | V4: =M4 -> 7799803000000 | W4: =L4/J4 -> 0.40732949 | X4: =L4/M4 -> 0.40732949 | Y4: =U4/J4 -> 0.12073472 | Z4: =U4/M4 -> 0.12073472 | AA4: =(O4-P4)/O4 -> 0.78538767 | AB4: =U4/O4 -> 0.2326372 | AC4: =AA4 -> 0.78538767
A5: 328 | B5: 2018 | C5: MNCN | D5: Media Nusantara Citra Tbk | E5: 9.4 | F5: Sub Sektor Advertising Printing dan Media | H5: 10065000000 | I5: 5541768000000 | J5: 16339552000000 | K5: 3543528000000 | L5: 5697247000000 | M5: 10642305000000 | N5: =5700000000+34300000000 -> 40000000000 | O5: 7443905000000 | P5: 2825002000000 | T5: =1879140000000+13176000000 -> 1892316000000 | U5: 1605621000000 | V5: =M5 -> 10642305000000 | W5: =L5/J5 -> 0.34867829 | X5: =L5/M5 -> 0.53533957 | Y5: =U5/J5 -> 0.098265913 | Z5: =U5/M5 -> 0.15087155 | AA5: =(O5-P5)/O5 -> 0.62049462 | AB5: =U5/O5 -> 0.21569606 | AC5: =AA5 -> 0.62049462
A6: 329 | B6: 2019 | C6: MNCN | D6: Media Nusantara Citra Tbk | E6: 9.4 | F6: Sub Sektor Advertising Printing dan Media | H6: 196065000000 | I6: 5682365000000 | J6: 17836430000000 | K6: 3171441000000 | L6: 5310928000000 | M6: 12525502000000 | N6: =5700000000+34300000000 -> 40000000000 | O6: 8353365000000 | P6: 3030488000000 | T6: =2063877000000+20378000000 -> 2084255000000 | U6: 2352529000000 | V6: =M6 -> 12525502000000 | W6: =L6/J6 -> 0.29775734 | X6: =L6/M6 -> 0.42400919 | Y6: =U6/J6 -> 0.13189461 | Z6: =U6/M6 -> 0.18781914 | AA6: =(O6-P6)/O6 -> 0.63721351 | AB6: =U6/O6 -> 0.28162651 | AC6: =AA6 -> 0.63721351
A7: 330 | B7: 2020 | C7: MNCN | D7: Media Nusantara Citra Tbk | E7: 9.4 | F7: Sub Sektor Advertising Printing dan Media | H7: 186000000000 | I7: 5781219000000 | J7: 18923235000000 | K7: 2302157000000 | L7: 4461328000000 | M7: 14461907000000 | N7: =5700000000+34300000000 -> 40000000000 | O7: 7956238000000 | P7: 3050672000000 | T7: =2085373000000+36220000000 -> 2121593000000 | U7: 1871028000000 | V7: =M7 -> 14461907000000 | W7: =L7/J7 -> 0.23575927 | X7: =L7/M7 -> 0.30848822 | Y7: =U7/J7 -> 0.098874637 | Z7: =U7/M7 -> 0.1293763 | AA7: =(O7-P7)/O7 -> 0.61656853 | AB7: =U7/O7 -> 0.23516491 | AC7: =AA7 -> 0.61656853
A8: 403 | B8: 2018 | C8: SCMA | D8: Surya Citra Media Tbk | E8: 9.4 | F8: Sub Sektor Advertising Printing dan Media | H8: =49777722000+101711857000 -> 151489579000 | I8: 1071441685000 | J8: 6589842943000 | K8: 218204415000 | L8: 1138592812000 | M8: 5451250131000 | N8: 58000000000 | O8: 5276794930000 | P8: =2358399763000+1069833225000 -> 3428232988000 | T8: =1069833225000+41960745000 -> 1111793970000 | U8: 1475042200000 | V8: =M8 -> 5451250131000 | W8: =L8/J8 -> 0.17277996 | X8: =L8/M8 -> 0.2088682 | Y8: =U8/J8 -> 0.22383571 | Z8: =U8/M8 -> 0.27058788 | AA8: =(O8-P8)/O8 -> 0.35031908 | AB8: =U8/O8 -> 0.27953374 | AC8: =AA8 -> 0.35031908
A9: 404 | B9: 2019 | C9: SCMA | D9: Surya Citra Media Tbk | E9: 9.4 | F9: Sub Sektor Advertising Printing dan Media | H9: =115471352000+17615430000 -> 133086782000 | I9: 1501728860000 | J9: 6716724073000 | K9: 239155397000 | L9: 1228125546000 | M9: 5488598527000 | N9: 58000000000 | O9: 5523362497000 | P9: =2862897768000+1177174576000 -> 4040072344000 | T9: =1177174576000+165730699000 -> 1342905275000 | U9: 1051164602000 | V9: =M9 -> 5488598527000 | W9: =L9/J9 -> 0.18284591 | X9: =L9/M9 -> 0.22375941 | Y9: =U9/J9 -> 0.1564996 | Z9: =U9/M9 -> 0.19151785 | AA9: =(O9-P9)/O9 -> 0.2685484 | AB9: =U9/O9 -> 0.19031244 | AC9: =AA9 -> 0.2685484
A10: 405 | B10: 2020 | C10: SCMA | D10: Surya Citra Media Tbk | E10: 9.4 | F10: Sub Sektor Advertising Printing dan Media | H10: =74618282000+45443124000 -> 120061406000 | I10: 1479438102000 | J10: 6766903494000 | K10: 1327841996000 | L10: 2870316946000 | M10: 3896586548000 | N10: 58000000000 | O10: 5101113259000 | P10: =2491631112000+1154111015000 -> 3645742127000 | T10: =1051164602000+1051164602000 -> 2102329204000 | U10: 1051164602000 | V10: =M10 -> 3896586548000 | W10: =L10/J10 -> 0.42416992 | X10: =L10/M10 -> 0.73662343 | Y10: =U10/J10 -> 0.15533909 | Z10: =U10/M10 -> 0.2697655 | AA10: =(O10-P10)/O10 -> 0.28530461 | AB10: =U10/O10 -> 0.20606572 | AC10: =AA10 -> 0.28530461
A11: 472 | B11: 2018 | C11: VIVA | D11: Visi Media Asia Tbk | E11: 9.4 | F11: Sub Sektor Advertising Printing dan Media | H11: 897825000 | I11: 801699400000 | J11: 8024565813000 | K11: 2949969316000 | L11: 6331144641000 | M11: 1692421172000 | N11: =38287370000+2069580000 -> 40356950000 | O11: 2400197838000 | P11: 2342825116000 | T11: =1332657089000+1144164032000 -> 2476821121000 | U11: -1111687862000 | V11: =M11 -> 1692421172000 | W11: =L11/J11 -> 0.78897037 | X11: =L11/M11 -> 3.7408801 | Y11: =U11/J11 -> -0.13853558 | Z11: =U11/M11 -> -0.65686242 | AA11: =(O11-P11)/O11 -> 0.02390333 | AB11: =U11/O11 -> -0.4631651 | AC11: =AA11 -> 0.02390333
A12: 473 | B12: 2019 | C12: VIVA | D12: Visi Media Asia Tbk | E12: 9.4 | F12: Sub Sektor Advertising Printing dan Media | I12: 755556286000 | J12: 8567653603000 | K12: 305874648000 | L12: 7419666167000 | M12: 1147987436000 | N12: =38287370000+2069580000 -> 40356950000 | O12: 2117781960000 | P12: 2149702385000 | T12: =1232204726000+473756432000 -> 1705961158000 | U12: -540883362000 | V12: =M12 -> 1147987436000 | W12: =L12/J12 -> 0.86600912 | X12: =L12/M12 -> 6.4631946 | Y12: =U12/J12 -> -0.063130863 | Z12: =U12/M12 -> -0.47115791 | AA12: =(O12-P12)/O12 -> -0.015072574 | AB12: =U12/O12 -> -0.25540087 | AC12: =AA12 -> -0.015072574
A13: 474 | B13: 2020 | C13: VIVA | D13: Visi Media Asia Tbk | E13: 9.4 | F13: Sub Sektor Advertising Printing dan Media | I13: 680914303000 | J13: 8584281930000 | K13: 459073171000 | L13: 8369846685000 | M13: 214435245000 | N13: =38287370000+2069580000 -> 40356950000 | O13: 1830516513000 | P13: 1780091859000 | T13: =1046289906000+828492869000 -> 1874782775000 | U13: -809081475000 | V13: =M13 -> 214435245000 | W13: =L13/J13 -> 0.97502001 | X13: =L13/M13 -> 39.032048 | Y13: =U13/J13 -> -0.094251503 | Z13: =U13/M13 -> -3.7730807 | AA13: =(O13-P13)/O13 -> 0.027546681 | AB13: =U13/O13 -> -0.44199627 | AC13: =AA13 -> 0.027546681
A14: 169 | B14: 2018 | C14: EMTK | D14: Elang Mahkota Teknologi Tbk | E14: 9.4 | F14: Sub Sektor Advertising, Printing dan Media | H14: =753122507000+1890135227000 -> 2643257734000 | I14: 2518586345000 | J14: 19525411684000 | K14: 1788053654000 | L14: 4061078369000 | M14: 15464333315000 | N14: 12567018000 | O14: 8959710884000 | P14: 6125120967000 | T14: =496501244000+2446991687000 -> 2943492931000 | U14: -2305536736000 | V14: =M14 -> 15464333315000 | W14: =L14/J14 -> 0.20798939 | X14: =L14/M14 -> 0.26260934 | Y14: =U14/J14 -> -0.11807878 | Z14: =U14/M14 -> -0.14908737 | AA14: =(O14-P14)/O14 -> 0.31637069 | AB14: =U14/O14 -> -0.25732267 | AC14: =AA14 -> 0.31637069 | AD14: 1574090526000 | AE14: 116849247000 | AI14: 1684548534000 | AK14: 28802899000 | AM14: 431375436000
A15: 170 | B15: 2019 | C15: EMTK | D15: Elang Mahkota Teknologi Tbk | E15: 9.4 | F15: Sub Sektor Advertising, Printing dan Media | H15: =780818591000+1274019829000 -> 2054838420000 | I15: 3028963325000 | J15: 17540637852000 | K15: 2586055335000 | L15: 5275358414000 | M15: 12265279438000 | N15: 12567018000 | O15: 11030044792000 | P15: 8270027096000 | T15: =1745999135000+2607161189000 -> 4353160324000 | U15: -2343106373000 | V15: =M15 -> 12265279438000 | W15: =L15/J15 -> 0.30075066 | X15: =L15/M15 -> 0.43010503 | Y15: =U15/J15 -> -0.13358159 | Z15: =U15/M15 -> -0.19103571 | AA15: =(O15-P15)/O15 -> 0.25022724 | AB15: =U15/O15 -> -0.21242945 | AC15: =AA15 -> 0.25022724 | AD15: 1497930720000 | AE15: 81273105000 | AI15: -528157639000 | AK15: 12280970000 | AM15: 56439826000
A16: 171 | B16: 2020 | C16: EMTK | D16: Elang Mahkota Teknologi Tbk | E16: 9.4 | F16: Sub Sektor Advertising, Printing dan Media | H16: =997476863000+1305584490000 -> 2303061353000 | I16: 4583995711000 | J16: 17884145634000 | K16: 2620257556000 | L16: 5485106483000 | M16: 12399039151000 | N16: 12567018000 | O16: 11936381982000 | P16: 9043072852000 | T16: =88249012000+1579745270000 -> 1667994282000 | U16: -1717376472000 | V16: =M16 -> 12399039151000 | W16: =L16/J16 -> 0.30670218 | X16: =L16/M16 -> 0.44238158 | Y16: =U16/J16 -> -0.096027873 | Z16: =U16/M16 -> -0.13850884 | AA16: =(O16-P16)/O16 -> 0.24239415 | AB16: =U16/O16 -> -0.14387747 | AC16: =AA16 -> 0.24239415 | AD16: 1521248746000 | AE16: 81267689000 | AI16: 0 | AK16: 9361613000 | AM16: 41008261000
A17: 259 | B17: 2018 | C17: JTPE | D17: Jasuindo Tiga Perkasa Tbk | E17: 9.4 | F17: Sub Sektor Advertising, Printing dan Media | H17: 8944733876 | I17: 437901244110 | J17: 1087169297635 | K17: 42310284440 | L17: 439743355312 | M17: 647425942323 | N17: 6850000000 | O17: 1269759234189 | P17: 991874760024 | T17: =40386642833+70097895345 -> 110484538178 | U17: 120550064804 | V17: =M17 -> 647425942323 | W17: =L17/J17 -> 0.40448471 | X17: =L17/M17 -> 0.679218 | Y17: =U17/J17 -> 0.11088435 | Z17: =U17/M17 -> 0.186199 | AA17: =(O17-P17)/O17 -> 0.21884816 | AB17: =U17/O17 -> 0.094939309 | AC17: =AA17 -> 0.21884816
A18: 260 | B18: 2019 | C18: JTPE | D18: Jasuindo Tiga Perkasa Tbk | E18: 9.4 | F18: Sub Sektor Advertising, Printing dan Media | H18: 9967624124 | I18: 501238262227 | J18: 1152696526641 | K18: 29176627515 | L18: 406866280932 | M18: 745830245709 | N18: 6850000000 | O18: 1438183885309 | P18: 1058393016361 | T18: =41198223065+82378805407 -> 123577028472 | U18: 182442649410 | V18: =M18 -> 745830245709 | W18: =L18/J18 -> 0.35296912 | X18: =L18/M18 -> 0.54552129 | Y18: =U18/J18 -> 0.15827466 | Z18: =U18/M18 -> 0.24461686 | AA18: =(O18-P18)/O18 -> 0.26407671 | AB18: =U18/O18 -> 0.12685627 | AC18: =AA18 -> 0.26407671
A19: 261 | B19: 2020 | C19: JTPE | D19: Jasuindo Tiga Perkasa Tbk | E19: 9.4 | F19: Sub Sektor Advertising, Printing dan Media | H19: 1637359473 | I19: 510514957020 | J19: 1038097010616 | K19: 23715199115 | L19: 267681176266 | M19: 770415834350 | N19: 6850000000 | O19: 978625887145 | P19: 758926697868 | T19: =27076217248+79701637171 -> 106777854419 | U19: 74172914384 | V19: =M19 -> 770415834350 | W19: =L19/J19 -> 0.25785757 | X19: =L19/M19 -> 0.34745025 | Y19: =U19/J19 -> 0.071450851 | Z19: =U19/M19 -> 0.096276467 | AA19: =(O19-P19)/O19 -> 0.22449763 | AB19: =U19/O19 -> 0.075792921 | AC19: =AA19 -> 0.22449763
A20: 31 | B20: 2018 | C20: ASBI | D20: Asuransi Bintang Tbk | E20: 8.4 | F20: Sub Sektor Asuransi | H20: =x!C12 -> 290476830 | I20: 123308301000 | J20: 874472888000 | L20: 593110979000 | M20: 281361909000 | N20: 640000000 | O20: 264899142000 | P20: 124758053000 | T20: 3501669000 | U20: 3274307000 | V20: =M20 -> 281361909000 | W20: =L20/J20 -> 0.67824971 | X20: =L20/M20 -> 2.1080003 | Y20: =U20/J20 -> 0.0037443208 | Z20: =U20/M20 -> 0.01163735 | AA20: =(O20-P20)/O20 -> 0.52903565 | AB20: =U20/O20 -> 0.01236058 | AC20: =AA20 -> 0.52903565 | AE20: 1914136000 | AI20: 4929704000 | AL20: 365466000 | AM20: 37472681000
A21: 32 | B21: 2019 | C21: ASBI | D21: Asuransi Bintang Tbk | E21: 8.4 | F21: Sub Sektor Asuransi | H21: =x!B12 -> 272057904 | I21: 127895603000 | J21: 857520585000 | L21: 566035087000 | M21: 291351494000 | N21: 640000000 | O21: 250804486000 | P21: 134257087000 | T21: 1102516000 | U21: 3581215000 | V21: =M21 -> 291351494000 | W21: =L21/J21 -> 0.66008338 | X21: =L21/M21 -> 1.9427911 | Y21: =U21/J21 -> 0.0041762438 | Z21: =U21/M21 -> 0.012291734 | AA21: =(O21-P21)/O21 -> 0.46469424 | AB21: =U21/O21 -> 0.014278911 | AC21: =AA21 -> 0.46469424 | AE21: 891342000 | AI21: 4929704000 | AL21: 259575000 | AM21: 24208733000
A22: 33 | B22: 2020 | C22: ASBI | D22: Asuransi Bintang Tbk | E22: 8.4 | F22: Sub Sektor Asuransi | H22: =x!A12 -> 304792271 | I22: 125064327000 | J22: 871769183000 | L22: 557997452000 | M22: 313771731000 | N22: 640000000 | O22: 231470118000 | P22: 109895092000 | T22: =780141000+425091000 -> 1205232000 | U22: 10456654000 | V22: =M22 -> 313771731000 | W22: =L22/J22 -> 0.64007476 | X22: =L22/M22 -> 1.7783548 | Y22: =U22/J22 -> 0.011994751 | Z22: =U22/M22 -> 0.033325673 | AA22: =(O22-P22)/O22 -> 0.5252299 | AB22: =U22/O22 -> 0.045174963 | AC22: =AA22 -> 0.5252299 | AE22: 207838000 | AI22: 4929704000 | AL22: 418733000 | AM22: 46947329000
A23: 37 | B23: 2018 | C23: ASMI | D23: Asuransi Kresna Mitra Tbk | E23: 8.4 | F23: Sub Sektor Asuransi | H23: 229934584995 | I23: 21609167523 | J23: 969866560976 | L23: 450272263738 | M23: 519594297238 | N23: 25000000000 | O23: 135633770098 | P23: 68591523905 | T23: 76025853817 | U23: 71761034881 | V23: =M23 -> 519594297238 | W23: =L23/J23 -> 0.46426208 | X23: =L23/M23 -> 0.86658431 | Y23: =U23/J23 -> 0.073990627 | Z23: =U23/M23 -> 0.13810974 | AA23: =(O23-P23)/O23 -> 0.49428875 | AB23: =U23/O23 -> 0.52907941 | AC23: =AA23 -> 0.49428875 | AE23: 1284135515 | AK23: 1378488571 | AM23: 19174178788
A24: 38 | B24: 2019 | C24: ASMI | D24: Asuransi Kresna Mitra Tbk | E24: 8.4 | F24: Sub Sektor Asuransi | H24: 351654846593 | I24: 24621076327 | J24: 975687462693 | L24: 445392630259 | M24: 530294832434 | N24: 25000000000 | O24: 175174507884 | P24: 101954815930 | T24: 72793612247 | U24: 8260755476 | V24: =M24 -> 530294832434 | W24: =L24/J24 -> 0.45649109 | X24: =L24/M24 -> 0.83989623 | Y24: =U24/J24 -> 0.0084666 | Z24: =U24/M24 -> 0.015577665 | AA24: =(O24-P24)/O24 -> 0.41798143 | AB24: =U24/O24 -> 0.047157292 | AC24: =AA24 -> 0.41798143 | AE24: 1219335058 | AK24: 1891162306 | AM24: 9580544598
A25: 39 | B25: 2020 | C25: ASMI | D25: Asuransi Kresna Mitra Tbk | E25: 8.4 | F25: Sub Sektor Asuransi | H25: 299816222397 | I25: 23989286699 | J25: 990991744064 | L25: 547541424689 | M25: 443450319375 | N25: 25000000000 | O25: 185567699856 | P25: 179184782942 | T25: 91760615438 | U25: -88526593736 | V25: =M25 -> 443450319375 | W25: =L25/J25 -> 0.55251865 | X25: =L25/M25 -> 1.23473 | Y25: =U25/J25 -> -0.089331313 | Z25: =U25/M25 -> -0.19963137 | AA25: =(O25-P25)/O25 -> 0.034396702 | AB25: =U25/O25 -> -0.4770582 | AC25: =AA25 -> 0.034396702 | AE25: 1078815684 | AK25: 1285504951 | AM25: 10945430380
A26: 40 | B26: 2018 | C26: ASRM | D26: Asuransi Ramayana Tbk | E26: 8.4 | F26: Sub Sektor Asuransi | H26: 405170089601 | I26: 59951428986 | J26: 1478007061719 | L26: 1072221723281 | M26: 405785338438 | N26: 420000000 | O26: 902165344517 | P26: 590399043504 | T26: 31849926816 | U26: 3573526494 | V26: =M26 -> 405785338438 | W26: =L26/J26 -> 0.72545102 | X26: =L26/M26 -> 2.6423373 | Y26: =U26/J26 -> 0.0024178007 | Z26: =U26/M26 -> 0.0088064456 | AA26: =(O26-P26)/O26 -> 0.34557557 | AB26: =U26/O26 -> 0.0039610549 | AC26: =AA26 -> 0.34557557 | AL26: 98816860220 | AM26: 32885830555
A27: 41 | B27: 2019 | C27: ASRM | D27: Asuransi Ramayana Tbk | E27: 8.4 | F27: Sub Sektor Asuransi | H27: 386940712793 | I27: 67512713635 | J27: 1548001829554 | L27: 1104712550189 | M27: 443289279365 | N27: 420000000 | O27: 1177500392010 | P27: 842624761795 | T27: 40486294000 | U27: 2089220151 | V27: =M27 -> 443289279365 | W27: =L27/J27 -> 0.71363775 | X27: =L27/M27 -> 2.4920805 | Y27: =U27/J27 -> 0.0013496238 | Z27: =U27/M27 -> 0.004712995 | AA27: =(O27-P27)/O27 -> 0.28439534 | AB27: =U27/O27 -> 0.001774284 | AC27: =AA27 -> 0.28439534 | AL27: 40172672851 | AM27: 58790710807
A28: 42 | B28: 2020 | C28: ASRM | D28: Asuransi Ramayana Tbk | E28: 8.4 | F28: Sub Sektor Asuransi | H28: 381002504552 | I28: 65757265183 | J28: 1516562973028 | L28: 1013381758085 | M28: 503181214943 | N28: 420000000 | O28: 1323139975825 | P28: 1014017867183 | T28: 25818453029 | U28: 16434884891 | V28: =M28 -> 503181214943 | W28: =L28/J28 -> 0.66820948 | X28: =L28/M28 -> 2.0139499 | Y28: =U28/J28 -> 0.010836929 | Z28: =U28/M28 -> 0.03266196 | AA28: =(O28-P28)/O28 -> 0.23362767 | AB28: =U28/O28 -> 0.012421123 | AC28: =AA28 -> 0.23362767 | AL28: 30381432048 | AM28: 63158641619
A29: 286 | B29: 2018 | C29: LPGI | D29: Lippo General Insurance Tbk | E29: 8.4 | F29: Sub Sektor Asuransi | H29: 1244581717689 | I29: 41712464138 | J29: 2485186649117 | L29: 1605367155250 | M29: 879819493867 | N29: 350000 | O29: 1132421357486 | P29: 1054327720740 | T29: 140384182320 | U29: 68687123783 | V29: =M29 -> 879819493867 | W29: =L29/J29 -> 0.64597448 | X29: =L29/M29 -> 1.8246551 | Y29: =U29/J29 -> 0.027638618 | Z29: =U29/M29 -> 0.078069563 | AA29: =(O29-P29)/O29 -> 0.068961642 | AB29: =U29/O29 -> 0.060655094 | AC29: =AA29 -> 0.068961642
A30: 287 | B30: 2019 | C30: LPGI | D30: Lippo General Insurance Tbk | E30: 8.4 | F30: Sub Sektor Asuransi | H30: 1185399911397 | I30: 59931111698 | J30: 2425843273596 | L30: 1575194310012 | M30: 848511733189 | N30: 350000 | O30: 1167490752228 | P30: 1079716721795 | T30: 190106898267 | U30: 80002543527 | V30: =M30 -> 848511733189 | W30: =L30/J30 -> 0.64933886 | X30: =L30/M30 -> 1.8564202 | Y30: =U30/J30 -> 0.032979271 | Z30: =U30/M30 -> 0.094285725 | AA30: =(O30-P30)/O30 -> 0.075181778 | AB30: =U30/O30 -> 0.068525205 | AC30: =AA30 -> 0.075181778
A31: 288 | B31: 2020 | C31: LPGI | D31: Lippo General Insurance Tbk | E31: 8.4 | F31: Sub Sektor Asuransi | H31: 1339253561392 | I31: 61211166120 | J31: 2815578393095 | L31: 1954498917680 | M31: 861079475415 | N31: 350000 | O31: 1220142637207 | P31: 1108228300836 | T31: 206201182748 | U31: 92908485040 | V31: =M31 -> 861079475415 | W31: =L31/J31 -> 0.69417315 | X31: =L31/M31 -> 2.2698241 | Y31: =U31/J31 -> 0.03299801 | Z31: =U31/M31 -> 0.10789769 | AA31: =(O31-P31)/O31 -> 0.091722339 | AB31: =U31/O31 -> 0.076145593 | AC31: =AA31 -> 0.091722339
A32: 334 | B32: 2018 | C32: MREI | D32: Maskapai Reasuransi Indonesia Tbk | E32: 8.4 | F32: Sub Sektor Asuransi | H32: =54966990708+829157926820+79259786000+3530551000+50555776200+147129560810+450308063 -> 1165050899601 | I32: 56864203151 | J32: 3426618296227 | L32: 2016141327384 | M32: 1410476968843 | N32: 1500000000 | O32: 1216973600364 | P32: 1045948505140 | T32: =94173689178 -> 94173689178 | U32: 140867155045 | V32: =M32 -> 1410476968843 | W32: =L32/J32 -> 0.5883764 | X32: =L32/M32 -> 1.4294039 | Y32: =U32/J32 -> 0.041109672 | Z32: =U32/M32 -> 0.099871999 | AA32: =(O32-P32)/O32 -> 0.14053312 | AB32: =U32/O32 -> 0.11575202 | AC32: =AA32 -> 0.14053312
A33: 335 | B33: 2019 | C33: MREI | D33: Maskapai Reasuransi Indonesia Tbk | E33: 8.4 | F33: Sub Sektor Asuransi | H33: =58470685750+824245247516+84426565660+116356935277+48742088000+51970033000+226867191437+85000000000+450308063 -> 1496529054703 | I33: 51455786161 | J33: 3915599148016 | L33: 2320512877462 | M33: 1595086270554 | N33: 1500000000 | O33: 1470949804896 | P33: 1309841112268 | T33: =95698788167+1430389202 -> 97129177369 | U33: 179282076899 | V33: =M33 -> 1595086270554 | W33: =L33/J33 -> 0.5926329 | X33: =L33/M33 -> 1.4547883 | Y33: =U33/J33 -> 0.045786627 | Z33: =U33/M33 -> 0.11239648 | AA33: =(O33-P33)/O33 -> 0.10952698 | AB33: =U33/O33 -> 0.12188185 | AC33: =AA33 -> 0.10952698
A34: 336 | B34: 2020 | C34: MREI | D34: Maskapai Reasuransi Indonesia Tbk | E34: 8.4 | F34: Sub Sektor Asuransi | H34: =62473445788+1346932585980+93783097120+101776975900+90999836000+53002907000+69729500572+85000000000+450308063 -> 1904148656423 | I34: 47281288654 | J34: 4203345266072 | L34: 2447545581054 | M34: 1755799685018 | N34: 1500000000 | O34: 1526256873467 | P34: 1437653868089 | T34: =87332688115+4793732040 -> 92126420155 | U34: 105182858790 | V34: =M34 -> 1755799685018 | W34: =L34/J34 -> 0.58228516 | X34: =L34/M34 -> 1.3939777 | Y34: =U34/J34 -> 0.025023607 | Z34: =U34/M34 -> 0.059905956 | AA34: =(O34-P34)/O34 -> 0.058052486 | AB34: =U34/O34 -> 0.068915568 | AC34: =AA34 -> 0.058052486
A35: 469 | B35: 2018 | C35: VINS | D35: Victoria Insurance Tbk | E35: 8.4 | F35: Sub Sektor Asuransi | H35: =8300000000+44396200000+17861250000+60822300000+16959102000+26178600000+3206244457+7374811915+90000000+3000751970 -> 188189260342 | I35: 1162886570 | J35: 262118630829 | L35: 82390315351 | M35: 179728315478 | N35: 4250000000 | O35: 25396161153 | P35: 13254779808 | T35: 13406900449 | U35: 3947657923 | V35: =W29:W38 -> 0.31432453 | W35: =L35/J35 -> 0.31432453 | X35: =L35/M35 -> 0.45841589 | Y35: =U34/J35 -> 0.4012796 | Z35: =U34/M35 -> 0.58523254 | AA35: =(O35-P35)/O35 -> 0.47807939 | AB35: =U34/O35 -> 4.1416834 | AC35: =AA35 -> 0.47807939
A36: 470 | B36: 2019 | C36: VINS | D36: Victoria Insurance Tbk | E36: 8.4 | F36: Sub Sektor Asuransi | H36: =38195050500+48523500000+66692600000+31599625000+951541661+3116108000 -> 189078425161 | I36: 2050262917 | J36: 284170955431 | L36: 97838690688 | M36: 186332264743 | N36: 4250000000 | O36: 26117484368 | P36: 11356539881 | T36: 15315108957 | U36: 21806030031 | V36: =M36 -> 186332264743 | W36: =L36/J36 -> 0.34429518 | X36: =L36/M36 -> 0.52507649 | Y36: =U36/J36 -> 0.076735604 | Z36: =U36/M36 -> 0.11702767 | AA36: =(O36-P36)/O36 -> 0.56517482 | AB36: =U36/O36 -> 0.83492077 | AC36: =AA36 -> 0.56517482
A37: 471 | B37: 2020 | C37: VINS | D37: Victoria Insurance Tbk | E37: 8.4 | F37: Sub Sektor Asuransi | H37: =27200000000+21361500000+81571880000+25341290000+20639947746+1995234258 -> 178109852004 | I37: 3518827068 | J37: 322342387320 | L37: 138095296876 | M37: 184247090444 | N37: 4250000000 | O37: 26509968632 | P37: 17239784399 | T37: 13577579905 | U37: 6211645756 | V37: =M37 -> 184247090444 | W37: =L37/J37 -> 0.42841185 | X37: =L37/M37 -> 0.74951141 | Y37: =U37/J37 -> 0.019270335 | Z37: =U37/M37 -> 0.033713671 | AA37: =(O37-P37)/O37 -> 0.34968673 | AB37: =U37/O37 -> 0.23431358 | AC37: =AA37 -> 0.34968673
A38: 13 | B38: 2018 | C38: AGRO | D38: Bank Rakyat Indonesia Agroniaga Tbk | E38: 8.1 | F38: Sub Sektor Bank | H38: 1931292672000 | I38: 259140701000 | J38: 23313671252000 | L38: 18889385436000 | M38: 4424285816000 | N38: 60000000000 | O38: 1663667161000 | P38: 987737580000 | T38: 281302960000 | U38: 142660203000 | V38: =M38 -> 4424285816000 | W38: =L38/J38 -> 0.81022784 | X38: =L38/M38 -> 4.2694768 | Y38: =U38/J38 -> 0.0061191651 | Z38: =U38/M38 -> 0.032244798 | AA38: =(O38-P38)/O38 -> 0.40628895 | AB38: =U38/O38 -> 0.085750447 | AC38: =AA38 -> 0.40628895 | AK38: 1988951000 | AL38: 611028000 | AM38: 12416420000
A39: 14 | B39: 2019 | C39: AGRO | D39: Bank Rakyat Indonesia Agroniaga Tbk | E39: 8.1 | F39: Sub Sektor Bank | H39: 3520204181000 | I39: 262120871000 | J39: 27067922912000 | L39: 22586218693000 | M39: 4481704219000 | N39: 60000000000 | O39: 2054837678000 | P39: 1361627112000 | T39: 312040493000 | U39: 86365196000 | V39: =M39 -> 4481704219000 | W39: =L39/J39 -> 0.83442748 | X39: =L39/M39 -> 5.0396496 | Y39: =U39/J39 -> 0.0031906843 | Z39: =U39/M39 -> 0.019270615 | AA39: =(O39-P39)/O39 -> 0.33735539 | AB39: =U39/O39 -> 0.042030179 | AC39: =AA39 -> 0.33735539 | AK39: 2133421000 | AL39: 811819000 | AM39: 14460082000
A40: 15 | B40: 2020 | C40: AGRO | D40: Bank Rakyat Indonesia Agroniaga Tbk | E40: 8.1 | F40: Sub Sektor Bank | H40: 3360741177000 | I40: 277438069000 | J40: 28015492262000 | L40: 23727802051000 | M40: 4287690211000 | N40: 60000000000 | O40: 1931524786000 | P40: 1306889194000 | T40: =115346440000+200473577000 -> 315820017000 | U40: 117206028000 | V40: =M40 -> 4287690211000 | W40: =L40/J40 -> 0.84695289 | X40: =L40/M40 -> 5.5339357 | Y40: =U40/J40 -> 0.0041836148 | Z40: =U40/M40 -> 0.02733547 | AA40: =(O40-P40)/O40 -> 0.32338989 | AB40: =U40/O40 -> 0.060680572 | AC40: =AA40 -> 0.32338989 | AK40: 1879511000 | AL40: 1043656000 | AM40: 10813540000
A41: 16 | B41: 2018 | C41: AGRS | D41: Bank Agris Tbk | E41: 8.1 | F41: Sub Sektor Bank | H41: 412475000000 | I41: 15792000000 | J41: 4151151000000 | L41: 3618348000000 | M41: 532803000000 | N41: 11800000000 | O41: 133934000000 | P41: 171078000000 | T41: 171078000000 | U41: -31122000000 | V41: =M41 -> 532803000000 | W41: =L41/J41 -> 0.87164933 | X41: =L41/M41 -> 6.7911555 | Y41: =U41/J41 -> -0.0074971978 | Z41: =U41/M41 -> -0.058411833 | AA41: =(O41-P41)/O41 -> -0.27733063 | AB41: =U41/O41 -> -0.23236818 | AC41: =AA41 -> -0.27733063 | AE41: 4239000000 | AK41: 6565000000 | AM41: 1237000000
A42: 17 | B42: 2019 | C42: AGRS | D42: Bank Agris Tbk | E42: 8.1 | F42: Sub Sektor Bank | H42: 1348990000000 | I42: 134776000000 | J42: 6421844000000 | L42: 5219244000000 | M42: 1202600000000 | N42: 11800000000 | O42: 166231000000 | P42: 223544000000 | T42: 212614000000 | U42: -259525000000 | V42: =M42 -> 1202600000000 | W42: =L42/J42 -> 0.81273292 | X42: =L42/M42 -> 4.3399667 | Y42: =U42/J42 -> -0.040412847 | Z42: =U42/M42 -> -0.21580326 | AA42: =(O42-P42)/O42 -> -0.34477925 | AB42: =U42/O42 -> -1.5612311 | AC42: =AA42 -> -0.34477925 | AE42: 55933000000 | AK42: 12466000000 | AM42: 3285000000
A43: 18 | B43: 2020 | C43: AGRS | D43: Bank Agris Tbk | E43: 8.1 | F43: Sub Sektor Bank | H43: 750146000000 | I43: 171496000000 | J43: 9854035000000 | L43: 7954197000000 | M43: 1899838000000 | N43: 11800000000 | O43: 169710000000 | P43: 336070000000 | T43: 336070000000 | U43: -176863000000 | V43: =M43 -> 1899838000000 | W43: =L43/J43 -> 0.80720202 | X43: =L43/M43 -> 4.1867765 | Y43: =U43/J43 -> -0.017948282 | Z43: =U43/M43 -> -0.093093727 | AA43: =(O43-P43)/O43 -> -0.98026044 | AB43: =U43/O43 -> -1.0421484 | AC43: =AA43 -> -0.98026044 | AE43: 52044000000 | AK43: 7075000000 | AM43: 4390000000
A44: 49 | B44: 2018 | C44: BABP | D44: Bank MNC Internasional Tbk | E44: 8.1 | F44: Sub Sektor Bank | H44: 927423000000 | I44: 48137000000 | J44: 10854855000000 | L44: 9424865000000 | M44: 1429990000000 | N44: 60000000000 | O44: 960256000000 | P44: 572785000000 | T44: 307274000000 | U44: 57021000000 | V44: =M44 -> 1429990000000 | W44: =L44/J44 -> 0.86826263 | X44: =L44/M44 -> 6.5908608 | Y44: =U44/J44 -> 0.0052530412 | Z44: =U44/M44 -> 0.039875104 | AA44: =(O44-P44)/O44 -> 0.40350802 | AB44: =U44/O44 -> 0.05938104 | AC44: =AA44 -> 0.40350802 | AK44: 49152000000 | AM44: 5817000000
A45: 50 | B45: 2019 | C45: BABP | D45: Bank MNC Internasional Tbk | E45: 8.1 | F45: Sub Sektor Bank | H45: 969245000000 | I45: 48316000000 | J45: 10607879000000 | L45: 9048429000000 | M45: 1559450000000 | N45: 60000000000 | O45: 1071032000000 | P45: 667529000000 | T45: 339722000000 | U45: 20433000000 | V45: =M45 -> 1559450000000 | W45: =L45/J45 -> 0.85299135 | X45: =L45/M45 -> 5.8023207 | Y45: =U45/J45 -> 0.0019262098 | Z45: =U45/M45 -> 0.013102696 | AA45: =(O45-P45)/O45 -> 0.37674224 | AB45: =U45/O45 -> 0.019077861 | AC45: =AA45 -> 0.37674224 | AK45: 49496000000 | AM45: 6474000000
A46: 51 | B46: 2020 | C46: BABP | D46: Bank MNC Internasional Tbk | E46: 8.1 | F46: Sub Sektor Bank | H46: 1620855000000 | I46: 40914000000 | J46: 11652904000000 | L46: 10101667000000 | M46: 11652904000000 | N46: 60000000000 | O46: 969784000000 | P46: 368535000000 | T46: 345839000000 | U46: 10414000000 | V46: =M46 -> 11652904000000 | W46: =L46/J46 -> 0.86687979 | X46: =L46/M46 -> 0.86687979 | Y46: =U46/J46 -> 0.00089368281 | Z46: =U46/M46 -> 0.00089368281 | AA46: =(O46-P46)/O46 -> 0.61998239 | AB46: =U46/O46 -> 0.010738474 | AC46: =AA46 -> 0.61998239 | AK46: 50635000000 | AM46: 8740000000
A47: 52 | B47: 2018 | C47: BBCA | D47: Bank Central Asia Tbk | E47: 8.1 | F47: Sub Sektor Bank | H47: 109080663000000 | I47: 19336901000000 | J47: 824787944000000 | L47: 668438779000000 | M47: 151753427000000 | N47: 88000000000 | O47: 56766800000000 | P47: 11476255000000 | T47: 27651554000000 | U47: 25851660000000 | V47: =M47 -> 151753427000000 | W47: =L47/J47 -> 0.81043714 | X47: =L47/M47 -> 4.4047689 | Y47: =U47/J47 -> 0.031343402 | Z47: =U47/M47 -> 0.17035306 | AA47: =(O47-P47)/O47 -> 0.79783509 | AB47: =U47/O47 -> 0.45540104 | AC47: =AA47 -> 0.79783509 | AK47: 102877000000 | AL47: 36150000000 | AM47: 1108898000000
A48: 53 | B48: 2019 | C48: BBCA | D48: Bank Central Asia Tbk | E48: 8.1 | F48: Sub Sektor Bank | H48: 142982705000000 | I48: 20852301000000 | J48: 918989312000000 | L48: 740067127000000 | M48: 174143156000000 | N48: 88000000000 | O48: 63837795000000 | P48: 13360347000000 | T48: 30742208000000 | U48: 28569974000000 | V48: =M48 -> 174143156000000 | W48: =L48/J48 -> 0.80530548 | X48: =L48/M48 -> 4.2497629 | Y48: =U48/J48 -> 0.031088473 | Z48: =U48/M48 -> 0.16406027 | AA48: =(O48-P48)/O48 -> 0.79071415 | AB48: =U48/O48 -> 0.44754011 | AC48: =AA48 -> 0.79071415 | AE48: 1945951000000 | AK48: 203919000000 | AL48: 32889000000 | AM48: 1118345000000
A49: 54 | B49: 2020 | C49: BBCA | D49: Bank Central Asia Tbk | E49: 8.1 | F49: Sub Sektor Bank | H49: 192553101000000 | I49: 21915054000000 | J49: 1.0755703e+15 | L49: 885537919000000 | M49: 184714709000000 | N49: 88000000000 | O49: 65403161000000 | P49: 11241891000000 | T49: 29968715000000 | U49: 27147109000000 | V49: =M49 -> 184714709000000 | W49: =L49/J49 -> 0.82331946 | X49: =L49/M49 -> 4.7940845 | Y49: =U49/J49 -> 0.025239736 | Z49: =U49/M49 -> 0.14696777 | AA49: =(O49-P49)/O49 -> 0.82811395 | AB49: =U49/O49 -> 0.41507335 | AC49: =AA49 -> 0.82811395 | AE49: 2197454000000 | AK49: 92751000000 | AL49: 25429000000 | AM49: 870086000000
A50: 55 | B50: 2018 | C50: BBHI | D50: Bank Harda Internasional Tbk | E50: 8.1 | F50: Sub Sektor Bank | H50: 91337427315 | I50: 34368921424 | J50: 2264172563518 | L50: 1927690426617 | M50: 336482136901 | N50: 10000000000 | O50: 222339040371 | P50: 120624113372 | T50: 58187078926 | U50: -123143307728 | V50: =M50 -> 336482136901 | W50: =L50/J50 -> 0.85138848 | X50: =L50/M50 -> 5.7289532 | Y50: =U50/J50 -> -0.054387775 | Z50: =U50/M50 -> -0.36597279 | AA50: =(O50-P50)/O50 -> 0.45747668 | AB50: =U50/O50 -> -0.55385373 | AC50: =AA50 -> 0.45747668 | AE50: 4611355795
A51: 56 | B51: 2019 | C51: BBHI | D51: Bank Harda Internasional Tbk | E51: 8.1 | F51: Sub Sektor Bank | H51: 115565191969 | I51: 32804430650 | J51: 2527173168770 | L51: 2227407291122 | M51: 299765877648 | N51: 10000000000 | O51: 222323923791 | P51: 135940003048 | T51: 60987155987 | U51: -36549663189 | V51: =M51 -> 299765877648 | W51: =L51/J51 -> 0.88138293 | X51: =L51/M51 -> 7.4304898 | Y51: =U51/J51 -> -0.014462667 | Z51: =U51/M51 -> -0.12192736 | AA51: =(O51-P51)/O51 -> 0.38854982 | AB51: =U51/O51 -> -0.16439825 | AC51: =AA51 -> 0.38854982 | AE51: 3466004250
A52: 57 | B52: 2020 | C52: BBHI | D52: Bank Harda Internasional Tbk | E52: 8.1 | F52: Sub Sektor Bank | H52: 934116390134 | I52: 30376640192 | J52: 2586663487991 | L52: 2239597029811 | M52: 347066458180 | N52: 10000000000 | O52: 162125871157 | P52: 114535488869 | T52: 41188991154 | U52: 37011391337 | V52: =M52 -> 347066458180 | W52: =L52/J52 -> 0.86582466 | X52: =L52/M52 -> 6.4529342 | Y52: =U52/J52 -> 0.014308545 | Z52: =U52/M52 -> 0.10664065 | AA52: =(O52-P52)/O52 -> 0.29353972 | AB52: =U52/O52 -> 0.228288 | AC52: =AA52 -> 0.29353972 | AE52: 4598452704
A53: 58 | B53: 2018 | C53: BBKP | D53: Bank Bukopin Tbk | E53: 8.1 | F53: Sub Sektor Bank | H53: 7842551000000 | I53: 3075041000000 | J53: 95643923000000 | L53: 87049486000000 | M53: 8594437000000 | N53: 22887540178 | O53: 7980892000000 | P53: 5387749000000 | T53: 2759809000000 | U53: 189970000000 | V53: =M53 -> 8594437000000 | W53: =L53/J53 -> 0.91014132 | X53: =L53/M53 -> 10.128585 | Y53: =U53/J53 -> 0.0019862213 | Z53: =U53/M53 -> 0.022103833 | AA53: =(O53-P53)/O53 -> 0.32491894 | AB53: =U53/O53 -> 0.023803104 | AC53: =AA53 -> 0.32491894 | AE53: 36856000000 | AM53: 47404000000
A54: 59 | B54: 2019 | C54: BBKP | D54: Bank Bukopin Tbk | E54: 8.1 | F54: Sub Sektor Bank | H54: 9069393000000 | I54: 3012215000000 | J54: 100264248000000 | L54: 91358763000000 | M54: 8905485000000 | N54: 22887540178 | O54: 7764858000000 | P54: 5750319000000 | T54: 2801776000000 | U54: 216749000000 | V54: =M54 -> 8905485000000 | W54: =L54/J54 -> 0.91117986 | X54: =L54/M54 -> 10.258707 | Y54: =U54/J54 -> 0.0021617775 | Z54: =U54/M54 -> 0.02433882 | AA54: =(O54-P54)/O54 -> 0.25944312 | AB54: =U54/O54 -> 0.027914097 | AC54: =AA54 -> 0.25944312 | AE54: 58409000000 | AM54: 73707000000
A55: 60 | B55: 2020 | C55: BBKP | D55: Bank Bukopin Tbk | E55: 8.1 | F55: Sub Sektor Bank | H55: 6026015000000 | I55: 3504403000000 | J55: 79938578000000 | L55: 71472136000000 | M55: 8466442000000 | N55: 22887540178 | O55: 5308366000000 | P55: 4756310000000 | T55: 2758323000000 | U55: -3258109000000 | V55: =M55 -> 8466442000000 | W55: =L55/J55 -> 0.89408816 | X55: =L55/M55 -> 8.4418149 | Y55: =U55/J55 -> -0.040757655 | Z55: =U55/M55 -> -0.38482624 | AA55: =(O55-P55)/O55 -> 0.10399735 | AB55: =U55/O55 -> -0.61376872 | AC55: =AA55 -> 0.10399735 | AE55: 14229000000 | AM55: 64447000000
A56: 64 | B56: 2018 | C56: BBMD | D56: Bank Mestika Dharma Tbk | E56: 8.1 | F56: Sub Sektor Bank | H56: 2565738955362 | I56: 470415776572 | J56: 12093079368934 | L56: 9005066283473 | M56: 3088013085461 | N56: 10000000000 | O56: 1026137099056 | P56: 339167553637 | T56: 428776741954 | U56: 265862564725 | V56: =M56 -> 3088013085461 | W56: =L56/J56 -> 0.74464626 | X56: =L56/M56 -> 2.9161361 | Y56: =U56/J56 -> 0.021984687 | Z56: =U56/M56 -> 0.086095025 | AA56: =(O56-P56)/O56 -> 0.6694715 | AB56: =U56/O56 -> 0.25909069 | AC56: =AA56 -> 0.6694715 | AE56: 5400572519 | AM56: 16118815407
A57: 65 | B57: 2019 | C57: BBMD | D57: Bank Mestika Dharma Tbk | E57: 8.1 | F57: Sub Sektor Bank | H57: 3212723394393 | I57: 492662820097 | J57: 12900218775263 | L57: 9419749653807 | M57: 3480469121456 | N57: 10000000000 | O57: 1058536635511 | P57: 358086464478 | T57: 473384503657 | U57: 247573726183 | V57: =M57 -> 3480469121456 | W57: =L57/J57 -> 0.73020077 | X57: =L57/M57 -> 2.7064598 | Y57: =U57/J57 -> 0.019191436 | Z57: =U57/M57 -> 0.071132286 | AA57: =(O57-P57)/O57 -> 0.66171557 | AB57: =U57/O57 -> 0.233883 | AC57: =AA57 -> 0.66171557 | AE57: 9774888856 | AM57: 16870246688
A58: 66 | B58: 2020 | C58: BBMD | D58: Bank Mestika Dharma Tbk | E58: 8.1 | F58: Sub Sektor Bank | H58: 5804656337068 | I58: 479822488029 | J58: 14159755232533 | L58: 10150492606994 | M58: 4009262625539 | N58: 10000000000 | O58: 1122202992204 | P58: 326616871157 | T58: 534878138389 | U58: 325932118524 | V58: =M58 -> 4009262625539 | W58: =L58/J58 -> 0.71685509 | X58: =L58/M58 -> 2.5317605 | Y58: =U58/J58 -> 0.023018203 | Z58: =U58/M58 -> 0.081294779 | AA58: =(O58-P58)/O58 -> 0.70895028 | AB58: =U58/O58 -> 0.29043954 | AC58: =AA58 -> 0.70895028 | AE58: 7292696769 | AM58: 15957619609
A59: 67 | B59: 2018 | C59: BBNP | D59: Bank Nusantara Parahyangan Tbk | E59: 8.1 | F59: Sub Sektor Bank | V59: =M59 -> 0 | W59: =L59/J59 -> #DIV/0! | X59: =L59/M59 -> #DIV/0! | Y59: =U59/J59 -> #DIV/0! | Z59: =U59/M59 -> #DIV/0! | AA59: =(O59-P59)/O59 -> #DIV/0! | AB59: =U59/O59 -> #DIV/0! | AC59: =AA59 -> #DIV/0!
A60: 68 | B60: 2019 | C60: BBNP | D60: Bank Nusantara Parahyangan Tbk | E60: 8.1 | F60: Sub Sektor Bank | V60: =M60 -> 0 | W60: =L60/J60 -> #DIV/0! | X60: =L60/M60 -> #DIV/0! | Y60: =U60/J60 -> #DIV/0! | Z60: =U60/M60 -> #DIV/0! | AA60: =(O60-P60)/O60 -> #DIV/0! | AB60: =U60/O60 -> #DIV/0! | AC60: =AA60 -> #DIV/0!
A61: 69 | B61: 2020 | C61: BBNP | D61: Bank Nusantara Parahyangan Tbk | E61: 8.1 | F61: Sub Sektor Bank | V61: =M61 -> 0 | W61: =L61/J61 -> #DIV/0! | X61: =L61/M61 -> #DIV/0! | Y61: =U61/J61 -> #DIV/0! | Z61: =U61/M61 -> #DIV/0! | AA61: =(O61-P61)/O61 -> #DIV/0! | AB61: =U61/O61 -> #DIV/0! | AC61: =AA61 -> #DIV/0!
A62: 70 | B62: 2018 | C62: BBRI | D62: Bank Rakyat Indonesia (Persero) Tbk | E62: 8.1 | F62: Sub Sektor Bank | H62: 184284052000000 | I62: 26914859000000 | J62: 1.2968983e+15 | L62: 109066408400000 | M62: 185275331000000 | N62: 300000000000 | O62: 111582804000000 | P62: 33917032000000 | T62: 41990284000000 | U62: 32418486000000 | V62: =M62 -> 185275331000000 | W62: =L62/J62 -> 0.084097889 | X62: =L62/M62 -> 0.58867205 | Y62: =U62/J62 -> 0.024996938 | Z62: =U62/M62 -> 0.17497465 | AA62: =(O62-P62)/O62 -> 0.69603711 | AB62: =U62/O62 -> 0.29053299 | AC62: =AA62 -> 0.69603711 | AJ62: 54453000000 | AL62: 24105000000
A63: 71 | B63: 2019 | C63: BBRI | D63: Bank Rakyat Indonesia (Persero) Tbk | E63: 8.1 | F63: Sub Sektor Bank | H63: 195840173000000 | I63: 31432629000000 | J63: 1.4167588e+15 | L63: 1.1831557e+15 | M63: 208784336000000 | N63: 300000000000 | O63: 121756276000000 | P63: 38671838000000 | T63: =44965625000000+67880000000 -> 45033505000000 | U63: 34413825000000 | V63: =M63 -> 208784336000000 | W63: =L63/J63 -> 0.83511437 | X63: =L63/M63 -> 5.6668795 | Y63: =U63/J63 -> 0.024290531 | Z63: =U63/M63 -> 0.16482953 | AA63: =(O63-P63)/O63 -> 0.68238321 | AB63: =U63/O63 -> 0.28264518 | AC63: =AA63 -> 0.68238321 | AJ63: 41042000000 | AL63: 29715000000
A64: 72 | B64: 2020 | C64: BBRI | D64: Bank Rakyat Indonesia (Persero) Tbk | E64: 8.1 | F64: Sub Sektor Bank | H64: 327266714000000 | I64: 32185160000000 | J64: 1.5118046e+15 | L64: 1.2783463e+15 | M64: 199911376000000 | N64: 300000000000 | O64: 116932512000000 | P64: 37722595000000 | T64: =34413825000000+34413825000000 -> 68827650000000 | U64: 34413825000000 | V64: =M64 -> 199911376000000 | W64: =L64/J64 -> 0.84557637 | X64: =L64/M64 -> 6.3945649 | Y64: =U64/J64 -> 0.022763408 | Z64: =U64/M64 -> 0.17214541 | AA64: =(O64-P64)/O64 -> 0.67739858 | AB64: =U64/O64 -> 0.29430502 | AC64: =AA64 -> 0.67739858 | AJ64: 74721000000 | AL64: 23670000000
A65: 73 | B65: 2018 | C65: BBYB | D65: Bank Yudha Bhakti Tbk | E65: 8.1 | F65: Sub Sektor Bank | H65: 164023512477 | I65: 83206069558 | J65: 4533729146622 | L65: 3933343821678 | M65: 600385324944 | N65: 15000000000 | O65: 589663115314 | P65: 303322028671 | T65: =438306955535+1877841614 -> 440184797149 | U65: -136988450929 | V65: =M65 -> 600385324944 | W65: =L65/J65 -> 0.86757362 | X65: =L65/M65 -> 6.5513657 | Y65: =U65/J65 -> -0.030215402 | Z65: =U65/M65 -> -0.22816755 | AA65: =(O65-P65)/O65 -> 0.48560115 | AB65: =U65/O65 -> -0.23231647 | AC65: =AA65 -> 0.48560115 | AE65: 1596094962 | AI65: 3466686768 | AM65: 8818286340
A66: 74 | B66: 2019 | C66: BBYB | D66: Bank Yudha Bhakti Tbk | E66: 8.1 | F66: Sub Sektor Bank | H66: 188000346790 | I66: 87885955385 | J66: 5123734649117 | L66: 4177951053821 | M66: 945783595296 | N66: 15000000000 | O66: 532495206620 | P66: 316396580171 | T66: =378992065915+24798132920 -> 403790198835 | U66: 16002797471 | V66: =M66 -> 945783595296 | W66: =L66/J66 -> 0.81541128 | X66: =L66/M66 -> 4.4174493 | Y66: =U66/J66 -> 0.0031232682 | Z66: =U66/M66 -> 0.016920147 | AA66: =(O66-P66)/O66 -> 0.40582267 | AB66: =U66/O66 -> 0.030052472 | AC66: =AA66 -> 0.40582267 | AE66: 1992512078 | AI66: 3466686768 | AM66: 11608898381
A67: 75 | B67: 2020 | C67: BBYB | D67: Bank Yudha Bhakti Tbk | E67: 8.1 | F67: Sub Sektor Bank | H67: 253230368200 | I67: 108803796324 | J67: 5421324398438 | L67: 4300705118122 | M67: 1120619280316 | N67: 15000000000 | O67: 435200503846 | P67: 276969580433 | T67: 229554559339 | U67: 15871502695 | V67: =M67 -> 1120619280316 | W67: =L67/J67 -> 0.79329418 | X67: =L67/M67 -> 3.8377933 | Y67: =U67/J67 -> 0.0029276062 | Z67: =U67/M67 -> 0.014163153 | AA67: =(O67-P67)/O67 -> 0.36358166 | AB67: =U67/O67 -> 0.036469403 | AC67: =AA67 -> 0.36358166 | AE67: 1185683187 | AI67: 3466686768 | AM67: 9703855947
A68: 76 | B68: 2018 | C68: BCIC | D68: Bank J Trust Indonesia Tbk | E68: 8.1 | F68: Sub Sektor Bank | H68: 3562738000000 | I68: 194079000000 | J68: 17823669000000 | L68: 16508766000000 | M68: 1314903000000 | N68: 12384618000 | O68: 1426813000000 | P68: 1035272000000 | T68: =617930000000+116594000000 -> 734524000000 | U68: -401101000000 | V68: =M68 -> 1314903000000 | W68: =L68/J68 -> 0.92622714 | X68: =L68/M68 -> 12.555121 | Y68: =U68/J68 -> -0.02250384 | Z68: =U68/M68 -> -0.30504227 | AA68: =(O68-P68)/O68 -> 0.27441648 | AB68: =U68/O68 -> -0.28111673 | AC68: =AA68 -> 0.27441648 | AE68: =141049000000-81819000000 -> 59230000000 | AI68: 53952000000 | AJ68: 6957000000 | AL68: 8206000000 | AM68: =53527000000+ 13678000000 -> 67205000000
A69: 77 | B69: 2019 | C69: BCIC | D69: Bank J Trust Indonesia Tbk | E69: 8.1 | F69: Sub Sektor Bank | H69: 4219862000000 | I69: 199165000000 | J69: 17311597000000 | L69: 15637771000000 | M69: 1673826000000 | N69: 12384618000 | O69: 1132243000000 | P69: 1081987000000 | T69: =565244000000+178401000000 -> 743645000000 | U69: 49495000000 | V69: =M69 -> 1673826000000 | W69: =L69/J69 -> 0.90331187 | X69: =L69/M69 -> 9.3425308 | Y69: =U69/J69 -> 0.0028590661 | Z69: =U69/M69 -> 0.029569979 | AA69: =(O69-P69)/O69 -> 0.044386232 | AB69: =U69/O69 -> 0.043714114 | AC69: =AA69 -> 0.044386232 | AE69: =154689000000- 90046000000 -> 64643000000 | AI69: =60158000000-35942000000 -> 24216000000 | AJ69: 9610000000 | AL69: 2415000000 | AM69: =1272000000+ 9081000000 -> 10353000000
A70: 78 | B70: 2020 | C70: BCIC | D70: Bank J Trust Indonesia Tbk | E70: 8.1 | F70: Sub Sektor Bank | H70: 1915516000000 | I70: 194214000000 | J70: 16204908000000 | L70: 14761678000000 | M70: 1443230000000 | N70: 12384618000 | O70: 978794000000 | P70: 952657000000 | T70: =633588000000+29272000000 -> 662860000000 | U70: -484441000000 | V70: =M70 -> 1443230000000 | W70: =L70/J70 -> 0.91093871 | X70: =L70/M70 -> 10.228223 | Y70: =U70/J70 -> -0.029894708 | Z70: =U70/M70 -> -0.33566445 | AA70: =(O70-P70)/O70 -> 0.02670327 | AB70: =U70/O70 -> -0.49493663 | AC70: =AA70 -> 0.02670327 | AE70: =177324000000-101058000000 -> 76266000000 | AI70: =64558000000-41492000000 -> 23066000000 | AJ70: 6454000000 | AL70: 1271000000 | AM70: =5503000000+ 16402000000 -> 21905000000
A71: 82 | B71: 2018 | C71: BDMN | D71: Bank Danamon Indonesia Tbk | E71: 8.1 | F71: Sub Sektor Bank | H71: 9148760000000 | I71: 1902608000000 | J71: 186762189000000 | L71: 144822368000000 | M71: 41939821000000 | N71: 17782400000 | O71: 20172187000000 | P71: 5931103000000 | T71: =12779304000000+350113000000 -> 13129417000000 | U71: 4107068000000 | V71: =M71 -> 41939821000000 | W71: =L71/J71 -> 0.7754373 | X71: =L71/M71 -> 3.4530993 | Y71: =U71/J71 -> 0.021990897 | Z71: =U71/M71 -> 0.097927647 | AA71: =(O71-P71)/O71 -> 0.7059762 | AB71: =U71/O71 -> 0.20360053 | AC71: =AA71 -> 0.7059762 | AE71: =1832927000000-1319539000000 -> 513388000000 | AM71: 144766000000
A72: 83 | B72: 2019 | C72: BDMN | D72: Bank Danamon Indonesia Tbk | E72: 8.1 | F72: Sub Sektor Bank | H72: 9405926000000 | I72: 1785994000000 | J72: 193533970000000 | L72: 148116943000000 | M72: 45417027000000 | N72: 17782400000 | O72: 21970144000000 | P72: 7390746000000 | T72: =15092762000000+445759000000 -> 15538521000000 | U72: 4240671000000 | V72: =M72 -> 45417027000000 | W72: =L72/J72 -> 0.76532788 | X72: =L72/M72 -> 3.2612646 | Y72: =U72/J72 -> 0.021911766 | Z72: =U72/M72 -> 0.093371832 | AA72: =(O72-P72)/O72 -> 0.66360048 | AB72: =U72/O72 -> 0.19301972 | AC72: =AA72 -> 0.66360048 | AE72: =2029724000000-1495961000000 -> 533763000000 | AM72: 112501000000
A73: 84 | B73: 2020 | C73: BDMN | D73: Bank Danamon Indonesia Tbk | E73: 8.1 | F73: Sub Sektor Bank | H73: 4689271000000 | I73: 2105691000000 | J73: 200890068000000 | L73: 157314590000000 | M73: 43575499000000 | N73: 17782400000 | O73: 20087555000000 | P73: 6363892000000 | T73: =15644897000000+313611000000 -> 15958508000000 | U73: 1088942000000 | V73: =M73 -> 43575499000000 | W73: =L73/J73 -> 0.78308794 | X73: =L73/M73 -> 3.6101615 | Y73: =U73/J73 -> 0.0054205865 | Z73: =U73/M73 -> 0.024989777 | AA73: =(O73-P73)/O73 -> 0.6831923 | AB73: =U73/O73 -> 0.054209783 | AC73: =AA73 -> 0.6831923 | AE73: =2203093000000-1690956000000 -> 512137000000 | AM73: 106938000000
A74: 85 | B74: 2018 | C74: BEKS | D74: Bank Pembangunan Daerah Banten | E74: 8.1 | F74: Sub Sektor Bank | H74: 961960000000 | I74: 77068000000 | J74: 9482130000000 | L74: 8788732000000 | M74: 693398000000 | N74: 125693155976 | O74: 571662000000 | P74: 436252000000 | T74: 296067000000 | U74: -100131000000 | V74: =M74 -> 693398000000 | W74: =L74/J74 -> 0.92687318 | X74: =L74/M74 -> 12.674874 | Y74: =U74/J74 -> -0.010559969 | Z74: =U74/M74 -> -0.14440624 | AA74: =(O74-P74)/O74 -> 0.23687074 | AB74: =U74/O74 -> -0.1751577 | AC74: =AA74 -> 0.23687074 | AE74: 20311000000 | AI74: 649000000 | AM74: 9447000000
A75: 86 | B75: 2019 | C75: BEKS | D75: Bank Pembangunan Daerah Banten | E75: 8.1 | F75: Sub Sektor Bank | H75: 943031000000 | I75: 65551000000 | J75: 8097328000000 | L75: 7547795000000 | M75: 549533000000 | N75: 125693155976 | O75: 553871000000 | P75: 481024000000 | T75: 308662000000 | U75: -137559000000 | V75: =M75 -> 549533000000 | W75: =L75/J75 -> 0.93213403 | X75: =L75/M75 -> 13.734926 | Y75: =U75/J75 -> -0.016988197 | Z75: =U75/M75 -> -0.25031982 | AA75: =(O75-P75)/O75 -> 0.13152341 | AB75: =U75/O75 -> -0.24835927 | AC75: =AA75 -> 0.13152341 | AE75: 16215000000 | AI75: 983000000 | AM75: 6504000000
A76: 87 | B76: 2020 | C76: BEKS | D76: Bank Pembangunan Daerah Banten | E76: 8.1 | F76: Sub Sektor Bank | H76: 617099000000 | I76: 65323000000 | J76: 5337281000000 | L76: 3975700000000 | M76: 1361581000000 | N76: 125693155976 | O76: 372209000000 | P76: 338465000000 | T76: 294640000000 | U76: 308158000000 | V76: =M76 -> 1361581000000 | W76: =L76/J76 -> 0.74489239 | X76: =L76/M76 -> 2.9199144 | Y76: =U76/J76 -> 0.057736889 | Z76: =U76/M76 -> 0.22632366 | AA76: =(O76-P76)/O76 -> 0.090658743 | AB76: =U76/O76 -> 0.82791657 | AC76: =AA76 -> 0.090658743 | AE76: 16668000000 | AI76: 412000000 | AM76: 4173000000
A77: 94 | B77: 2018 | C77: BKSW | D77: Bank QNB Indonesia Tbk | E77: 8.1 | F77: Sub Sektor Bank | H77: =x!A28 -> 6759275000000 | I77: 119656000000 | J77: 20486926000000 | L77: 15814866000000 | M77: 4672060000000 | N77: 32000000000 | O77: 1353059000000 | P77: 1050216000000 | T77: 2149585000000 | U77: 14568000000 | V77: =M77 -> 4672060000000 | W77: =L77/J77 -> 0.77194919 | X77: =L77/M77 -> 3.3849878 | Y77: =U77/J77 -> 0.00071108765 | Z77: =U77/M77 -> 0.0031181106 | AA77: =(O77-P77)/O77 -> 0.22382099 | AB77: =U77/O77 -> 0.010766715 | AC77: =AA77 -> 0.22382099 | AE77: =51005000000-31823000000 -> 19182000000 | AI77: =34767000000-19835000000 -> 14932000000 | AM77: 5393000000
A78: 95 | B78: 2019 | C78: BKSW | D78: Bank QNB Indonesia Tbk | E78: 8.1 | F78: Sub Sektor Bank | H78: =x!B28 -> 3642725000000 | I78: 138903000000 | J78: 23021785000000 | L78: 18332221000000 | M78: 4689564000000 | N78: 32000000000 | O78: 1401513000000 | P78: 979937000000 | T78: 594032000000 | U78: 5277000000 | V78: =M78 -> 4689564000000 | W78: =L78/J78 -> 0.79629885 | X78: =L78/M78 -> 3.9091525 | Y78: =U78/J78 -> 0.00022921767 | Z78: =U78/M78 -> 0.0011252645 | AA78: =(O78-P78)/O78 -> 0.30080063 | AB78: =U78/O78 -> 0.0037652166 | AC78: =AA78 -> 0.30080063 | AE78: =55534000000-37692000000 -> 17842000000 | AI78: =36350000000-24182000000 -> 12168000000 | AM78: 2457000000
A79: 96 | B79: 2020 | C79: BKSW | D79: Bank QNB Indonesia Tbk | E79: 8.1 | F79: Sub Sektor Bank | H79: 1286995000000 | I79: 365906000000 | J79: 18297700000000 | L79: 14185258000000 | M79: 4112442000000 | N79: 32000000000 | O79: 1233605000000 | P79: 971493000000 | T79: 663981000000 | U79: -422168000000 | V79: =M79 -> 4112442000000 | W79: =L79/J79 -> 0.77524815 | X79: =L79/M79 -> 3.4493515 | Y79: =U79/J79 -> -0.023072189 | Z79: =U79/M79 -> -0.10265628 | AA79: =(O79-P79)/O79 -> 0.21247644 | AB79: =U79/O79 -> -0.342223 | AC79: =AA79 -> 0.21247644 | AE79: =69870000000-43956000000 -> 25914000000 | AI79: =37106000000-28496000000 -> 8610000000 | AM79: 1704000000
A80: 97 | B80: 2018 | C80: BMAS | D80: Bank Maspion Indonesia Tbk | E80: 8.1 | F80: Sub Sektor Bank | I80: 439337143000 | J80: 6694023677000 | L80: 5493283082000 | M80: 1200740595000 | N80: 12000000000 | O80: 511186044000 | P80: 276263254000 | T80: 196095958000 | U80: 71013866000 | V80: =M80 -> 1200740595000 | W80: =L80/J80 -> 0.82062499 | X80: =L80/M80 -> 4.5749124 | Y80: =U80/J80 -> 0.010608547 | Z80: =U80/M80 -> 0.059141722 | AA80: =(O80-P80)/O80 -> 0.45956417 | AB80: =U80/O80 -> 0.13891981 | AC80: =AA80 -> 0.45956417 | AE80: 3506116000 | AK80: 1391686000 | AM80: 1790198000
A81: 98 | B81: 2019 | C81: BMAS | D81: Bank Maspion Indonesia Tbk | E81: 8.1 | F81: Sub Sektor Bank | H81: 187893655000 | I81: 438379326000 | J81: 7569580138000 | L81: 6340648554000 | M81: 1228931584000 | N81: 12000000000 | O81: 595200789000 | P81: 354239522000 | T81: =195369022000+1826745000 -> 197195767000 | U81: 59746814000 | V81: =M81 -> 1228931584000 | W81: =L81/J81 -> 0.83764865 | X81: =L81/M81 -> 5.1594805 | Y81: =U81/J81 -> 0.0078930156 | Z81: =U81/M81 -> 0.048616876 | AA81: =(O81-P81)/O81 -> 0.4048403 | AB81: =U81/O81 -> 0.10038094 | AC81: =AA81 -> 0.4048403 | AE81: 3133254000 | AK81: 2464524000 | AM81: 2448358000
A82: 99 | B82: 2020 | C82: BMAS | D82: Bank Maspion Indonesia Tbk | E82: 8.1 | F82: Sub Sektor Bank | H82: 715192869000 | I82: 433371108000 | J82: 10110519691000 | L82: 8826257598000 | M82: 1284262093000 | N82: 12000000000 | O82: 630419914000 | P82: 401285815000 | T82: 209895189000 | U82: 66986471000 | V82: =M82 -> 1284262093000 | W82: =L82/J82 -> 0.87297764 | X82: =L82/M82 -> 6.8726295 | Y82: =U82/J82 -> 0.0066254231 | Z82: =U82/M82 -> 0.052159502 | AA82: =(O82-P82)/O82 -> 0.36346266 | AB82: =U82/O82 -> 0.10625691 | AC82: =AA82 -> 0.36346266 | AE82: 4271415000 | AK82: 2645095000 | AM82: 2315867000
A83: 100 | B83: 2018 | C83: BMRI | D83: Bank Mandiri (Persero) Tbk | E83: 8.1 | F83: Sub Sektor Bank | H83: 63835900000000 | I83: 38442696000000 | J83: 1.2022521e+15 | L83: 941953100000000 | M83: 184960305000000 | N83: =31999999999+1 -> 32000000000 | O83: =x!A35 -> 91335057000000 | P83: =x!B35 -> 34005292000000 | T83: 37566139000000 | U83: 25851937000000 | V83: =M83 -> 184960305000000 | W83: =L83/J83 -> 0.7834905 | X83: =L83/M83 -> 5.0927311 | Y83: =U83/J83 -> 0.021502925 | Z83: =U83/M83 -> 0.13977019 | AA83: =(O83-P83)/O83 -> 0.62768631 | AB83: =U83/O83 -> 0.28304506 | AC83: =AA83 -> 0.62768631 | AE83: 2341611000000 | AM83: 1055052000000
A84: 101 | B84: 2019 | C84: BMRI | D84: Bank Mandiri (Persero) Tbk | E84: 8.1 | F84: Sub Sektor Bank | H84: 71263368000000 | I84: 44612199000000 | J84: 1.3182463e+15 | L84: 1.0257496e+15 | M84: 209034525000000 | N84: =63999999999+1 -> 64000000000 | O84: =x!A40 -> 102638740000000 | P84: =x!B40 -> 41391049000000 | T84: =40076167000000+10074000000 -> 40086241000000 | U84: 28455592000000 | V84: =M84 -> 209034525000000 | W84: =L84/J84 -> 0.77811677 | X84: =L84/M84 -> 4.9070821 | Y84: =U84/J84 -> 0.021585944 | Z84: =U84/M84 -> 0.13612867 | AA84: =(O84-P84)/O84 -> 0.59673074 | AB84: =U84/O84 -> 0.27724027 | AC84: =AA84 -> 0.59673074 | AE84: 2898169000000 | AM84: 1135295000000
A85: 102 | B85: 2020 | C85: BMRI | D85: Bank Mandiri (Persero) Tbk | E85: 8.1 | F85: Sub Sektor Bank | H85: 79900770000000 | I85: 46728153000000 | J85: 1.4293345e+15 | L85: 1.1512678e+15 | M85: 193796083000000 | N85: =63999999999+1 -> 64000000000 | O85: =x!A45 -> 100211477000000 | P85: =x!B45 -> 42189633000000 | T85: 40646791000000 | U85: 17645624000000 | V85: =M85 -> 193796083000000 | W85: =L85/J85 -> 0.80545727 | X85: =L85/M85 -> 5.9406146 | Y85: =U85/J85 -> 0.012345343 | Z85: =U85/M85 -> 0.091052532 | AA85: =(O85-P85)/O85 -> 0.578994 | AB85: =U85/O85 -> 0.17608386 | AC85: =AA85 -> 0.578994 | AE85: 3673819000000 | AM85: 1302175000000
A86: 103 | B86: 2018 | C86: BNBA | D86: Bank Bumi Arta Tbk | E86: 8.1 | F86: Sub Sektor Bank | H86: 386881958251 | I86: 788081883230 | J86: 7297273467260 | L86: 5802518829966 | M86: 1494754637294 | N86: 8000000000 | O86: 645259846041 | P86: 311140279900 | T86: 244105811984 | U86: 92897864488 | V86: =M86 -> 1494754637294 | W86: =L86/J86 -> 0.79516258 | X86: =L86/M86 -> 3.8819206 | Y86: =U86/J86 -> 0.01273049 | Z86: =U86/M86 -> 0.06214924 | AA86: =(O86-P86)/O86 -> 0.51780623 | AB86: =U86/O86 -> 0.1439697 | AC86: =AA86 -> 0.51780623 | AE86: 2346057885
A87: 104 | B87: 2019 | C87: BNBA | D87: Bank Bumi Arta Tbk | E87: 8.1 | F87: Sub Sektor Bank | H87: 246243822177 | I87: 790755582369 | J87: 7607653715376 | L87: 6083998151873 | M87: 1523655563503 | N87: 8000000000 | O87: 653036862635 | P87: 345037801425 | T87: 253248805324 | U87: 51167901115 | V87: =M87 -> 1523655563503 | W87: =L87/J87 -> 0.7997207 | X87: =L87/M87 -> 3.9930272 | Y87: =U87/J87 -> 0.0067258452 | Z87: =U87/M87 -> 0.033582328 | AA87: =(O87-P87)/O87 -> 0.47164116 | AB87: =U87/O87 -> 0.078353771 | AC87: =AA87 -> 0.47164116 | AE87: 4574210831
A88: 105 | B88: 2020 | C88: BNBA | D88: Bank Bumi Arta Tbk | E88: 8.1 | F88: Sub Sektor Bank | H88: 122215074540 | I88: 815641804959 | J88: 7637524325854 | L88: 6128138202911 | M88: 1509386122943 | N88: 8000000000 | O88: 633832905528 | P88: 346829023353 | T88: 247615102198 | U88: 35053333152 | V88: =M88 -> 1509386122943 | W88: =L88/J88 -> 0.80237233 | X88: =L88/M88 -> 4.0600202 | Y88: =U88/J88 -> 0.0045896198 | Z88: =U88/M88 -> 0.023223569 | AA88: =(O88-P88)/O88 -> 0.45280685 | AB88: =U88/O88 -> 0.055303745 | AC88: =AA88 -> 0.45280685 | AE88: 6652236482
A89: 109 | B89: 2018 | C89: BNGA | D89: Bank CIMB Niaga Tbk | E89: 8.1 | F89: Sub Sektor Bank | H89: 3659000000 | I89: 5453282000000 | J89: 266781498000000 | L89: 227200919000000 | M89: 39580579000000 | N89: =71853936+50814606400 -> 50886460336 | O89: =18346593000000+1946654000000 -> 20293247000000 | P89: =7256236000000+1025280000000 -> 8281516000000 | T89: 8004128000000 | U89: 3482428000000 | V89: =M89 -> 39580579000000 | W89: =L89/J89 -> 0.85163672 | X89: =L89/M89 -> 5.7402121 | Y89: =U89/J89 -> 0.013053484 | Z89: =U89/M89 -> 0.087983251 | AA89: =(O89-P89)/O89 -> 0.59190779 | AB89: =U89/O89 -> 0.17160526 | AC89: =AA89 -> 0.59190779 | AE89: 1596278000000 | AK89: 37470000000 | AM89: 292391000000
A90: 110 | B90: 2019 | C90: BNGA | D90: Bank CIMB Niaga Tbk | E90: 8.1 | F90: Sub Sektor Bank | H90: 3659000000 | I90: 6248281000000 | J90: 274467227000000 | L90: 231173061000000 | M90: 43294166000000 | N90: =71853936+50814606400 -> 50886460336 | O90: =18396236000000+3293250000000 -> 21689486000000 | P90: =7050137000000+2071331000000 -> 9121468000000 | T90: 8634364000000 | U90: 3642935000000 | V90: =M90 -> 43294166000000 | W90: =L90/J90 -> 0.84226107 | X90: =L90/M90 -> 5.3395892 | Y90: =U90/J90 -> 0.01327275 | Z90: =U90/M90 -> 0.084143785 | AA90: =(O90-P90)/O90 -> 0.57945209 | AB90: =U90/O90 -> 0.16795857 | AC90: =AA90 -> 0.57945209 | AE90: 1704049000000 | AK90: 277702000000 | AM90: 313837000000
A91: 111 | B91: 2020 | C91: BNGA | D91: Bank CIMB Niaga Tbk | E91: 8.1 | F91: Sub Sektor Bank | H91: 3659000000 | I91: 6989721000000 | J91: 280943605000000 | L91: 239890554000000 | M91: 41053051000000 | N91: =71853936+50814606400 -> 50886460336 | O91: =17248452000000+3454647000000 -> 20703099000000 | P91: =6212158000000+2020423000000 -> 8232581000000 | T91: 8100784000000 | U91: 2011254000000 | V91: =M91 -> 41053051000000 | W91: =L91/J91 -> 0.85387441 | X91: =L91/M91 -> 5.8434282 | Y91: =U91/J91 -> 0.0071589243 | Z91: =U91/M91 -> 0.048991584 | AA91: =(O91-P91)/O91 -> 0.60235031 | AB91: =U91/O91 -> 0.097147485 | AC91: =AA91 -> 0.60235031 | AE91: 1765210000000 | AK91: 163362000000 | AM91: 234239000000
A92: 112 | B92: 2018 | C92: BNII | D92: Bank Maybank Indonesia Tbk | E92: 8.1 | F92: Sub Sektor Bank | H92: 16539984000000 | I92: 2926594000000 | J92: 177532858000000 | L92: 152442167000000 | M92: 25090691000000 | N92: 476608857231 | O92: 14790035000000 | P92: 6690157000000 | T92: 7333658000000 | U92: 2262245000000 | V92: =M92 -> 25090691000000 | W92: =L92/J92 -> 0.85867016 | X92: =L92/M92 -> 6.0756464 | Y92: =U92/J92 -> 0.012742683 | Z92: =U92/M92 -> 0.090162722 | AA92: =(O92-P92)/O92 -> 0.5476578 | AB92: =U92/O92 -> 0.15295738 | AC92: =AA92 -> 0.5476578 | AE92: 179213000000 | AL92: 89552000000 | AM92: 150251000000
A93: 113 | B93: 2019 | C93: BNII | D93: Bank Maybank Indonesia Tbk | E93: 8.1 | F93: Sub Sektor Bank | H93: 16509217000000 | I93: 2927444000000 | J93: 169082830000000 | L93: 142397914000000 | M93: 26684916000000 | N93: 476608857231 | O93: 15479869000000 | P93: 7311894000000 | T93: 8178275000000 | U93: 1924180000000 | V93: =M93 -> 26684916000000 | W93: =L93/J93 -> 0.84217844 | X93: =L93/M93 -> 5.3362699 | Y93: =U93/J93 -> 0.011380103 | Z93: =U93/M93 -> 0.072107403 | AA93: =(O93-P93)/O93 -> 0.52765143 | AB93: =U93/O93 -> 0.12430209 | AC93: =AA93 -> 0.52765143 | AE93: 221972000000 | AL93: 101182000000 | AM93: 101998000000
A94: 114 | B94: 2020 | C94: BNII | D94: Bank Maybank Indonesia Tbk | E94: 8.1 | F94: Sub Sektor Bank | H94: 24266764000000 | I94: 3479263000000 | J94: 173224412000000 | L94: 146000782000000 | M94: 27223630000000 | N94: 476608857231 | O94: 12826683000000 | P94: 5566873000000 | T94: 7793430000000 | U94: 1254392000000 | V94: =M94 -> 27223630000000 | W94: =L94/J94 -> 0.84284184 | X94: =L94/M94 -> 5.3630167 | Y94: =U94/J94 -> 0.0072414274 | Z94: =U94/M94 -> 0.046077323 | AA94: =(O94-P94)/O94 -> 0.56599278 | AB94: =U94/O94 -> 0.09779551 | AC94: =AA94 -> 0.56599278 | AE94: 205574000000 | AL94: 45675000000 | AM94: 71913000000
A95: 115 | B95: 2018 | C95: BNLI | D95: Bank Permata Tbk | E95: 8.1 | F95: Sub Sektor Bank | H95: 14989712000000 | I95: 2552305000000 | J95: 152892866000000 | L95: 130440930000000 | M95: 22451936000000 | N95: =26880234+97311976600 -> 97338856834 | O95: =9419839000000+1661113000000 -> 11080952000000 | P95: =5026890000000+653877000000 -> 5680767000000 | T95: 4465833000000 | U95: 901252000000 | V95: =M95 -> 22451936000000 | W95: =L95/J95 -> 0.85315249 | X95: =L95/M95 -> 5.8097854 | Y95: =U95/J95 -> 0.0058946635 | Z95: =U95/M95 -> 0.040141394 | AA95: =(O95-P95)/O95 -> 0.48733945 | AB95: =U95/O95 -> 0.081333445 | AC95: =AA95 -> 0.48733945 | AE95: =434246000000-270338000000 -> 163908000000 | AK95: 193473000000 | AM95: 181236000000
A96: 116 | B96: 2019 | C96: BNLI | D96: Bank Permata Tbk | E96: 8.1 | F96: Sub Sektor Bank | H96: 16229868000000 | I96: 2451459000000 | J96: 161451259000000 | L96: 137413908000000 | M96: 24037351000000 | N96: =26880234+97311976600 -> 97338856834 | O96: =10114747000000+1627316000000 -> 11742063000000 | P96: =5372123000000+648972000000 -> 6021095000000 | T96: 4737632000000 | U96: 1500420000000 | V96: =M96 -> 24037351000000 | W96: =L96/J96 -> 0.85111698 | X96: =L96/M96 -> 5.7166827 | Y96: =U96/J96 -> 0.0092933311 | Z96: =U96/M96 -> 0.062420356 | AA96: =(O96-P96)/O96 -> 0.48722001 | AB96: =U96/O96 -> 0.12778163 | AC96: =AA96 -> 0.48722001 | AE96: =450908000000-236552000000 -> 214356000000 | AK96: 226768000000 | AM96: 187094000000
A97: 117 | B97: 2020 | C97: BNLI | D97: Bank Permata Tbk | E97: 8.1 | F97: Sub Sektor Bank | H97: 23256980000000 | I97: 3073596000000 | J97: 197726097000000 | L97: 162654644000000 | M97: 35071453000000 | N97: =117311976600+26880234 -> 117338856834 | O97: =10450915000000+1472863000000 -> 11923778000000 | P97: =4678378000000+613610000000 -> 5291988000000 | T97: 5076563000000 | U97: 721587000000 | V97: =M97 -> 35071453000000 | W97: =L97/J97 -> 0.82262608 | X97: =L97/M97 -> 4.6378074 | Y97: =U97/J97 -> 0.0036494272 | Z97: =U97/M97 -> 0.020574768 | AA97: =(O97-P97)/O97 -> 0.55618194 | AB97: =U97/O97 -> 0.060516642 | AC97: =AA97 -> 0.55618194 | AE97: =415497000000-191249000000 -> 224248000000 | AK97: 203936000000 | AM97: 120228000000
A98: 124 | B98: 2018 | C98: BSIM | D98: Bank Sinarmas Tbk | E98: 8.1 | F98: Sub Sektor Bank | H98: 2882064000000 | I98: 1211744000000 | J98: 30748742000000 | L98: 23532846000000 | M98: 4856420000000 | N98: 60000000000 | O98: =2604754000000+480765000000 -> 3085519000000 | P98: =763373000000+156204000000 -> 919577000000 | T98: 781734000000 | U98: 50472000000 | V98: =M98 -> 4856420000000 | W98: =L98/J98 -> 0.76532711 | X98: =L98/M98 -> 4.8457189 | Y98: =U98/J98 -> 0.001641433 | Z98: =U98/M98 -> 0.010392841 | AA98: =(O98-P98)/O98 -> 0.70197007 | AB98: =U98/O98 -> 0.016357702 | AC98: =AA98 -> 0.70197007 | AL98: 13140000000 | AM98: 40893000000
A99: 125 | B99: 2019 | C99: BSIM | D99: Bank Sinarmas Tbk | E99: 8.1 | F99: Sub Sektor Bank | H99: 5584294000000 | I99: 1399242000000 | J99: 36559556000000 | L99: 26385919000000 | M99: 6074463000000 | N99: 60000000000 | O99: =2781204000000+579656000000 -> 3360860000000 | P99: =967014000000+183343000000 -> 1150357000000 | T99: 987162000000 | U99: 6752000000 | V99: =M99 -> 6074463000000 | W99: =L99/J99 -> 0.72172427 | X99: =L99/M99 -> 4.3437451 | Y99: =U99/J99 -> 0.00018468496 | Z99: =U99/M99 -> 0.0011115386 | AA99: =(O99-P99)/O99 -> 0.65771945 | AB99: =U99/O99 -> 0.0020090096 | AC99: =AA99 -> 0.65771945 | AM99: 38942000000
A100: 126 | B100: 2020 | C100: BSIM | D100: Bank Sinarmas Tbk | E100: 8.1 | F100: Sub Sektor Bank | H100: 9183303000000 | I100: 1584298000000 | J100: 44612045000000 | L100: 32557921000000 | M100: 6056844000000 | N100: 60000000000 | O100: =2632465000000+667796000000 -> 3300261000000 | P100: =905187000000+206870000000 -> 1112057000000 | T100: 1201125000000 | U100: 118522000000 | V100: =M100 -> 6056844000000 | W100: =L100/J100 -> 0.72980113 | X100: =L100/M100 -> 5.3753937 | Y100: =U100/J100 -> 0.0026567265 | Z100: =U100/M100 -> 0.019568277 | AA100: =(O100-P100)/O100 -> 0.66303968 | AB100: =U100/O100 -> 0.035912917 | AC100: =AA100 -> 0.66303968 | AM100: 46351000000
...

Sheet x
A2: Asuransi Bintang
A3: 100577266 | B3: 100874830 | C3: 114544426
A4: 618749 | B4: 437959 | C4: 450363
A5: 21646177 | B5: 23284126 | C5: 29624898
A6: 1528415 | B6: 1483648 | C6: 1664714
A7: 56925260 | B7: 55928711 | C7: 54076685
A8: 6729951 | B8: 6080793 | C8: 5486436
A9: 15450006 | B9: 16600424 | C9: 16490088
A10: 101219947 | B10: 67291213 | C10: 68072520
A11: 96500 | B11: 76200 | C11: 66700
A12: =SUM(A3:A11) -> 304792271 | B12: =SUM(B3:B11) -> 272057904 | C12: =SUM(C3:C11) -> 290476830
A14: Asuransi Ramayana
A16: 211605200000 | B16: 192475119000 | C16: 181937996190
A17: 4445786600 | B17: 3794412480 | C17: 4113860200
A18: 103519000000 | B18: 108236723800 | C18: 111934083010
A19: 50000000000 | B19: 50000000000 | C19: 50000000000
A20: 23582160000 | B20: 21982190044 | C20: 23833902641
A21: 9978743001 | B21: 8413067469 | C21: 7143462511
A22: 2039200000 | B22: 2039200000 | C22: 2039200000
A23: =SUM(A16:A22) -> 405170089601 | B23: =SUM(B16:B22) -> 386940712793 | C23: =SUM(C16:C22) -> 381002504552
A25: BANK QNB
A26: 3426305000000 | B26: 2653527000000
A27: 3332970000000 | B27: 989198000000
A28: =SUM(A26:A27) -> 6759275000000 | B28: =SUM(B26:B27) -> 3642725000000 | C28: =SUM(C26) -> 0
A30: BANK MANDIRI
A31: pendapatan | B31: beban
A32: 74454382000000 | B32: 23710628000000
A33: 6538188000000 | B33: 2659310000000
A34: 10342487000000 | B34: 7635354000000
A35: =SUM(A32,A33,A34) -> 91335057000000 | B35: =SUM(B34,B33,B32) -> 34005292000000
A37: 84431175000000 | B37: 29070226000000
A38: 7093915000000 | B38: 3014676000000
A39: 11113650000000 | B39: 9306147000000
A40: =SUM(A39,A38,A37) -> 102638740000000 | B40: =SUM(B39,B38,B37) -> 41391049000000
A42: 80093037000000 | B42: 28222605000000
A43: 7228080000000 | B43: 2590383000000
A44: 12890360000000 | B44: 11376645000000
A45: =SUM(A44,A43,A42) -> 100211477000000 | B45: =SUM(B44,B43,B42) -> 42189633000000
A47: BAKRIE
A48: 389948000000
A49: 263067000000
A50: =SUM(A49,A48) -> 653015000000
A52: 10000000000
A53: 263067000000
A54: =SUM(A53,A52) -> 273067000000
A56: 10000000000
A57: 992718000000
A58: =SUM(A57,A56) -> 1002718000000
A60: KREN
A61: 50618272000 | B61: 47340365600 | C61: 32058273564
A62: 1058515254376 | B62: 1231750009584 | C62: 622077010518
A63: 622145108829 | B63: 731541758548 | C63: 737155177576
A64: =SUM(A61:A63) -> 1731278635205 | B64: =SUM(B61:B63) -> 2010632133732 | C64: =SUM(C61:C63) -> 1391290461658
A66: LPKR
A67: 4700208 | B67: 4491322 | C67: 2097325
B68: 3239387 | C68: 1991078
A69: 145985
A70: =SUM(A67:A69) -> 4846193 | B70: =SUM(B67:B69) -> 7730709 | C70: =SUM(C67:C69) -> 4088403
A72: LPPS
A73: 2414841846 | B73: 2860228288 | C73: 60000000
A74: 12138603 | B74: 4697728
A75: -3823855541 | B75: -5019110393
A76: -502177303 | B76: -1252816478
A77: 882715528
A78: =A73+A74+A77 -> 3309695977 | B78: =B73+B74+B77 -> 2864926016 | C78: =SUM(C73:C77) -> 60000000
A79: =SUM(A75:A76) -> -4326032844 | B79: =SUM(B75:B76) -> -6271926871 | C79: =SUM(C75:C76) -> 0

Sheet banking-financial
A1: Tahun | B1: Kode | C1: Emiten | D1: Current Assets | E1: Fixed Assets | F1: Total Assets | G1: Current Liabilities | H1: Long-term Liabilities | I1: Total Liabilities | J1: Total Equity | K1: Outstanding shares | L1: Total Sales/Revenue | M1: COGS/COR | N1: Expenses | O1: Net Income | P1: Dividend | Q1: Price | R1: CR | S1: DER | T1: ROA | U1: ROE | V1: NPM | W1: DY | X1: DPR | Y1: PER | Z1: PBV | AA1: Industri
A2: 2018 | B2: ASBI | C2: Asuransi Bintang Tbk | D2: 673579165000 | E2: 123308301000 | F2: 874472888000 | I2: 593110979000 | J2: 281361909000 | K2: 640000000 | L2: 264899142000 | M2: 124758053000 | N2: 3501669000 | O2: 3274307000 | P2: 3658165000 | Q2: 250 | R2: =D2/I2 -> 1.1356714 | S2: =I2/J2 -> 2.1080003 | T2: =O2/F2 -> 0.0037443208 | U2: =O2/J2 -> 0.01163735 | V2: =O2/L2 -> 0.01236058 | W2: =(P2/K2)/Q2 -> 0.022863531 | X2: =P2/O2 -> 1.1172334 | Y2: =Q2/(O2/K2) -> 48.865302 | Z2: =Q2/(J2/K2) -> 0.56866262 | AA2: 1
A3: 2019 | B3: ASBI | C3: Asuransi Bintang Tbk | D3: 653613149000 | E3: 127895603000 | F3: 857520585000 | I3: 566035087000 | J3: 291351494000 | K3: 640000000 | L3: 250804486000 | M3: 134257087000 | N3: 1102516000 | O3: 3581215000 | P3: 3516989000 | Q3: 308 | R3: =D3/I3 -> 1.154722 | S3: =I3/J3 -> 1.9427911 | T3: =O3/F3 -> 0.0041762438 | U3: =O3/J3 -> 0.012291734 | V3: =O3/L3 -> 0.014278911 | W3: =(P3/K3)/Q3 -> 0.017841868 | X3: =P3/O3 -> 0.98206586 | Y3: =Q3/(O3/K3) -> 55.042772 | Z3: =Q3/(J3/K3) -> 0.6765711 | AA3: 1
A4: 2020 | B4: ASBI | C4: Asuransi Bintang Tbk | D4: 632468200000 | E4: 125064327000 | F4: 871769183000 | I4: 557997452000 | J4: 313771731000 | K4: 640000000 | L4: 231470118000 | M4: 109895092000 | N4: 1205232000 | O4: 10456654000 | P4: 2091802000 | Q4: 310 | R4: =D4/I4 -> 1.1334607 | S4: =I4/J4 -> 1.7783548 | T4: =O4/F4 -> 0.011994751 | U4: =O4/J4 -> 0.033325673 | V4: =O4/L4 -> 0.045174963 | W4: =(P4/K4)/Q4 -> 0.010543357 | X4: =P4/O4 -> 0.20004506 | Y4: =Q4/(O4/K4) -> 18.973565 | Z4: =Q4/(J4/K4) -> 0.6323068 | AA4: 1
A5: 2018 | B5: ASMI | C5: Asuransi Kresna Mitra Tbk | D5: 920102856747 | E5: 21609167523 | F5: 969866560976 | I5: 450272263738 | J5: 519594297238 | K5: 25000000000 | L5: 135633770098 | M5: 68591523905 | N5: 76025853817 | O5: 71761034881 | Q5: 700 | R5: =D5/I5 -> 2.0434367 | S5: =I5/J5 -> 0.86658431 | T5: =O5/F5 -> 0.073990627 | U5: =O5/J5 -> 0.13810974 | V5: =O5/L5 -> 0.52907941 | W5: =(P5/K5)/Q5 -> 0 | X5: =P5/O5 -> 0 | Y5: =Q5/(O5/K5) -> 243.86493 | Z5: =Q5/(J5/K5) -> 33.680123 | AA5: 1
A6: 2019 | B6: ASMI | C6: Asuransi Kresna Mitra Tbk | D6: 922123474882 | E6: 24621076327 | F6: 975687462693 | I6: 445392630259 | J6: 530294832434 | K6: 25000000000 | L6: 175174507884 | M6: 101954815930 | N6: 72793612247 | O6: 8260755476 | Q6: 1285 | R6: =D6/I6 -> 2.0703609 | S6: =I6/J6 -> 0.83989623 | T6: =O6/F6 -> 0.0084666 | U6: =O6/J6 -> 0.015577665 | V6: =O6/L6 -> 0.047157292 | W6: =(P6/K6)/Q6 -> 0 | X6: =P6/O6 -> 0 | Y6: =Q6/(O6/K6) -> 3888.8695 | Z6: =Q6/(J6/K6) -> 60.579508 | AA6: 1
A7: 2020 | B7: ASMI | C7: Asuransi Kresna Mitra Tbk | D7: 924782474882 | E7: 23989286699 | F7: 990991744064 | I7: 547541424689 | J7: 443450319375 | K7: 25000000000 | L7: 185567699856 | M7: 179184782942 | N7: 91760615438 | O7: -88526593736 | Q7: 990 | R7: =D7/I7 -> 1.6889726 | S7: =I7/J7 -> 1.23473 | T7: =O7/F7 -> -0.089331313 | U7: =O7/J7 -> -0.19963137 | V7: =O7/L7 -> -0.4770582 | W7: =(P7/K7)/Q7 -> 0 | X7: =P7/O7 -> 0 | Y7: =Q7/(O7/K7) -> -279.57701 | Z7: =Q7/(J7/K7) -> 55.81234 | AA7: 1
A8: 2018 | B8: ASRM | C8: Asuransi Ramayana Tbk | D8: 1210842541630 | E8: 59951428986 | F8: 1478007061719 | I8: 1072221723281 | J8: 405785338438 | K8: 420000000 | L8: 902165344517 | M8: 590399043504 | N8: 31849926816 | O8: 3573526494 | P8: 21297309695 | Q8: 2350 | R8: =D8/I8 -> 1.1292837 | S8: =I8/J8 -> 2.6423373 | T8: =O8/F8 -> 0.0024178007 | U8: =O8/J8 -> 0.0088064456 | V8: =O8/L8 -> 0.0039610549 | W8: =(P8/K8)/Q8 -> 0.021577821 | X8: =P8/O8 -> 5.9597459 | Y8: =Q8/(O8/K8) -> 276.19776 | Z8: =Q8/(J8/K8) -> 2.4323205 | AA8: 1
A9: 2019 | B9: ASRM | C9: Asuransi Ramayana Tbk | D9: 1254061746961 | E9: 67512713635 | F9: 1548001829554 | I9: 1104712550189 | J9: 443289279365 | K9: 420000000 | L9: 1177500392010 | M9: 842624761795 | N9: 40486294000 | O9: 2089220151 | P9: 18237550870 | Q9: 2010 | R9: =D9/I9 -> 1.1351928 | S9: =I9/J9 -> 2.4920805 | T9: =O9/F9 -> 0.0013496238 | U9: =O9/J9 -> 0.004712995 | V9: =O9/L9 -> 0.001774284 | W9: =(P9/K9)/Q9 -> 0.021603353 | X9: =P9/O9 -> 8.7293581 | Y9: =Q9/(O9/K9) -> 404.07422 | Z9: =Q9/(J9/K9) -> 1.9043998 | AA9: 1
A10: 2020 | B10: ASRM | C10: Asuransi Ramayana Tbk | D10: 1213949686630 | E10: 65757265183 | F10: 1516562973028 | I10: 1013381758085 | J10: 503181214943 | K10: 420000000 | L10: 1323139975825 | M10: 1014017867183 | N10: 25818453029 | O10: 16434884891 | P10: 16272822539 | Q10: 1680 | R10: =D10/I10 -> 1.1979194 | S10: =I10/J10 -> 2.0139499 | T10: =O10/F10 -> 0.010836929 | U10: =O10/J10 -> 0.03266196 | V10: =O10/L10 -> 0.012421123 | W10: =(P10/K10)/Q10 -> 0.02306239 | X10: =P10/O10 -> 0.99013912 | Y10: =Q10/(O10/K10) -> 42.933066 | Z10: =Q10/(J10/K10) -> 1.4022781 | AA10: 1
A11: 2018 | B11: LPGI | C11: Lippo General Insurance Tbk | D11: 2315732267904 | E11: 41712464138 | F11: 2485186649117 | I11: 1605367155250 | J11: 879819493867 | K11: 350000 | L11: 1132421357486 | M11: 1054327720740 | N11: 140384182320 | O11: 68687123783 | P11: 36732360000 | Q11: 4300 | R11: =D11/I11 -> 1.4424939 | S11: =I11/J11 -> 1.8246551 | T11: =O11/F11 -> 0.027638618 | U11: =O11/J11 -> 0.078069563 | V11: =O11/L11 -> 0.060655094 | W11: =(P11/K11)/Q11 -> 24.406884 | X11: =P11/O11 -> 0.53477796 | Y11: =Q11/(O11/K11) -> 0.021910948 | Z11: =Q11/(J11/K11) -> 0.0017105781 | AA11: 1
A12: 2019 | B12: LPGI | C12: Lippo General Insurance Tbk | D12: 2235292189141 | E12: 59931111698 | F12: 2425843273596 | I12: 1575194310012 | J12: 848511733189 | K12: 350000 | L12: 1167490752228 | M12: 1079716721795 | N12: 190106898267 | O12: 80002543527 | P12: 48726600000 | Q12: 3600 | R12: =D12/I12 -> 1.4190581 | S12: =I12/J12 -> 1.8564202 | T12: =O12/F12 -> 0.032979271 | U12: =O12/J12 -> 0.094285725 | V12: =O12/L12 -> 0.068525205 | W12: =(P12/K12)/Q12 -> 38.671905 | X12: =P12/O12 -> 0.60906314 | Y12: =Q12/(O12/K12) -> 0.015749499 | Z12: =Q12/(J12/K12) -> 0.0014849529 | AA12: 1
A13: 2020 | B13: LPGI | C13: Lippo General Insurance Tbk | D13: 2624614720238 | E13: 61211166120 | F13: 2815578393095 | I13: 1954498917680 | J13: 861079475415 | K13: 350000 | L13: 1220142637207 | M13: 1108228300836 | N13: 206201182748 | O13: 92908485040 | P13: 32084592000 | Q13: 3390 | R13: =D13/I13 -> 1.3428581 | S13: =I13/J13 -> 2.2698241 | T13: =O13/F13 -> 0.03299801 | U13: =O13/J13 -> 0.10789769 | V13: =O13/L13 -> 0.076145593 | W13: =(P13/K13)/Q13 -> 27.041375 | X13: =P13/O13 -> 0.34533543 | Y13: =Q13/(O13/K13) -> 0.012770631 | Z13: =Q13/(J13/K13) -> 0.0013779216 | AA13: 1
A14: 2018 | B14: MREI | C14: Maskapai Reasuransi Indonesia Tbk | D14: 2614558188655 | E14: 56864203151 | F14: 3426618296227 | I14: 2016141327384 | J14: 1410476968843 | K14: 1500000000 | L14: 1216973600364 | M14: 1045948505140 | N14: 94173689178 | O14: 140867155045 | P14: 28291292960 | Q14: 5100 | R14: =D14/I14 -> 1.296813 | S14: =I14/J14 -> 1.4294039 | T14: =O14/F14 -> 0.041109672 | U14: =O14/J14 -> 0.099871999 | V14: =O14/L14 -> 0.11575202 | W14: =(P14/K14)/Q14 -> 0.0036982082 | X14: =P14/O14 -> 0.20083669 | Y14: =Q14/(O14/K14) -> 54.306485 | Z14: =Q14/(J14/K14) -> 5.4236972 | AA14: 1
A15: 2019 | B15: MREI | C15: Maskapai Reasuransi Indonesia Tbk | D15: 3050314188997 | E15: 51455786161 | F15: 3915599148016 | I15: 2320512877462 | J15: 1595086270554 | K15: 1500000000 | L15: 1470949804896 | M15: 1309841112268 | N15: 97129177369 | O15: 179282076899 | P15: 25754804480 | Q15: 4280 | R15: =D15/I15 -> 1.3145 | S15: =I15/J15 -> 1.4547883 | T15: =O15/F15 -> 0.045786627 | U15: =O15/J15 -> 0.11239648 | V15: =O15/L15 -> 0.12188185 | W15: =(P15/K15)/Q15 -> 0.0040116518 | X15: =P15/O15 -> 0.14365521 | Y15: =Q15/(O15/K15) -> 35.809491 | Z15: =Q15/(J15/K15) -> 4.0248607 | AA15: 1
A16: 2020 | B16: MREI | C16: Maskapai Reasuransi Indonesia Tbk | D16: 3311255955993 | E16: 47281288654 | F16: 4203345266072 | I16: 2447545581054 | J16: 1755799685018 | K16: 1500000000 | L16: 1526256873467 | M16: 1437653868089 | N16: 92126420155 | O16: 105182858790 | P16: 25718451237 | Q16: 4700 | R16: =D16/I16 -> 1.3528884 | S16: =I16/J16 -> 1.3939777 | T16: =O16/F16 -> 0.025023607 | U16: =O16/J16 -> 0.059905956 | V16: =O16/L16 -> 0.068915568 | W16: =(P16/K16)/Q16 -> 0.0036480073 | X16: =P16/O16 -> 0.24451181 | Y16: =Q16/(O16/K16) -> 67.02613 | Z16: =Q16/(J16/K16) -> 4.0152644 | AA16: 1
A17: 2018 | B17: VINS | C17: Victoria Insurance Tbk | D17: 256222710742 | E17: 1162886570 | F17: 262118630829 | I17: 82390315351 | J17: 179728315478 | K17: 4250000000 | L17: 25396161153 | M17: 13254779808 | N17: 13406900449 | O17: 3947657923 | P17: 2325732322 | Q17: 126 | R17: =D17/I17 -> 3.1098644 | S17: =I17/J17 -> 0.45841589 | T17: =O17/F17 -> 0.015060577 | U17: =O17/J17 -> 0.021964585 | V17: =O17/L17 -> 0.1554431 | W17: =(P17/K17)/Q17 -> 0.0043431042 | X17: =P17/O17 -> 0.58914231 | Y17: =Q17/(O17/K17) -> 135.65005 | Z17: =Q17/(J17/K17) -> 2.9794971 | AA17: 1
A18: 2019 | B18: VINS | C18: Victoria Insurance Tbk | D18: 278787602299 | E18: 2050262917 | F18: 284170955431 | I18: 97838690688 | J18: 186332264743 | K18: 4250000000 | L18: 26117484368 | M18: 11356539881 | N18: 15315108957 | O18: 21806030031 | P18: 12646169490 | Q18: 123 | R18: =D18/I18 -> 2.8494617 | S18: =I18/J18 -> 0.52507649 | T18: =O18/F18 -> 0.076735604 | U18: =O18/J18 -> 0.11702767 | V18: =O18/L18 -> 0.83492077 | W18: =(P18/K18)/Q18 -> 0.02419162 | X18: =P18/O18 -> 0.5799391 | Y18: =Q18/(O18/K18) -> 23.972727 | Z18: =Q18/(J18/K18) -> 2.8054723 | AA18: 1
A19: 2020 | B19: VINS | C19: Victoria Insurance Tbk | D19: 317224915081 | E19: 3518827068 | F19: 322342387320 | I19: 138095296876 | J19: 184247090444 | K19: 4250000000 | L19: 26509968632 | M19: 17239784399 | N19: 13577579905 | O19: 6211645756 | P19: 13874395982 | Q19: 91 | R19: =D19/I19 -> 2.297145 | S19: =I19/J19 -> 0.74951141 | T19: =O19/F19 -> 0.019270335 | U19: =O19/J19 -> 0.033713671 | V19: =O19/L19 -> 0.23431358 | W19: =(P19/K19)/Q19 -> 0.035874327 | X19: =P19/O19 -> 2.2336103 | Y19: =Q19/(O19/K19) -> 62.262082 | Z19: =Q19/(J19/K19) -> 2.0990834 | AA19: 1
... A22: 2020 | B22: AGRO | C22: Bank Rakyat Indonesia Agroniaga Tbk | D22: 27536353583000 | E22: 277438069000 | F22: 28015492262000 | I22: 23727802051000 | J22: 4287690211000 | K22: 60000000000 | L22: 1931524786000 | M22: 1306889194000 | N22: 315820017000 | O22: 117206028000 | P22: 0 | Q22: 1035 | R22: =D22/I22 -> 1.1605101 | S22: =I22/J22 -> 5.5339357 | T22: =O22/F22 -> 0.0041836148 | U22: =O22/J22 -> 0.02733547 | V22: =O22/L22 -> 0.060680572 | W22: =(P22/K22)/Q22 -> 0 | X22: =P22/O22 -> 0 | Y22: =Q22/(O22/K22) -> 529.83623 | Z22: =Q22/(J22/K22) -> 14.483322 | AA22: 1
A23: 2018 | B23: AGRS | C23: Bank Agris Tbk | D23: 4035734000000 | E23: 15792000000 | F23: 4151151000000 | I23: 3618348000000 | J23: 532803000000 | K23: 11800000000 | L23: 133934000000 | M23: 171078000000 | N23: 171078000000 | O23: -31122000000 | Q23: 238 | R23: =D23/I23 -> 1.1153526 | S23: =I23/J23 -> 6.7911555 | T23: =O23/F23 -> -0.0074971978 | U23: =O23/J23 -> -0.058411833 | V23: =O23/L23 -> -0.23236818 | W23: =(P23/K23)/Q23 -> 0 | X23: =P23/O23 -> 0 | Y23: =Q23/(O23/K23) -> -90.238417 | Z23: =Q23/(J23/K23) -> 5.2709913 | AA23: 1
A24: 2019 | B24: AGRS | C24: Bank Agris Tbk | D24: 6083396000000 | E24: 134776000000 | F24: 6421844000000 | I24: 5219244000000 | J24: 1202600000000 | K24: 11800000000 | L24: 166231000000 | M24: 223544000000 | N24: 212614000000 | O24: -259525000000 | Q24: 135 | R24: =D24/I24 -> 1.1655703 | S24: =I24/J24 -> 4.3399667 | T24: =O24/F24 -> -0.040412847 | U24: =O24/J24 -> -0.21580326 | V24: =O24/L24 -> -1.5612311 | W24: =(P24/K24)/Q24 -> 0 | X24: =P24/O24 -> 0 | Y24: =Q24/(O24/K24) -> -6.138137 | Z24: =Q24/(J24/K24) -> 1.32463 | AA24: 1
A25: 2020 | B25: AGRS | C25: Bank Agris Tbk | D25: 7907292000000 | E25: 171496000000 | F25: 9854035000000 | I25: 7954197000000 | J25: 1899838000000 | K25: 11800000000 | L25: 169710000000 | M25: 336070000000 | N25: 336070000000 | O25: -176863000000 | Q25: 204 | R25: =D25/I25 -> 0.99410311 | S25: =I25/J25 -> 4.1867765 | T25: =O25/F25 -> -0.017948282 | U25: =O25/J25 -> -0.093093727 | V25: =O25/L25 -> -1.0421484 | W25: =(P25/K25)/Q25 -> 0 | X25: =P25/O25 -> 0 | Y25: =Q25/(O25/K25) -> -13.610535 | Z25: =Q25/(J25/K25) -> 1.2670554 | AA25: 1
A26: 2018 | B26: BABP | C26: Bank MNC Internasional Tbk | D26: 9968365000000 | E26: 48137000000 | F26: 10854855000000 | I26: 9424865000000 | J26: 1429990000000 | K26: 60000000000 | L26: 960256000000 | M26: 572785000000 | N26: 307274000000 | O26: 57021000000 | Q26: 50 | R26: =D26/I26 -> 1.0576666 | S26: =I26/J26 -> 6.5908608 | T26: =O26/F26 -> 0.0052530412 | U26: =O26/J26 -> 0.039875104 | V26: =O26/L26 -> 0.05938104 | W26: =(P26/K26)/Q26 -> 0 | X26: =P26/O26 -> 0 | Y26: =Q26/(O26/K26) -> 52.612196 | Z26: =Q26/(J26/K26) -> 2.0979168 | AA26: 1
A27: 2019 | B27: BABP | C27: Bank MNC Internasional Tbk | D27: 9281777000000 | E27: 48316000000 | F27: 10607879000000 | I27: 9048429000000 | J27: 1559450000000 | K27: 60000000000 | L27: 1071032000000 | M27: 667529000000 | N27: 339722000000 | O27: 20433000000 | Q27: 50 | R27: =D27/I27 -> 1.0257888 | S27: =I27/J27 -> 5.8023207 | T27: =O27/F27 -> 0.0019262098 | U27: =O27/J27 -> 0.013102696 | V27: =O27/L27 -> 0.019077861 | W27: =(P27/K27)/Q27 -> 0 | X27: =P27/O27 -> 0 | Y27: =Q27/(O27/K27) -> 146.82132 | Z27: =Q27/(J27/K27) -> 1.9237552 | AA27: 1
A28: 2020 | B28: BABP | C28: Bank MNC Internasional Tbk | D28: 102648350000000 | E28: 40914000000 | F28: 11652904000000 | I28: 10101667000000 | J28: 11652904000000 | K28: 60000000000 | L28: 969784000000 | M28: 368535000000 | N28: 345839000000 | O28: 10414000000 | Q28: 50 | R28: =D28/I28 -> 10.161526 | S28: =I28/J28 -> 0.86687979 | T28: =O28/F28 -> 0.00089368281 | U28: =O28/J28 -> 0.00089368281 | V28: =O28/L28 -> 0.010738474 | W28: =(P28/K28)/Q28 -> 0 | X28: =P28/O28 -> 0 | Y28: =Q28/(O28/K28) -> 288.07375 | Z28: =Q28/(J28/K28) -> 0.25744656 | AA28: 1
A29: 2018 | B29: BBCA | C29: Bank Central Asia Tbk | D29: 788261904000000 | E29: 19336901000000 | F29: 824787944000000 | I29: 668438779000000 | J29: 151753427000000 | K29: 88000000000 | L29: 56766800000000 | M29: 11476255000000 | N29: 27651554000000 | O29: 25851660000000 | P29: 6410302000000 | Q29: 26000 | R29: =D29/I29 -> 1.1792582 | S29: =I29/J29 -> 4.4047689 | T29: =O29/F29 -> 0.031343402 | U29: =O29/J29 -> 0.17035306 | V29: =O29/L29 -> 0.45540104 | W29: =(P29/K29)/Q29 -> 0.0028017054 | X29: =P29/O29 -> 0.24796481 | Y29: =Q29/(O29/K29) -> 88.504955 | Z29: =Q29/(J29/K29) -> 15.077089 | AA29: 1
A30: 2019 | B30: BBCA | C30: Bank Central Asia Tbk | D30: 878881370000000 | E30: 20852301000000 | F30: 918989312000000 | I30: 740067127000000 | J30: 174143156000000 | K30: 88000000000 | L30: 63837795000000 | M30: 13360347000000 | N30: 30742208000000 | O30: 28569974000000 | P30: 8752529000000 | Q30: 33425 | R30: =D30/I30 -> 1.1875698 | S30: =I30/J30 -> 4.2497629 | T30: =O30/F30 -> 0.031088473 | U30: =O30/J30 -> 0.16406027 | V30: =O30/L30 -> 0.44754011 | W30: =(P30/K30)/Q30 -> 0.0029756337 | X30: =P30/O30 -> 0.30635411 | Y30: =Q30/(O30/K30) -> 102.95424 | Z30: =Q30/(J30/K30) -> 16.890701 | AA30: 1
A31: 2020 | B31: BBCA | C31: Bank Central Asia Tbk | D31: 1.0305302e+15 | E31: 21915054000000 | F31: 1.0755703e+15 | I31: 885537919000000 | J31: 184714709000000 | K31: 88000000000 | L31: 65403161000000 | M31: 11241891000000 | N31: 29968715000000 | O31: 27147109000000 | P31: 13634221000000 | Q31: 33850 | R31: =D31/I31 -> 1.1637336 | S31: =I31/J31 -> 4.7940845 | T31: =O31/F31 -> 0.025239736 | U31: =O31/J31 -> 0.14696777 | V31: =O31/L31 -> 0.41507335 | W31: =(P31/K31)/Q31 -> 0.0045770851 | X31: =P31/O31 -> 0.50223473 | Y31: =Q31/(O31/K31) -> 109.72807 | Z31: =Q31/(J31/K31) -> 16.126491 | AA31: 1
A32: 2018 | B32: BBHI | C32: Bank Harda Internasional Tbk | D32: 2020118373285 | E32: 34368921424 | F32: 2264172563518 | I32: 1927690426617 | J32: 336482136901 | K32: 10000000000 | L32: 222339040371 | M32: 120624113372 | N32: 58187078926 | O32: -123143307728 | Q32: 171 | R32: =D32/I32 -> 1.0479475 | S32: =I32/J32 -> 5.7289532 | T32: =O32/F32 -> -0.054387775 | U32: =O32/J32 -> -0.36597279 | V32: =O32/L32 -> -0.55385373 | W32: =(P32/K32)/Q32 -> 0 | X32: =P32/O32 -> 0 | Y32: =Q32/(O32/K32) -> -13.88626 | Z32: =Q32/(J32/K32) -> 5.0819934 | AA32: 1
A33: 2019 | B33: BBHI | C33: Bank Harda Internasional Tbk | D33: 2287435487925 | E33: 32804430650 | F33: 2527173168770 | I33: 2227407291122 | J33: 299765877648 | K33: 10000000000 | L33: 222323923791 | M33: 135940003048 | N33: 60987155987 | O33: -36549663189 | Q33: 125 | R33: =D33/I33 -> 1.0269498 | S33: =I33/J33 -> 7.4304898 | T33: =O33/F33 -> -0.014462667 | U33: =O33/J33 -> -0.12192736 | V33: =O33/L33 -> -0.16439825 | W33: =(P33/K33)/Q33 -> 0 | X33: =P33/O33 -> 0 | Y33: =Q33/(O33/K33) -> -34.200042 | Z33: =Q33/(J33/K33) -> 4.1699209 | AA33: 1
A34: 2020 | B34: BBHI | C34: Bank Harda Internasional Tbk | D34: 2306058477913 | E34: 30376640192 | F34: 2586663487991 | I34: 2239597029811 | J34: 347066458180 | K34: 10000000000 | L34: 162125871157 | M34: 114535488869 | N34: 41188991154 | O34: 37011391337 | Q34: 424 | R34: =D34/I34 -> 1.0296756 | S34: =I34/J34 -> 6.4529342 | T34: =O34/F34 -> 0.014308545 | U34: =O34/J34 -> 0.10664065 | V34: =O34/L34 -> 0.228288 | W34: =(P34/K34)/Q34 -> 0 | X34: =P34/O34 -> 0 | Y34: =Q34/(O34/K34) -> 114.55932 | Z34: =Q34/(J34/K34) -> 12.21668 | AA34: 1
A35: 2018 | B35: BBKP | C35: Bank Bukopin Tbk | D35: 85349356000000 | E35: 3075041000000 | F35: 95643923000000 | I35: 87049486000000 | J35: 8594437000000 | K35: 22887540178 | L35: 7980892000000 | M35: 5387749000000 | N35: 2759809000000 | O35: 189970000000 | Q35: 272 | R35: =D35/I35 -> 0.98046938 | S35: =I35/J35 -> 10.128585 | T35: =O35/F35 -> 0.0019862213 | U35: =O35/J35 -> 0.022103833 | V35: =O35/L35 -> 0.023803104 | W35: =(P35/K35)/Q35 -> 0 | X35: =P35/O35 -> 0 | Y35: =Q35/(O35/K35) -> 32.770495 | Z35: =Q35/(J35/K35) -> 0.72435355 | AA35: 1
A36: 2019 | B36: BBKP | C36: Bank Bukopin Tbk | D36: 87668576000000 | E36: 3012215000000 | F36: 100264248000000 | I36: 91358763000000 | J36: 8905485000000 | K36: 22887540178 | L36: 7764858000000 | M36: 5750319000000 | N36: 2801776000000 | O36: 216749000000 | Q36: 224 | R36: =D36/I36 -> 0.95960774 | S36: =I36/J36 -> 10.258707 | T36: =O36/F36 -> 0.0021617775 | U36: =O36/J36 -> 0.02433882 | V36: =O36/L36 -> 0.027914097 | W36: =(P36/K36)/Q36 -> 0 | X36: =P36/O36 -> 0 | Y36: =Q36/(O36/K36) -> 23.653207 | Z36: =Q36/(J36/K36) -> 0.57569116 | AA36: 1
A37: 2020 | B37: BBKP | C37: Bank Bukopin Tbk | D37: 69019702000000 | E37: 3504403000000 | F37: 79938578000000 | I37: 71472136000000 | J37: 8466442000000 | K37: 22887540178 | L37: 5308366000000 | M37: 4756310000000 | N37: 2758323000000 | O37: -3258109000000 | Q37: 575 | R37: =D37/I37 -> 0.96568685 | S37: =I37/J37 -> 8.4418149 | T37: =O37/F37 -> -0.040757655 | U37: =O37/J37 -> -0.38482624 | V37: =O37/L37 -> -0.61376872 | W37: =(P37/K37)/Q37 -> 0 | X37: =P37/O37 -> 0 | Y37: =Q37/(O37/K37) -> -4.0392558 | Z37: =Q37/(J37/K37) -> 1.5544116 | AA37: 1
A38: 2018 | B38: BBMD | C38: Bank Mestika Dharma Tbk | D38: 11454704380759 | E38: 470415776572 | F38: 12093079368934 | I38: 9005066283473 | J38: 3088013085461 | K38: 10000000000 | L38: 1026137099056 | M38: 339167553637 | N38: 428776741954 | O38: 265862564725 | Q38: 1380 | R38: =D38/I38 -> 1.2720289 | S38: =I38/J38 -> 2.9161361 | T38: =O38/F38 -> 0.021984687 | U38: =O38/J38 -> 0.086095025 | V38: =O38/L38 -> 0.25909069 | W38: =(P38/K38)/Q38 -> 0 | X38: =P38/O38 -> 0 | Y38: =Q38/(O38/K38) -> 51.906518 | Z38: =Q38/(J38/K38) -> 4.468893 | AA38: 1
A39: 2019 | B39: BBMD | C39: Bank Mestika Dharma Tbk | D39: 12276512567406 | E39: 492662820097 | F39: 12900218775263 | I39: 9419749653807 | J39: 3480469121456 | K39: 10000000000 | L39: 1058536635511 | M39: 358086464478 | N39: 473384503657 | O39: 247573726183 | Q39: 2800 | R39: =D39/I39 -> 1.3032738 | S39: =I39/J39 -> 2.7064598 | T39: =O39/F39 -> 0.019191436 | U39: =O39/J39 -> 0.071132286 | V39: =O39/L39 -> 0.233883 | W39: =(P39/K39)/Q39 -> 0 | X39: =P39/O39 -> 0 | Y39: =Q39/(O39/K39) -> 113.09762 | Z39: =Q39/(J39/K39) -> 8.0448925 | AA39: 1
A40: 2020 | B40: BBMD | C40: Bank Mestika Dharma Tbk | D40: 13522482361051 | E40: 479822488029 | F40: 14159755232533 | I40: 10150492606994 | J40: 4009262625539 | K40: 10000000000 | L40: 1122202992204 | M40: 326616871157 | N40: 534878138389 | O40: 325932118524 | Q40: 1500 | R40: =D40/I40 -> 1.3321996 | S40: =I40/J40 -> 2.5317605 | T40: =O40/F40 -> 0.023018203 | U40: =O40/J40 -> 0.081294779 | V40: =O40/L40 -> 0.29043954 | W40: =(P40/K40)/Q40 -> 0 | X40: =P40/O40 -> 0 | Y40: =Q40/(O40/K40) -> 46.021853 | Z40: =Q40/(J40/K40) -> 3.7413364 | AA40: 1
A41: 2018 | B41: BBNP | C41: Bank Nusantara Parahyangan Tbk | Q41: 2200 | R41: =D41/I41 -> #DIV/0! | S41: =I41/J41 -> #DIV/0! | T41: =O41/F41 -> #DIV/0! | U41: =O41/J41 -> #DIV/0! | V41: =O41/L41 -> #DIV/0! | W41: =(P41/K41)/Q41 -> #DIV/0! | X41: =P41/O41 -> #DIV/0! | Y41: =Q41/(O41/K41) -> #DIV/0! | Z41: =Q41/(J41/K41) -> #DIV/0! | AA41: 1
A42: 2019 | B42: BBNP | C42: Bank Nusantara Parahyangan Tbk | Q42: 0 | R42: =D42/I42 -> #DIV/0! | S42: =I42/J42 -> #DIV/0! | T42: =O42/F42 -> #DIV/0! | U42: =O42/J42 -> #DIV/0! | V42: =O42/L42 -> #DIV/0! | W42: =(P42/K42)/Q42 -> #DIV/0! | X42: =P42/O42 -> #DIV/0! | Y42: =Q42/(O42/K42) -> #DIV/0! | Z42: =Q42/(J42/K42) -> #DIV/0! | AA42: 1
A43: 2020 | B43: BBNP | C43: Bank Nusantara Parahyangan Tbk | R43: =D43/I43 -> #DIV/0! | S43: =I43/J43 -> #DIV/0! | T43: =O43/F43 -> #DIV/0! | U43: =O43/J43 -> #DIV/0! | V43: =O43/L43 -> #DIV/0! | W43: =(P43/K43)/Q43 -> #DIV/0! | X43: =P43/O43 -> #DIV/0! | Y43: =Q43/(O43/K43) -> #DIV/0! | Z43: =Q43/(J43/K43) -> #DIV/0! | AA43: 1
A44: 2018 | B44: BBRI | C44: Bank Rakyat Indonesia (Persero) Tbk | D44: 1.2410291e+15 | E44: 26914859000000 | F44: 1.2968983e+15 | I44: 109066408400000 | J44: 185275331000000 | K44: 300000000000 | L44: 111582804000000 | M44: 33917032000000 | N44: 41990284000000 | O44: 32418486000000 | P44: 13048441000000 | Q44: 3660 | R44: =D44/I44 -> 11.378656 | S44: =I44/J44 -> 0.58867205 | T44: =O44/F44 -> 0.024996938 | U44: =O44/J44 -> 0.17497465 | V44: =O44/L44 -> 0.29053299 | W44: =(P44/K44)/Q44 -> 0.011883826 | X44: =P44/O44 -> 0.40250001 | Y44: =Q44/(O44/K44) -> 33.869564 | Z44: =Q44/(J44/K44) -> 5.9263151 | AA44: 1
A45: 2019 | B45: BBRI | C45: Bank Rakyat Indonesia (Persero) Tbk | D45: 1.3597731e+15 | E45: 31432629000000 | F45: 1.4167588e+15 | I45: 1.1831557e+15 | J45: 208784336000000 | K45: 300000000000 | L45: 121756276000000 | M45: 38671838000000 | N45: 45033505000000 | O45: 34413825000000 | P45: 16175565000000 | Q45: 4400 | R45: =D45/I45 -> 1.1492766 | S45: =I45/J45 -> 5.6668795 | T45: =O45/F45 -> 0.024290531 | U45: =O45/J45 -> 0.16482953 | V45: =O45/L45 -> 0.28264518 | W45: =(P45/K45)/Q45 -> 0.012254216 | X45: =P45/O45 -> 0.47003101 | Y45: =Q45/(O45/K45) -> 38.356678 | Z45: =Q45/(J45/K45) -> 6.3223134 | AA45: 1
A46: 2020 | B46: BBRI | C46: Bank Rakyat Indonesia (Persero) Tbk | D46: 1.4426202e+15 | E46: 32185160000000 | F46: 1.5118046e+15 | I46: 1.2783463e+15 | J46: 199911376000000 | K46: 300000000000 | L46: 116932512000000 | M46: 37722595000000 | N46: 68827650000000 | O46: 34413825000000 | P46: 20623565000000 | R46: =D46/I46 -> 1.128505 | S46: =I46/J46 -> 6.3945649 | T46: =O46/F46 -> 0.022763408 | U46: =O46/J46 -> 0.17214541 | V46: =O46/L46 -> 0.29430502 | W46: =(P46/K46)/Q46 -> #DIV/0! | X46: =P46/O46 -> 0.59928139 | Y46: =Q46/(O46/K46) -> 0 | Z46: =Q46/(J46/K46) -> 0 | AA46: 1
A47: 2018 | B47: BBYB | C47: Bank Yudha Bhakti Tbk | D47: 4781138960034 | E47: 83206069558 | F47: 4533729146622 | I47: 3933343821678 | J47: 600385324944 | K47: 15000000000 | L47: 589663115314 | M47: 303322028671 | N47: 440184797149 | O47: -136988450929 | P47: 5763770665 | Q47: 284 | R47: =D47/I47 -> 1.2155406 | S47: =I47/J47 -> 6.5513657 | T47: =O47/F47 -> -0.030215402 | U47: =O47/J47 -> -0.22816755 | V47: =O47/L47 -> -0.23231647 | W47: =(P47/K47)/Q47 -> 0.0013529978 | X47: =P47/O47 -> -0.042074866 | Y47: =Q47/(O47/K47) -> -31.097512 | Z47: =Q47/(J47/K47) -> 7.0954432 | AA47: 1
A48: 2019 | B48: BBYB | C48: Bank Yudha Bhakti Tbk | D48: 4918029226569 | E48: 87885955385 | F48: 5123734649117 | I48: 4177951053821 | J48: 945783595296 | K48: 15000000000 | L48: 532495206620 | M48: 316396580171 | N48: 403790198835 | O48: 16002797471 | P48: 0 | Q48: 284 | R48: =D48/I48 -> 1.177139 | S48: =I48/J48 -> 4.4174493 | T48: =O48/F48 -> 0.0031232682 | U48: =O48/J48 -> 0.016920147 | V48: =O48/L48 -> 0.030052472 | W48: =(P48/K48)/Q48 -> 0 | X48: =P48/O48 -> 0 | Y48: =Q48/(O48/K48) -> 266.20346 | Z48: =Q48/(J48/K48) -> 4.5042016 | AA48: 1
A49: 2020 | B49: BBYB | C49: Bank Yudha Bhakti Tbk | D49: 4978233171638 | E49: 108803796324 | F49: 5421324398438 | I49: 4300705118122 | J49: 1120619280316 | K49: 15000000000 | L49: 435200503846 | M49: 276969580433 | N49: 229554559339 | O49: 15871502695 | P49: 1598830857 | Q49: 298 | R49: =D49/I49 -> 1.1575388 | S49: =I49/J49 -> 3.8377933 | T49: =O49/F49 -> 0.0029276062 | U49: =O49/J49 -> 0.014163153 | V49: =O49/L49 -> 0.036469403 | W49: =(P49/K49)/Q49 -> 0.00035768028 | X49: =P49/O49 -> 0.10073595 | Y49: =Q49/(O49/K49) -> 281.63685 | Z49: =Q49/(J49/K49) -> 3.9888659 | AA49: 1
A50: 2018 | B50: BCIC | C50: Bank J Trust Indonesia Tbk | D50: 12539574000000 | E50: 194079000000 | F50: 17823669000000 | I50: 16508766000000 | J50: 1314903000000 | K50: 12384618000 | L50: 1426813000000 | M50: 1035272000000 | N50: 734524000000 | O50: -401101000000 | P50: 0 | Q50: 450 | R50: =D50/I50 -> 0.75957064 | S50: =I50/J50 -> 12.555121 | T50: =O50/F50 -> -0.02250384 | U50: =O50/J50 -> -0.30504227 | V50: =O50/L50 -> -0.28111673 | W50: =(P50/K50)/Q50 -> 0 | X50: =P50/O50 -> 0 | Y50: =Q50/(O50/K50) -> -13.894451 | Z50: =Q50/(J50/K50) -> 4.2383948 | AA50: 1
A51: 2019 | B51: BCIC | C51: Bank J Trust Indonesia Tbk | D51: 8271271000000 | E51: 199165000000 | F51: 17311597000000 | I51: 15637771000000 | J51: 1673826000000 | K51: 12384618000 | L51: 1132243000000 | M51: 1081987000000 | N51: 743645000000 | O51: 49495000000 | P51: 0 | Q51: 450 | R51: =D51/I51 -> 0.52892903 | S51: =I51/J51 -> 9.3425308 | T51: =O51/F51 -> 0.0028590661 | U51: =O51/J51 -> 0.029569979 | V51: =O51/L51 -> 0.043714114 | W51: =(P51/K51)/Q51 -> 0 | X51: =P51/O51 -> 0 | Y51: =Q51/(O51/K51) -> 112.59881 | Z51: =Q51/(J51/K51) -> 3.3295445 | AA51: 1
A52: 2020 | B52: BCIC | C52: Bank J Trust Indonesia Tbk | D52: 11101933000000 | E52: 194214000000 | F52: 16204908000000 | I52: 14761678000000 | J52: 1443230000000 | K52: 12384618000 | L52: 978794000000 | M52: 952657000000 | N52: 662860000000 | O52: -484441000000 | P52: 0 | Q52: 700 | R52: =D52/I52 -> 0.75207798 | S52: =I52/J52 -> 10.228223 | T52: =O52/F52 -> -0.029894708 | U52: =O52/J52 -> -0.33566445 | V52: =O52/L52 -> -0.49493663 | W52: =(P52/K52)/Q52 -> 0 | X52: =P52/O52 -> 0 | Y52: =Q52/(O52/K52) -> -17.895332 | Z52: =Q52/(J52/K52) -> 6.0068268 | AA52: 1
A53: 2018 | B53: BDMN | C53: Bank Danamon Indonesia Tbk | D53: 171650004000000 | E53: 1902608000000 | F53: 186762189000000 | I53: 144822368000000 | J53: 41939821000000 | K53: 17782400000 | L53: 20172187000000 | M53: 5931103000000 | N53: 13129417000000 | O53: 4107068000000 | P53: 1341456000000 | Q53: 7600 | R53: =D53/I53 -> 1.1852451 | S53: =I53/J53 -> 3.4530993 | T53: =O53/F53 -> 0.021990897 | U53: =O53/J53 -> 0.097927647 | V53: =O53/L53 -> 0.20360053 | W53: =(P53/K53)/Q53 -> 0.0099259587 | X53: =P53/O53 -> 0.32662133 | Y53: =Q53/(O53/K53) -> 32.905771 | Z53: =Q53/(J53/K53) -> 3.2223848 | AA53: 1
A54: 2019 | B54: BDMN | C54: Bank Danamon Indonesia Tbk | D54: 181728084000000 | E54: 1785994000000 | F54: 193533970000000 | I54: 148116943000000 | J54: 45417027000000 | K54: 17782400000 | L54: 21970144000000 | M54: 7390746000000 | N54: 15538521000000 | O54: 4240671000000 | P54: 1444699000000 | Q54: 3950 | R54: =D54/I54 -> 1.226923 | S54: =I54/J54 -> 3.2612646 | T54: =O54/F54 -> 0.021911766 | U54: =O54/J54 -> 0.093371832 | V54: =O54/L54 -> 0.19301972 | W54: =(P54/K54)/Q54 -> 0.020567898 | X54: =P54/O54 -> 0.34067698 | Y54: =Q54/(O54/K54) -> 16.56353 | Z54: =Q54/(J54/K54) -> 1.5465671 | AA54: 1
A55: 2020 | B55: BDMN | C55: Bank Danamon Indonesia Tbk | D55: 187946193000000 | E55: 2105691000000 | F55: 200890068000000 | I55: 157314590000000 | J55: 43575499000000 | K55: 17782400000 | L55: 20087555000000 | M55: 6363892000000 | N55: 15958508000000 | O55: 1088942000000 | P55: 1916205000000 | Q55: 3140 | R55: =D55/I55 -> 1.1947156 | S55: =I55/J55 -> 3.6101615 | T55: =O55/F55 -> 0.0054205865 | U55: =O55/J55 -> 0.024989777 | V55: =O55/L55 -> 0.054209783 | W55: =(P55/K55)/Q55 -> 0.034317998 | X55: =P55/O55 -> 1.7596943 | Y55: =Q55/(O55/K55) -> 51.276134 | Z55: =Q55/(J55/K55) -> 1.2813792 | AA55: 1
A56: 2018 | B56: BEKS | C56: Bank Pembangunan Daerah Banten | D56: 8488491000000 | E56: 77068000000 | F56: 9482130000000 | I56: 8788732000000 | J56: 693398000000 | K56: 125693155976 | L56: 571662000000 | M56: 436252000000 | N56: 296067000000 | O56: -100131000000 | P56: 0 | Q56: 50 | R56: =D56/I56 -> 0.96583796 | S56: =I56/J56 -> 12.674874 | T56: =O56/F56 -> -0.010559969 | U56: =O56/J56 -> -0.14440624 | V56: =O56/L56 -> -0.1751577 | W56: =(P56/K56)/Q56 -> 0 | X56: =P56/O56 -> 0 | Y56: =Q56/(O56/K56) -> -62.764357 | Z56: =Q56/(J56/K56) -> 9.0635649 | AA56: 1
A57: 2019 | B57: BEKS | C57: Bank Pembangunan Daerah Banten | D57: 7018761000000 | E57: 65551000000 | F57: 8097328000000 | I57: 7547795000000 | J57: 549533000000 | K57: 125693155976 | L57: 553871000000 | M57: 481024000000 | N57: 308662000000 | O57: -137559000000 | P57: 0 | Q57: 50 | R57: =D57/I57 -> 0.9299088 | S57: =I57/J57 -> 13.734926 | T57: =O57/F57 -> -0.016988197 | U57: =O57/J57 -> -0.25031982 | V57: =O57/L57 -> -0.24835927 | W57: =(P57/K57)/Q57 -> 0 | X57: =P57/O57 -> 0 | Y57: =Q57/(O57/K57) -> -45.686998 | Z57: =Q57/(J57/K57) -> 11.436361 | AA57: 1
A58: 2020 | B58: BEKS | C58: Bank Pembangunan Daerah Banten | D58: 4119081000000 | E58: 65323000000 | F58: 5337281000000 | I58: 3975700000000 | J58: 1361581000000 | K58: 125693155976 | L58: 372209000000 | M58: 338465000000 | N58: 294640000000 | O58: 308158000000 | P58: 0 | Q58: 98 | R58: =D58/I58 -> 1.0360643 | S58: =I58/J58 -> 2.9199144 | T58: =O58/F58 -> 0.057736889 | U58: =O58/J58 -> 0.22632366 | V58: =O58/L58 -> 0.82791657 | W58: =(P58/K58)/Q58 -> 0 | X58: =P58/O58 -> 0 | Y58: =Q58/(O58/K58) -> 39.972771 | Z58: =Q58/(J58/K58) -> 9.0467841 | AA58: 1
... A76: 2020 | B76: BNII | C76: Bank Maybank Indonesia Tbk | D76: 165206394000000 | E76: 3479263000000 | F76: 173224412000000 | I76: 146000782000000 | J76: 27223630000000 | K76: 476608857231 | L76: 12826683000000 | M76: 5566873000000 | N76: 7793430000000 | O76: 1254392000000 | P76: 392907000000 | Q76: 346 | R76: =D76/I76 -> 1.1315446 | S76: =I76/J76 -> 5.3630167 | T76: =O76/F76 -> 0.0072414274 | U76: =O76/J76 -> 0.046077323 | V76: =O76/L76 -> 0.09779551 | W76: =(P76/K76)/Q76 -> 0.0023826023 | X76: =P76/O76 -> 0.31322505 | Y76: =Q76/(O76/K76) -> 131.46342 | Z76: =Q76/(J76/K76) -> 6.0574826 | AA76: 1
A77: 2018 | B77: BNLI | C77: Bank Permata Tbk | D77: 141176845000000 | E77: 2552305000000 | F77: 152892866000000 | I77: 130440930000000 | J77: 22451936000000 | K77: 97338856834 | L77: 11080952000000 | M77: 5680767000000 | N77: 4465833000000 | O77: 901252000000 | Q77: 625 | R77: =D77/I77 -> 1.0823048 | S77: =I77/J77 -> 5.8097854 | T77: =O77/F77 -> 0.0058946635 | U77: =O77/J77 -> 0.040141394 | V77: =O77/L77 -> 0.081333445 | W77: =(P77/K77)/Q77 -> 0 | X77: =P77/O77 -> 0 | Y77: =Q77/(O77/K77) -> 67.502525 | Z77: =Q77/(J77/K77) -> 2.7096454 | AA77: 1
A78: 2019 | B78: BNLI | C78: Bank Permata Tbk | D78: 150355796000000 | E78: 2451459000000 | F78: 161451259000000 | I78: 137413908000000 | J78: 24037351000000 | K78: 97338856834 | L78: 11742063000000 | M78: 6021095000000 | N78: 4737632000000 | O78: 1500420000000 | Q78: 1265 | R78: =D78/I78 -> 1.0941818 | S78: =I78/J78 -> 5.7166827 | T78: =O78/F78 -> 0.0092933311 | U78: =O78/J78 -> 0.062420356 | V78: =O78/L78 -> 0.12778163 | W78: =(P78/K78)/Q78 -> 0 | X78: =P78/O78 -> 0 | Y78: =Q78/(O78/K78) -> 82.066124 | Z78: =Q78/(J78/K78) -> 5.1225967 | AA78: 1
A79: 2020 | B79: BNLI | C79: Bank Permata Tbk | D79: 186388089000000 | E79: 3073596000000 | F79: 197726097000000 | I79: 162654644000000 | J79: 35071453000000 | K79: 117338856834 | L79: 11923778000000 | M79: 5291988000000 | N79: 5076563000000 | O79: 721587000000 | Q79: 3020 | R79: =D79/I79 -> 1.1459131 | S79: =I79/J79 -> 4.6378074 | T79: =O79/F79 -> 0.0036494272 | U79: =O79/J79 -> 0.020574768 | V79: =O79/L79 -> 0.060516642 | W79: =(P79/K79)/Q79 -> 0 | X79: =P79/O79 -> 0 | Y79: =Q79/(O79/K79) -> 491.08887 | Z79: =Q79/(J79/K79) -> 10.10404 | AA79: 1
A80: 2018 | B80: BSIM | C80: Bank Sinarmas Tbk | D80: 27617905000000 | E80: 1211744000000 | F80: 30748742000000 | I80: 23532846000000 | J80: 4856420000000 | K80: 60000000000 | L80: 3085519000000 | M80: 919577000000 | N80: 781734000000 | O80: 50472000000 | Q80: 550 | R80: =D80/I80 -> 1.1735897 | S80: =I80/J80 -> 4.8457189 | T80: =O80/F80 -> 0.001641433 | U80: =O80/J80 -> 0.010392841 | V80: =O80/L80 -> 0.016357702 | W80: =(P80/K80)/Q80 -> 0 | X80: =P80/O80 -> 0 | Y80: =Q80/(O80/K80) -> 653.82786 | Z80: =Q80/(J80/K80) -> 6.7951289 | AA80: 1
A81: 2019 | B81: BSIM | C81: Bank Sinarmas Tbk | D81: 31667485000000 | E81: 1399242000000 | F81: 36559556000000 | I81: 26385919000000 | J81: 6074463000000 | K81: 60000000000 | L81: 3360860000000 | M81: 1150357000000 | N81: 987162000000 | O81: 6752000000 | Q81: 585 | R81: =D81/I81 -> 1.2001661 | S81: =I81/J81 -> 4.3437451 | T81: =O81/F81 -> 0.00018468496 | U81: =O81/J81 -> 0.0011115386 | V81: =O81/L81 -> 0.0020090096 | W81: =(P81/K81)/Q81 -> 0 | X81: =P81/O81 -> 0 | Y81: =Q81/(O81/K81) -> 5198.4597 | Z81: =Q81/(J81/K81) -> 5.7782885 | AA81: 1
A82: 2020 | B82: BSIM | C82: Bank Sinarmas Tbk | D82: 39397647000000 | E82: 1584298000000 | F82: 44612045000000 | I82: 32557921000000 | J82: 6056844000000 | K82: 60000000000 | L82: 3300261000000 | M82: 1112057000000 | N82: 1201125000000 | O82: 118522000000 | Q82: 505 | R82: =D82/I82 -> 1.2100787 | S82: =I82/J82 -> 5.3753937 | T82: =O82/F82 -> 0.0026567265 | U82: =O82/J82 -> 0.019568277 | V82: =O82/L82 -> 0.035912917 | W82: =(P82/K82)/Q82 -> 0 | X82: =P82/O82 -> 0 | Y82: =Q82/(O82/K82) -> 255.64874 | Z82: =Q82/(J82/K82) -> 5.0026053 | AA82: 1
A83: 2018 | B83: BSWD | C83: Bank Of India Indonesia Tbk | D83: 3589446529008 | E83: 125754140019 | F83: 3896760492444 | I83: 2766528043722 | J83: 1130232448722 | K83: 3450000000 | L83: 314850371256 | M83: 176462730317 | N83: 10669420520 | O83: 9879658315 | Q83: 1750 | R83: =D83/I83 -> 1.2974553 | S83: =I83/J83 -> 2.4477514 | T83: =O83/F83 -> 0.0025353517 | U83: =O83/J83 -> 0.0087412623 | V83: =O83/L83 -> 0.0313789 | W83: =(P83/K83)/Q83 -> 0 | X83: =P83/O83 -> 0 | Y83: =Q83/(O83/K83) -> 611.10413 | Z83: =Q83/(J83/K83) -> 5.3418215 | AA83: 1
A84: 2019 | B84: BSWD | C84: Bank Of India Indonesia Tbk | D84: 3628547496443 | E84: 123155112941 | F84: 4007412556573 | I84: 2846135386095 | J84: 1161277170478 | K84: 3450000000 | L84: 287717146129 | M84: 145535047285 | N84: 1675418516 | O84: 30952161285 | Q84: 1750 | R84: =D84/I84 -> 1.2749033 | S84: =I84/J84 -> 2.4508666 | T84: =O84/F84 -> 0.0077237272 | U84: =O84/J84 -> 0.026653552 | V84: =O84/L84 -> 0.10757844 | W84: =(P84/K84)/Q84 -> 0 | X84: =P84/O84 -> 0 | Y84: =Q84/(O84/K84) -> 195.05908 | Z84: =Q84/(J84/K84) -> 5.1990172 | AA84: 1
A85: 2020 | B85: BSWD | C85: Bank Of India Indonesia Tbk | D85: 3420216280720 | E85: 122716526336 | F85: 3721363459751 | I85: 2663693880300 | J85: 1057669579451 | K85: 3450000000 | L85: 230453382943 | M85: 142465319309 | N85: 2848631236 | O85: 70581531876 | Q85: 1750 | R85: =D85/I85 -> 1.2840125 | S85: =I85/J85 -> 2.5184556 | T85: =O85/F85 -> 0.018966578 | U85: =O85/J85 -> 0.066733064 | V85: =O85/L85 -> 0.30627249 | W85: =(P85/K85)/Q85 -> 0 | X85: =P85/O85 -> 0 | Y85: =Q85/(O85/K85) -> 85.539373 | Z85: =Q85/(J85/K85) -> 5.7083045 | AA85: 1
A86: 2018 | B86: BTPN | C86: Bank Tabungan Pensiunan Nasional Tbk | D86: 95049657000000 | E86: 1786727000000 | F86: 101919301000000 | I86: 76544999000000 | J86: 19364407000000 | K86: 15000000000 | L86: 14126651000000 | M86: 4526243000000 | N86: 7286241000000 | O86: 2128064000000 | P86: 574509000000 | Q86: 3440 | R86: =D86/I86 -> 1.2417488 | S86: =I86/J86 -> 3.9528708 | T86: =O86/F86 -> 0.020879892 | U86: =O86/J86 -> 0.10989565 | V86: =O86/L86 -> 0.15064179 | W86: =(P86/K86)/Q86 -> 0.011133895 | X86: =P86/O86 -> 0.26996791 | Y86: =Q86/(O86/K86) -> 24.247391 | Z86: =Q86/(J86/K86) -> 2.6646827 | AA86: 1
A87: 2019 | B87: BTPN | C87: Bank Tabungan Pensiunan Nasional Tbk | D87: 174663286000000 | E87: 1893746000000 | F87: 181631385000000 | I87: 142608793000000 | J87: 31471928000000 | K87: 15000000000 | L87: 18680979000000 | M87: 7689284000000 | N87: 8594419000000 | O87: 2992418000000 | P87: 0 | Q87: 3250 | R87: =D87/I87 -> 1.2247722 | S87: =I87/J87 -> 4.5313015 | T87: =O87/F87 -> 0.016475225 | U87: =O87/J87 -> 0.095082132 | V87: =O87/L87 -> 0.16018529 | W87: =(P87/K87)/Q87 -> 0 | X87: =P87/O87 -> 0 | Y87: =Q87/(O87/K87) -> 16.291173 | Z87: =Q87/(J87/K87) -> 1.5489995 | AA87: 1
A88: 2020 | B88: BTPN | C88: Bank Tabungan Pensiunan Nasional Tbk | D88: 175897784000000 | E88: 2357987000000 | F88: 183165978000000 | I88: 142277859000000 | J88: 32964753000000 | K88: 15000000000 | L88: 16403483000000 | M88: 5779055000000 | N88: 9690939000000 | O88: 2005677000000 | P88: 103887000000 | Q88: 3110 | R88: =D88/I88 -> 1.2362977 | S88: =I88/J88 -> 4.3160602 | T88: =O88/F88 -> 0.010950052 | U88: =O88/J88 -> 0.060843077 | V88: =O88/L88 -> 0.12227141 | W88: =(P88/K88)/Q88 -> 0.0022269453 | X88: =P88/O88 -> 0.051796476 | Y88: =Q88/(O88/K88) -> 23.258979 | Z88: =Q88/(J88/K88) -> 1.4151479 | AA88: 1
A89: 2018 | B89: BVIC | C89: Bank Victoria International Tbk | D89: 28094350409000 | E89: 541283738000 | F89: 30172315337000 | I89: 25808570240000 | J89: 2806025405000 | K89: 14000000000 | L89: 2280212771000 | M89: 1820882197000 | N89: 741051703000 | O89: 79081921000 | Q89: 190 | R89: =D89/I89 -> 1.0885667 | S89: =I89/J89 -> 9.197554 | T89: =O89/F89 -> 0.0026210094 | U89: =O89/J89 -> 0.028182896 | V89: =O89/L89 -> 0.034681817 | W89: =(P89/K89)/Q89 -> 0 | X89: =P89/O89 -> 0 | Y89: =Q89/(O89/K89) -> 33.636006 | Z89: =Q89/(J89/K89) -> 0.94796006 | AA89: 1
A90: 2019 | B90: BVIC | C90: Bank Victoria International Tbk | D90: 28304904517000 | E90: 521735784000 | F90: 30456458802000 | I90: 25782313852000 | J90: 2986454603000 | K90: 14000000000 | L90: 2223204722000 | M90: 1954056503000 | N90: 648356649000 | O90: -13764500000 | Q90: 84 | R90: =D90/I90 -> 1.0978419 | S90: =I90/J90 -> 8.6330841 | T90: =O90/F90 -> -0.00045194026 | U90: =O90/J90 -> -0.0046089768 | V90: =O90/L90 -> -0.0061912877 | W90: =(P90/K90)/Q90 -> 0 | X90: =P90/O90 -> 0 | Y90: =Q90/(O90/K90) -> -85.437175 | Z90: =Q90/(J90/K90) -> 0.39377796 | AA90: 1
A91: 2020 | B91: BVIC | C91: Bank Victoria International Tbk | D91: 23651943876000 | E91: 559673354000 | F91: 26221407472000 | I91: 22197849857000 | J91: 2644375254000 | K91: 14000000000 | L91: 1790640395000 | M91: 1600981946000 | N91: 928353052000 | O91: -252193690000 | Q91: 114 | R91: =D91/I91 -> 1.0655061 | S91: =I91/J91 -> 8.3943645 | T91: =O91/F91 -> -0.0096178548 | U91: =O91/J91 -> -0.095369857 | V91: =O91/L91 -> -0.14083994 | W91: =(P91/K91)/Q91 -> 0 | X91: =P91/O91 -> 0 | Y91: =Q91/(O91/K91) -> -6.3284692 | Z91: =Q91/(J91/K91) -> 0.6035452 | AA91: 1
A92: 2018 | B92: INPC | C92: Bank Artha Graha Internasional Tbk | D92: 22228828000000 | E92: 2053140000000 | F92: 26025188000000 | I92: 21438077000000 | J92: 4587111000000 | K92: 52310000000 | L92: 2263784000000 | M92: 1065854000000 | N92: 1197424000000 | O92: 53621000000 | Q92: 62 | R92: =D92/I92 -> 1.0368854 | S92: =I92/J92 -> 4.6735466 | T92: =O92/F92 -> 0.0020603502 | U92: =O92/J92 -> 0.011689493 | V92: =O92/L92 -> 0.023686447 | W92: =(P92/K92)/Q92 -> 0 | X92: =P92/O92 -> 0 | Y92: =Q92/(O92/K92) -> 60.484139 | Z92: =Q92/(J92/K92) -> 0.70702889 | AA92: 1
A93: 2019 | B93: INPC | C93: Bank Artha Graha Internasional Tbk | D93: 20925424000000 | E93: 2029527000000 | F93: 25532041000000 | I93: 20995806000000 | J93: 4536235000000 | K93: 52310000000 | L93: 1976522000000 | M93: 1049601000000 | N93: 1110037000000 | O93: -58345000000 | Q93: 61 | R93: =D93/I93 -> 0.99664781 | S93: =I93/J93 -> 4.6284652 | T93: =O93/F93 -> -0.0022851679 | U93: =O93/J93 -> -0.012861988 | V93: =O93/L93 -> -0.029519024 | W93: =(P93/K93)/Q93 -> 0 | X93: =P93/O93 -> 0 | Y93: =Q93/(O93/K93) -> -54.690376 | Z93: =Q93/(J93/K93) -> 0.70342696 | AA93: 1
A94: 2020 | B94: INPC | C94: Bank Artha Graha Internasional Tbk | D94: 25019864000000 | E94: 2065208000000 | F94: 30526965000000 | I94: 26967430000000 | J94: 3559535000000 | K94: 52310000000 | L94: 1688028000000 | M94: 1056241000000 | N94: 717238000000 | O94: 21371000000 | Q94: 69 | R94: =D94/I94 -> 0.92778081 | S94: =I94/J94 -> 7.5761104 | T94: =O94/F94 -> 0.00070006959 | U94: =O94/J94 -> 0.0060038741 | V94: =O94/L94 -> 0.012660335 | W94: =(P94/K94)/Q94 -> 0 | X94: =P94/O94 -> 0 | Y94: =Q94/(O94/K94) -> 168.89196 | Z94: =Q94/(J94/K94) -> 1.014006 | AA94: 1
A95: 2018 | B95: MCOR | C95: Bank China Construction Bank Indonesia Tbk | D95: 14724304000000 | E95: 683878000000 | F95: 15992475000000 | I95: 13476317000000 | J95: 2516158000000 | K95: 26000000000 | L95: 1240762000000 | M95: 653396000000 | N95: 470404000000 | O95: 89860000000 | Q95: 142 | R95: =D95/I95 -> 1.0926059 | S95: =I95/J95 -> 5.3559105 | T95: =O95/F95 -> 0.0056188926 | U95: =O95/J95 -> 0.035713179 | V95: =O95/L95 -> 0.072423237 | W95: =(P95/K95)/Q95 -> 0 | X95: =P95/O95 -> 0 | Y95: =Q95/(O95/K95) -> 41.086134 | Z95: =Q95/(J95/K95) -> 1.4673164 | AA95: 1
A96: 2019 | B96: MCOR | C96: Bank China Construction Bank Indonesia Tbk | D96: 17492563000000 | E96: 828752000000 | F96: 18893684000000 | I96: 16098826000000 | J96: 2794858000000 | K96: 26000000000 | L96: 1298866000000 | M96: 738975000000 | N96: 493623000000 | O96: 78967000000 | Q96: 129 | R96: =D96/I96 -> 1.0865738 | S96: =I96/J96 -> 5.7601588 | T96: =O96/F96 -> 0.0041795449 | U96: =O96/J96 -> 0.028254387 | V96: =O96/L96 -> 0.06079688 | W96: =(P96/K96)/Q96 -> 0 | X96: =P96/O96 -> 0 | Y96: =Q96/(O96/K96) -> 42.473438 | Z96: =Q96/(J96/K96) -> 1.200061 | AA96: 1
A97: 2020 | B97: MCOR | C97: Bank China Construction Bank Indonesia Tbk | D97: 23842335000000 | E97: 832249000000 | F97: 25235573000000 | I97: 19218857000000 | J97: 6016716000000 | K97: 26000000000 | L97: 1282612000000 | M97: 720255000000 | N97: 514337000000 | O97: 49979000000 | Q97: 139 | R97: =D97/I97 -> 1.2405699 | S97: =I97/J97 -> 3.1942437 | T97: =O97/F97 -> 0.0019804979 | U97: =O97/J97 -> 0.0083066909 | V97: =O97/L97 -> 0.038966578 | W97: =(P97/K97)/Q97 -> 0 | X97: =P97/O97 -> 0 | Y97: =Q97/(O97/K97) -> 72.31037 | Z97: =Q97/(J97/K97) -> 0.60065989 | AA97: 1
A98: 2018 | B98: NISP | C98: Bank OCBC NISP Tbk | D98: 167124533000000 | E98: 2799661000000 | F98: 173582894000000 | I98: 149154640000000 | J98: 24428254000000 | K98: 50000000000 | L98: 12221471000000 | M98: 5843536000000 | N98: 3512758000000 | O98: 2638064000000 | Q98: 855 | R98: =D98/I98 -> 1.1204783 | S98: =I98/J98 -> 6.1058248 | T98: =O98/F98 -> 0.015197719 | U98: =O98/J98 -> 0.10799233 | V98: =O98/L98 -> 0.21585487 | W98: =(P98/K98)/Q98 -> 0 | X98: =P98/O98 -> 0 | Y98: =Q98/(O98/K98) -> 16.205066 | Z98: =Q98/(J98/K98) -> 1.7500227 | AA98: 1
A99: 2019 | B99: NISP | C99: Bank OCBC NISP Tbk | D99: 174533222000000 | E99: 2784242000000 | F99: 180706987000000 | I99: 153042184000000 | J99: 27664803000000 | K99: 50000000000 | L99: 13496091000000 | M99: 7057159000000 | N99: 3768918000000 | O99: 2939243000000 | Q99: 845 | R99: =D99/I99 -> 1.1404256 | S99: =I99/J99 -> 5.5320178 | T99: =O99/F99 -> 0.016265243 | U99: =O99/J99 -> 0.10624486 | V99: =O99/L99 -> 0.21778476 | W99: =(P99/K99)/Q99 -> 0 | X99: =P99/O99 -> 0 | Y99: =Q99/(O99/K99) -> 14.374449 | Z99: =Q99/(J99/K99) -> 1.5272113 | AA99: 1
A100: 2020 | B100: NISP | C100: Bank OCBC NISP Tbk | D100: 199398374000000 | E100: 3001632000000 | F100: 206297200000000 | I100: 176467884000000 | J100: 29829316000000 | K100: 50000000000 | L100: 12484662000000 | M100: 5658106000000 | N100: 3839552000000 | O100: 2101671000000 | Q100: 820 | R100: =D100/I100 -> 1.1299414 | S100: =I100/J100 -> 5.9159212 | T100: =O100/F100 -> 0.010187589 | U100: =O100/J100 -> 0.07045656 | V100: =O100/L100 -> 0.16834024 | W100: =(P100/K100)/Q100 -> 0 | X100: =P100/O100 -> 0 | Y100: =Q100/(O100/K100) -> 19.508287 | Z100: =Q100/(J100/K100) -> 1.3744868 | AA100: 1
... A109: 2020 | B109: PNBS | C109: Bank Panin Dubai Syariah Tbk | D109: 9947516700000 | E109: 198947537000 | F109: 11302082193000 | I109: 600931510000 | J109: 3115653432000 | K109: 39000000000 | L109: 1399900947000 | M109: 218943558000 | N109: 215546807000 | O109: 128116000 | Q109: 83 | R109: =D109/I109 -> 16.553495 | S109: =I109/J109 -> 0.19287495 | T109: =O109/F109 -> 1.133561e-05 | U109: =O109/J109 -> 4.1120106e-05 | V109: =O109/L109 -> 9.1517904e-05 | W109: =(P109/K109)/Q109 -> 0 | X109: =P109/O109 -> 0 | Y109: =Q109/(O109/K109) -> 25266.165 | Z109: =Q109/(J109/K109) -> 1.0389474 | AA109: 1
A110: 2018 | B110: SDRA | C110: Bank Woori Saudara Indonesia 1906 Tbk | D110: 26920081000000 | E110: 355058000000 | F110: 29631693000000 | I110: 23081225000000 | J110: 6550468000000 | K110: 15000000000 | L110: 2214687000000 | M110: 924860000000 | N110: 817755000000 | O110: 537971000000 | P110: 98714000000 | Q110: 860 | R110: =D110/I110 -> 1.1663194 | S110: =I110/J110 -> 3.5235994 | T110: =O110/F110 -> 0.018155257 | U110: =O110/J110 -> 0.082127109 | V110: =O110/L110 -> 0.24291062 | W110: =(P110/K110)/Q110 -> 0.0076522481 | X110: =P110/O110 -> 0.18349316 | Y110: =Q110/(O110/K110) -> 23.978988 | Z110: =Q110/(J110/K110) -> 1.9693249 | AA110: 1
A111: 2019 | B111: SDRA | C111: Bank Woori Saudara Indonesia 1906 Tbk | D111: 34227611000000 | E111: 370993000000 | F111: 36936262000000 | I111: 30000672000000 | J111: 6935590000000 | K111: 15000000000 | L111: 2438993000000 | M111: 1325908000000 | N111: 772982000000 | O111: 499791000000 | P111: 98714000000 | Q111: 830 | R111: =D111/I111 -> 1.1408948 | S111: =I111/J111 -> 4.3256121 | T111: =O111/F111 -> 0.013531174 | U111: =O111/J111 -> 0.072061786 | V111: =O111/L111 -> 0.20491695 | W111: =(P111/K111)/Q111 -> 0.0079288353 | X111: =P111/O111 -> 0.19751056 | Y111: =Q111/(O111/K111) -> 24.910413 | Z111: =Q111/(J111/K111) -> 1.7950888 | AA111: 1
A112: 2020 | B112: SDRA | C112: Bank Woori Saudara Indonesia 1906 Tbk | D112: 35164985000000 | E112: 448354000000 | F112: 38053939000000 | I112: 30782968000000 | J112: 7270971000000 | K112: 15000000000 | L112: 2425276000000 | M112: 1178215000000 | N112: 812041000000 | O112: 536001000000 | P112: 85552000000 | Q112: 740 | R112: =D112/I112 -> 1.142352 | S112: =I112/J112 -> 4.2336805 | T112: =O112/F112 -> 0.014085296 | U112: =O112/J112 -> 0.073717939 | V112: =O112/L112 -> 0.22100619 | W112: =(P112/K112)/Q112 -> 0.0077073874 | X112: =P112/O112 -> 0.15961164 | Y112: =Q112/(O112/K112) -> 20.708917 | Z112: =Q112/(J112/K112) -> 1.5266187 | AA112: 1
A113: 2018 | B113: APIC | C113: Pacific Strategic Financial Tbk | D113: 2520428991187 | E113: 182238112107 | F113: 2896589814278 | I113: 1167083160521 | J113: 1729506653757 | K113: 12902280000 | L113: 473564916412 | M113: 359305382036 | N113: 144391182125 | O113: 70399722671 | Q113: 540 | R113: =D113/I113 -> 2.1595967 | S113: =I113/J113 -> 0.67480698 | T113: =O113/F113 -> 0.024304347 | U113: =O113/J113 -> 0.040705089 | V113: =O113/L113 -> 0.14865908 | W113: =(P113/K113)/Q113 -> 0 | X113: =P113/O113 -> 0 | Y113: =Q113/(O113/K113) -> 98.966742 | Z113: =Q113/(J113/K113) -> 4.0284501 | AA113: 1
A114: 2019 | B114: APIC | C114: Pacific Strategic Financial Tbk | D114: 3328927878165 | E114: 179433881039 | F114: 3652947899746 | I114: 1818115863373 | J114: 1834832036373 | K114: 12902280000 | L114: 1193590630021 | M114: 1009410116496 | N114: 120227476034 | O114: 102897273401 | Q114: 690 | R114: =D114/I114 -> 1.8309768 | S114: =I114/J114 -> 0.99088954 | T114: =O114/F114 -> 0.028168284 | U114: =O114/J114 -> 0.056079942 | V114: =O114/L114 -> 0.086208178 | W114: =(P114/K114)/Q114 -> 0 | X114: =P114/O114 -> 0 | Y114: =Q114/(O114/K114) -> 86.519039 | Z114: =Q114/(J114/K114) -> 4.8519826 | AA114: 1
A115: 2020 | B115: APIC | C115: Pacific Strategic Financial Tbk | D115: 4201191401871 | E115: 190479472617 | F115: 4881911874208 | I115: 2920986089935 | J115: 1960925784273 | K115: 12902280000 | L115: 2275473702348 | M115: 2062436886511 | N115: 153728295937 | O115: 124726300324 | Q115: 785 | R115: =D115/I115 -> 1.4382785 | S115: =I115/J115 -> 1.4895954 | T115: =O115/F115 -> 0.025548659 | U115: =O115/J115 -> 0.063605824 | V115: =O115/L115 -> 0.054813334 | W115: =(P115/K115)/Q115 -> 0 | X115: =P115/O115 -> 0 | Y115: =Q115/(O115/K115) -> 81.204123 | Z115: =Q115/(J115/K115) -> 5.1650551 | AA115: 1
A116: 2018 | B116: ARTA | C116: Arthavest Tbk | D116: 73149118953 | E116: 265730271470 | F116: 431672804838 | H116: 54497512512 | I116: 63912279502 | J116: 367760525336 | K116: 850000000 | L116: 87440977373 | M116: 27307815715 | N116: 56739467276 | O116: 7498492703 | Q116: 1310 | R116: =D116/I116 -> 1.1445237 | S116: =I116/J116 -> 0.17378776 | T116: =O116/F116 -> 0.017370779 | U116: =O116/J116 -> 0.020389607 | V116: =O116/L116 -> 0.085754905 | W116: =(P116/K116)/Q116 -> 0 | X116: =P116/O116 -> 0 | Y116: =Q116/(O116/K116) -> 148.49651 | Z116: =Q116/(J116/K116) -> 3.0277855 | AA116: 1
A117: 2019 | B117: ARTA | C117: Arthavest Tbk | D117: 85188330002 | E117: 259633756608 | F117: 439070378556 | H117: 54263912675 | I117: 66308261273 | J117: 372762117283 | K117: 850000000 | L117: 85726802073 | M117: 26800834114 | N117: 62778284141 | O117: 628762882 | Q117: 450 | R117: =D117/I117 -> 1.2847318 | S117: =I117/J117 -> 0.17788358 | T117: =O117/F117 -> 0.0014320321 | U117: =O117/J117 -> 0.0016867671 | V117: =O117/L117 -> 0.0073344959 | W117: =(P117/K117)/Q117 -> 0 | X117: =P117/O117 -> 0 | Y117: =Q117/(O117/K117) -> 608.33744 | Z117: =Q117/(J117/K117) -> 1.0261236 | AA117: 1
A118: 2020 | B118: ARTA | C118: Arthavest Tbk | D118: 93732057163 | E118: 241844455384 | F118: 394280340197 | H118: 41284563811 | I118: 51589144973 | J118: 342691195224 | K118: 850000000 | L118: 32934176030 | M118: 12471168816 | N118: 41357026843 | O118: -11209268817 | Q118: 256 | R118: =D118/I118 -> 1.816895 | S118: =I118/J118 -> 0.1505412 | T118: =O118/F118 -> -0.028429692 | U118: =O118/J118 -> -0.032709533 | V118: =O118/L118 -> -0.3403537 | W118: =(P118/K118)/Q118 -> 0 | X118: =P118/O118 -> 0 | Y118: =Q118/(O118/K118) -> -19.412506 | Z118: =Q118/(J118/K118) -> 0.634974 | AA118: 1
A119: 2018 | B119: DYAN | C119: Dyandra Media International Tbk | D119: 397576606710 | E119: 668004938529 | F119: 1229926003723 | H119: 140926455842 | I119: 416632326814 | J119: 813293676909 | K119: 10000000000 | L119: 1035508850963 | M119: 694804974807 | N119: 239999883906 | O119: 80315046464 | P119: 3457187223 | Q119: 77 | R119: =D119/I119 -> 0.9542625 | S119: =I119/J119 -> 0.51227784 | T119: =O119/F119 -> 0.065300714 | U119: =O119/J119 -> 0.098752823 | V119: =O119/L119 -> 0.077560946 | W119: =(P119/K119)/Q119 -> 0.0044898535 | X119: =P119/O119 -> 0.043045324 | Y119: =Q119/(O119/K119) -> 9.5872447 | Z119: =Q119/(J119/K119) -> 0.94676747 | AA119: 1
A120: 2019 | B120: DYAN | C120: Dyandra Media International Tbk | D120: 415197995568 | E120: 623057370408 | F120: 1215041391937 | H120: 108411097142 | I120: 390067438922 | J120: 824973953015 | K120: 10000000000 | L120: 980145831991 | M120: 682255151407 | N120: 254608244796 | O120: 20100336037 | P120: 12151609257 | Q120: 128 | R120: =D120/I120 -> 1.0644262 | S120: =I120/J120 -> 0.47282394 | T120: =O120/F120 -> 0.016542923 | U120: =O120/J120 -> 0.024364813 | V120: =O120/L120 -> 0.020507495 | W120: =(P120/K120)/Q120 -> 0.0094934447 | X120: =P120/O120 -> 0.60454757 | Y120: =Q120/(O120/K120) -> 63.680527 | Z120: =Q120/(J120/K120) -> 1.5515641 | AA120: 1
A121: 2020 | B121: DYAN | C121: Dyandra Media International Tbk | D121: 264413829825 | E121: 580933225999 | F121: 1043313799003 | H121: 163009184592 | I121: 466243114050 | J121: 577070684953 | K121: 10000000000 | L121: 284181538459 | M121: 237921357900 | N121: 235610486134 | O121: -256092630622 | P121: 28040000 | Q121: 55 | R121: =D121/I121 -> 0.56711579 | S121: =I121/J121 -> 0.80794801 | T121: =O121/F121 -> -0.24546079 | U121: =O121/J121 -> -0.44378035 | V121: =O121/L121 -> -0.90115858 | W121: =(P121/K121)/Q121 -> 5.0981818e-05 | X121: =P121/O121 -> -0.00010949163 | Y121: =Q121/(O121/K121) -> -2.1476604 | Z121: =Q121/(J121/K121) -> 0.95308948 | AA121: 1
A122: 2018 | B122: GEMA | C122: Gema Grahasarana Tbk | D122: 587179039123 | E122: 313507248253 | F122: 986798686383 | H122: 106701019905 | I122: 560755293708 | J122: 426043392675 | K122: 4000000000 | L122: 1176679314139 | M122: 947170542507 | N122: 159317990074 | O122: 21618512703 | P122: 8000000000 | Q122: 316 | R122: =D122/I122 -> 1.0471217 | S122: =I122/J122 -> 1.3161929 | T122: =O122/F122 -> 0.021907723 | U122: =O122/J122 -> 0.050742514 | V122: =O122/L122 -> 0.018372476 | W122: =(P122/K122)/Q122 -> 0.0063291139 | X122: =P122/O122 -> 0.37005321 | Y122: =Q122/(O122/K122) -> 58.468407 | Z122: =Q122/(J122/K122) -> 2.9668339 | AA122: 1
A123: 2019 | B123: GEMA | C123: Gema Grahasarana Tbk | D123: 553095462520 | E123: 297319143583 | F123: 962025149261 | H123: 106816001403 | I123: 553754286838 | J123: 408270862423 | K123: 4000000000 | L123: 1187269670295 | M123: 891846999972 | N123: 211484755362 | O123: 32133014664 | P123: 8000000000 | Q123: 338 | R123: =D123/I123 -> 0.99881026 | S123: =I123/J123 -> 1.3563405 | T123: =O123/F123 -> 0.033401429 | U123: =O123/J123 -> 0.078705138 | V123: =O123/L123 -> 0.02706463 | W123: =(P123/K123)/Q123 -> 0.0059171598 | X123: =P123/O123 -> 0.24896512 | Y123: =Q123/(O123/K123) -> 42.075106 | Z123: =Q123/(J123/K123) -> 3.311527 | AA123: 1
A124: 2020 | B124: GEMA | C124: Gema Grahasarana Tbk | D124: 505972668218 | E124: 385727013711 | F124: 972015359252 | H124: 151749817514 | I124: 601172001077 | J124: 370843358175 | K124: 4000000000 | L124: 984347363283 | M124: 745766889459 | N124: 189978072198 | O124: 1599783419 | P124: 8000000000 | Q124: 346 | R124: =D124/I124 -> 0.84164377 | S124: =I124/J124 -> 1.6210942 | T124: =O124/F124 -> 0.0016458417 | U124: =O124/J124 -> 0.0043139061 | V124: =O124/L124 -> 0.0016252224 | W124: =(P124/K124)/Q124 -> 0.0057803468 | X124: =P124/O124 -> 5.0006769 | Y124: =Q124/(O124/K124) -> 865.1171 | Z124: =Q124/(J124/K124) -> 3.7320339 | AA124: 1
A125: 2018 | B125: LPPS | C125: Lippo Securities Tbk | D125: 179359221655 | E125: 604523211 | F125: 1262027127785 | I125: 12074906518 | J125: 1249952221267 | K125: 34386750000 | L125: 3309695977 | M125: 4326032844 | N125: 38942653627 | O125: 36602219324 | Q125: 102 | R125: =D125/I125 -> 14.853881 | S125: =I125/J125 -> 0.0096602945 | T125: =O125/F125 -> 0.02900272 | U125: =O125/J125 -> 0.029282895 | V125: =O125/L125 -> 11.059088 | W125: =(P125/K125)/Q125 -> 0 | X125: =P125/O125 -> 0 | Y125: =Q125/(O125/K125) -> 95.826116 | Z125: =Q125/(J125/K125) -> 2.8060661 | AA125: 1
A126: 2019 | B126: LPPS | C126: Lippo Securities Tbk | D126: 167434324974 | E126: 544048165 | F126: 1093765589044 | I126: 12322265710 | J126: 1081443323334 | K126: 34386750000 | L126: 2864926016 | M126: 6271926871 | N126: 38109266181 | O126: -40516442135 | Q126: 80 | R126: =D126/I126 -> 13.58795 | S126: =I126/J126 -> 0.011394278 | T126: =O126/F126 -> -0.037043076 | U126: =O126/J126 -> -0.037465155 | V126: =O126/L126 -> -14.14223 | W126: =(P126/K126)/Q126 -> 0 | X126: =P126/O126 -> 0 | Y126: =Q126/(O126/K126) -> -67.89688 | Z126: =Q126/(J126/K126) -> 2.5437671 | AA126: 1
A127: 2020 | B127: LPPS | C127: Lippo Securities Tbk | D127: 80574942090 | E127: 488353479 | F127: 1098807182384 | I127: 4057590748 | J127: 1094749591636 | K127: 34386750000 | L127: 60000000 | M127: 0 | N127: 10339109764 | O127: 15645276591 | Q127: 88 | R127: =D127/I127 -> 19.857829 | S127: =I127/J127 -> 0.0037064099 | T127: =O127/F127 -> 0.014238419 | U127: =O127/J127 -> 0.014291192 | V127: =O127/L127 -> 260.75461 | W127: =(P127/K127)/Q127 -> 0 | X127: =P127/O127 -> 0 | Y127: =Q127/(O127/K127) -> 193.41518 | Z127: =Q127/(J127/K127) -> 2.7641335 | AA127: 1
...

Sheet commodities
A1: Year | B1: Code | C1: Company Name | D1: Current Assets | E1: Fixed Assets | F1: Total Assets | G1: Current liabilities | H1: Long-Term Liabilities | I1: Total Liabilities | J1: Total Equity | K1: Total outstanding shares | L1: Total Sales/ Revenue | M1: COGS/ Cost of Revenues | N1: Expenses (Income) | O1: Net Income | P1: Dividend | Q1: Price | R1: CR | S1: DER | T1: ROA | U1: ROE | V1: NPM | W1: DY | X1: DPR | Y1: PER | Z1: PBV | AA1: Industri
A2: 2018 | B2: PGAS | C2: Perusahaan Gas Negara (Persero) Tbk | D2: 35820328250826 | E2: 41436061933356 | F2: 114968614731327 | G2: 23235117344046 | H2: 45366918001290 | I2: 68602035345336 | J2: 46366579385991 | K2: 70000000000 | L2: 56045332632978 | M2: 37082460251259 | N2: 10515185697510 | O2: 5280332435460 | P2: 796583982267 | Q2: 2130 | R2: =D2/G2 -> 1.5416461 | S2: =H2/J2 -> 0.97844004 | T2: =O2/F2 -> 0.045928469 | U2: =O2/J2 -> 0.11388229 | V2: =O2/L2 -> 0.094215382 | W2: =(P2/K2)/Q2 -> 0.0053426156 | X2: =P2/O2 -> 0.15085868 | Y2: =Q2/(O2/K2) -> 28.236859 | Z2: =Q2/(J2/K2) -> 3.2156782 | AA2: 2
A3: 2019 | B3: PGAS | C3: Perusahaan Gas Negara (Persero) Tbk | D3: 30852713195881 | E3: 38195772167402 | F3: 102501986581556 | G3: 15615845389597 | H3: 41926124645178 | I3: 57541970034775 | J3: 44960016546781 | K3: 70000000000 | L3: 53501024525284 | M3: 36439368501116 | N3: 10330208510406 | O3: 1570551591695 | P3: 1353577596878 | Q3: 2170 | R3: =D3/G3 -> 1.9757312 | S3: =H3/J3 -> 0.93252022 | T3: =O3/F3 -> 0.015322158 | U3: =O3/J3 -> 0.034932184 | V3: =O3/L3 -> 0.029355542 | W3: =(P3/K3)/Q3 -> 0.0089109783 | X3: =P3/O3 -> 0.86184854 | Y3: =Q3/(O3/K3) -> 96.717612 | Z3: =Q3/(J3/K3) -> 3.3785575 | AA3: 2
A4: 2020 | B4: PGAS | C4: Perusahaan Gas Negara (Persero) Tbk | D4: 28291608511530 | E4: 38050883273585 | F4: 106266878101475 | G4: 16688406014280 | H4: 47892007037420 | I4: 64580413051700 | J4: 41686465049775 | K4: 70000000000 | L4: 40700486761025 | M4: 28648929334025 | N4: 8359448650280 | O4: -2473389962225 | P4: 953146912445 | Q4: 1655 | R4: =D4/G4 -> 1.6952852 | S4: =H4/J4 -> 1.1488623 | T4: =O4/F4 -> -0.023275267 | U4: =O4/J4 -> -0.059333166 | V4: =O4/L4 -> -0.060770525 | W4: =(P4/K4)/Q4 -> 0.0082274226 | X4: =P4/O4 -> -0.38536055 | Y4: =Q4/(O4/K4) -> -46.83855 | Z4: =Q4/(J4/K4) -> 2.7790795 | AA4: 2
A5: 2018 | B5: RAJA | C5: Rukun Raharja Tbk | D5: 968326542522 | E5: 799069023234 | F5: 2767379051340 | G5: 258247232082 | H5: 601184420514 | I5: 859431652596 | J5: 1907947398744 | K5: 4227082500 | L5: 1710322585164 | M5: 1413357025509 | N5: 222397112736 | O5: 180054987318 | P5: 47384597871 | Q5: 472 | R5: =D5/G5 -> 3.7496105 | S5: =H5/J5 -> 0.31509486 | T5: =O5/F5 -> 0.065063363 | U5: =O5/J5 -> 0.094371044 | V5: =O5/L5 -> 0.10527545 | W5: =(P5/K5)/Q5 -> 0.0237495 | X5: =P5/O5 -> 0.26316737 | Y5: =Q5/(O5/K5) -> 11.080965 | Z5: =Q5/(J5/K5) -> 1.0457222 | AA5: 2
A6: 2019 | B6: RAJA | C6: Rukun Raharja Tbk | D6: 984042226112 | E6: 803461591434 | F6: 2508297621585 | G6: 326901962935 | H6: 475724956855 | I6: 802626919790 | J6: 1705670701795 | K6: 4227082500 | L6: 1697756320356 | M6: 1460057977986 | N6: 215576318772 | O6: 88096225202 | P6: 32799770926 | Q6: 189 | R6: =D6/G6 -> 3.0102059 | S6: =H6/J6 -> 0.27890786 | T6: =O6/F6 -> 0.035121919 | U6: =O6/J6 -> 0.051649023 | V6: =O6/L6 -> 0.051889794 | W6: =(P6/K6)/Q6 -> 0.04105521 | X6: =P6/O6 -> 0.37231755 | Y6: =Q6/(O6/K6) -> 9.068704 | Z6: =Q6/(J6/K6) -> 0.4683897 | AA6: 2
A7: 2020 | B7: RAJA | C7: Rukun Raharja Tbk | D7: 2350514170095 | E7: 745978102870 | F7: 2350514155990 | G7: 307596000530 | H7: 304525088140 | I7: 612121088670 | J7: 1738393081425 | K7: 4227082500 | L7: 1393076432020 | M7: 1166087107185 | N7: 44814815045 | O7: 85004671115 | P7: 27326152490 | Q7: 252 | R7: =D7/G7 -> 7.6415628 | S7: =H7/J7 -> 0.1751762 | T7: =O7/F7 -> 0.036164288 | U7: =O7/J7 -> 0.048898418 | V7: =O7/L7 -> 0.061019388 | W7: =(P7/K7)/Q7 -> 0.025652945 | X7: =P7/O7 -> 0.32146648 | Y7: =Q7/(O7/K7) -> 12.531368 | Z7: =Q7/(J7/K7) -> 0.61276405 | AA7: 2
A8: 2018 | B8: CTBN | C8: Citra Tubindo Tbk | D8: 2254015683477 | E8: 672401254464 | F8: 2254015683477 | G8: 714813569289 | H8: 109402434495 | I8: 824216003784 | J8: 1429799679693 | K8: 3200000000 | L8: 1239476562819 | M8: 1055003147262 | N8: 289740496401 | O8: 83913832674 | P8: 0 | Q8: 4300 | R8: =D8/G8 -> 3.1532917 | S8: =H8/J8 -> 0.076515918 | T8: =O8/F8 -> 0.037228593 | U8: =O8/J8 -> 0.058689223 | V8: =O8/L8 -> 0.067701024 | W8: =(P8/K8)/Q8 -> 0 | X8: =P8/O8 -> 0 | Y8: =Q8/(O8/K8) -> 163.97773 | Z8: =Q8/(J8/K8) -> 9.6237258 | AA8: 2
A9: 2019 | B9: CTBN | C9: Citra Tubindo Tbk | D9: 2395446398276 | E9: 617721642309 | F9: 2395446398276 | G9: 852416965550 | H9: 132771272903 | I9: 985188238453 | J9: 1410258159823 | K9: 3200000000 | L9: 1995615229813 | M9: 1631562719269 | N9: 314445540954 | O9: 22867965159 | P9: 252928695 | Q9: 3150 | R9: =D9/G9 -> 2.8101815 | S9: =H9/J9 -> 0.094146786 | T9: =O9/F9 -> 0.0095464316 | U9: =O9/J9 -> 0.016215446 | V9: =O9/L9 -> 0.011459105 | W9: =(P9/K9)/Q9 -> 2.5092132e-05 | X9: =P9/O9 -> 0.011060394 | Y9: =Q9/(O9/K9) -> 440.7913 | Z9: =Q9/(J9/K9) -> 7.1476275 | AA9: 2
A10: 2020 | B10: CTBN | C10: Citra Tubindo Tbk | D10: 1074198843445 | E10: 603761986100 | F10: 1839922465290 | G10: 321104528290 | H10: 117549095300 | I10: 438653623590 | J10: 1401268841700 | K10: 3200000000 | L10: 1779978175885 | M10: 1493795681105 | N10: 281118009900 | O10: -43122327885 | P10: 81061435 | Q10: 3220 | R10: =D10/G10 -> 3.3453245 | S10: =H10/J10 -> 0.083887611 | T10: =O10/F10 -> -0.023437035 | U10: =O10/J10 -> -0.030773772 | V10: =O10/L10 -> -0.024226324 | W10: =(P10/K10)/Q10 -> 7.8669871e-06 | X10: =P10/O10 -> -0.0018798019 | Y10: =Q10/(O10/K10) -> -238.94814 | Z10: =Q10/(J10/K10) -> 7.3533356 | AA10: 2
A11: 2018 | B11: ISSP | C11: Steel Pipe Industry of Indonesia Tbk | D11: 3640720000000 | E11: 2197050000000 | F11: 6494070000000 | G11: =I11-H11 -> 2579383000000 | H11: 999271000000 | I11: 3578654000000 | J11: 2915416000000 | K11: 17000000000 | L11: 4467590000000 | M11: 3935894000000 | N11: =110556000000+149591000000+257413000000+67212000000 -> 584772000000 | O11: 48741000000 | P11: 0 | Q11: 87 | R11: =D11/G11 -> 1.4114693 | S11: =H11/J11 -> 0.34275417 | T11: =O11/F11 -> 0.0075054627 | U11: =O11/J11 -> 0.016718369 | V11: =O11/L11 -> 0.010909909 | W11: =(P11/K11)/Q11 -> 0 | X11: =P11/O11 -> 0 | Y11: =Q11/(O11/K11) -> 30.344064 | Z11: =Q11/(J11/K11) -> 0.50730325 | AA11: 2
A12: 2019 | B12: ISSP | C12: Steel Pipe Industry of Indonesia Tbk | D12: 3547289000000 | E12: 2128844000000 | F12: 6424507000000 | G12: =I12-H12 -> 2542901000000 | H12: 782940000000 | I12: 3325841000000 | J12: 3098666000000 | K12: 17000000000 | L12: 4885875000000 | M12: 4197484000000 | N12: =149742000000+147856000000+261675000000+19267000000 -> 578540000000 | O12: 185694000000 | P12: 0 | Q12: 184 | R12: =D12/G12 -> 1.3949772 | S12: =H12/J12 -> 0.25267002 | T12: =O12/F12 -> 0.028904008 | U12: =O12/J12 -> 0.059927078 | V12: =O12/L12 -> 0.038006294 | W12: =(P12/K12)/Q12 -> 0 | X12: =P12/O12 -> 0 | Y12: =Q12/(O12/K12) -> 16.844917 | Z12: =Q12/(J12/K12) -> 1.0094667 | AA12: 2
A13: 2020 | B13: ISSP | C13: Steel Pipe Industry of Indonesia Tbk | D13: 3113612000000 | E13: 2197790000000 | F13: 6076604000000 | G13: =I13-H13 -> 2162323000000 | H13: 578941000000 | I13: 2741264000000 | J13: 3335340000000 | K13: 17000000000 | L13: 3775530000000 | M13: 3217408000000 | N13: =111101000000+130681000000+205664000000+27162000000 -> 474608000000 | O13: 175835000000 | P13: 0 | Q13: 160 | R13: =D13/G13 -> 1.4399384 | S13: =H13/J13 -> 0.17357781 | T13: =O13/F13 -> 0.028936393 | U13: =O13/J13 -> 0.052718763 | V13: =O13/L13 -> 0.046572269 | W13: =(P13/K13)/Q13 -> 0 | X13: =P13/O13 -> 0 | Y13: =Q13/(O13/K13) -> 15.469048 | Z13: =Q13/(J13/K13) -> 0.81550906 | AA13: 2
A14: 2018 | B14: NIKL | C14: Pelat Timah Nusantara Tbk | D14: 1633538255625 | E14: 438353322849 | F14: 2139961806972 | G14: 1485155286090 | H14: 31348266066 | I14: 1516503552156 | J14: 623458254816 | K14: 8000000000 | L14: 2362363017831 | M14: 2241184156263 | N14: 97572413241 | O14: -22261091022 | P14: 0 | Q14: 3500 | R14: =D14/G14 -> 1.0999107 | S14: =H14/J14 -> 0.050281259 | T14: =O14/F14 -> -0.010402565 | U14: =O14/J14 -> -0.035705824 | V14: =O14/L14 -> -0.0094232304 | W14: =(P14/K14)/Q14 -> 0 | X14: =P14/O14 -> 0 | Y14: =Q14/(O14/K14) -> -1257.8 | Z14: =Q14/(J14/K14) -> 44.910786 | AA14: 2
A15: 2019 | B15: NIKL | C15: Pelat Timah Nusantara Tbk | D15: 1635991007928 | E15: 405386814321 | F15: 2108628483178 | G15: 1437911697143 | H15: 36286808974 | I15: 1474198506117 | J15: 634429977061 | K15: 8000000000 | L15: 2267048602389 | M15: 2120573320557 | N15: 101630628030 | O15: 37263938066 | P15: 0 | Q15: 675 | R15: =D15/G15 -> 1.1377549 | S15: =H15/J15 -> 0.057195924 | T15: =O15/F15 -> 0.017672121 | U15: =O15/J15 -> 0.058736093 | V15: =O15/L15 -> 0.016437203 | W15: =(P15/K15)/Q15 -> 0 | X15: =P15/O15 -> 0 | Y15: =Q15/(O15/K15) -> 144.91222 | Z15: =Q15/(J15/K15) -> 8.5115776 | AA15: 2
A16: 2020 | B16: NIKL | C16: Pelat Timah Nusantara Tbk | D16: 1398292277655 | E16: 385936891340 | F16: 1860803648340 | G16: 1134888102530 | H16: 43444020620 | I16: 1178332123150 | J16: 682471525190 | K16: 8000000000 | L16: 2041413970050 | M16: 1903450256890 | N16: 100600541405 | O16: 38338476085 | P16: 0 | Q16: 1445 | R16: =D16/G16 -> 1.232097 | S16: =H16/J16 -> 0.063656899 | T16: =O16/F16 -> 0.020603182 | U16: =O16/J16 -> 0.056175935 | V16: =O16/L16 -> 0.018780354 | W16: =(P16/K16)/Q16 -> 0 | X16: =P16/O16 -> 0 | Y16: =Q16/(O16/K16) -> 301.52477 | Z16: =Q16/(J16/K16) -> 16.938436 | AA16: 2
A17: 2018 | B17: SRSN | C17: Indo Acidatama Tbk | D17: 448247260 | E17: 224257888000 | F17: 686777211000 | G17: =I17-H17 -> 182749220000 | H17: 26239975000 | I17: 208989195000 | J17: 477788016000 | K17: 12000000000 | L17: 600986872000 | M17: 458091261000 | N17: =83109088000+762203000 -> 83871291000 | O17: 38735092000 | P17: 0 | Q17: 66 | R17: =D17/G17 -> 0.0024527999 | S17: =H17/J17 -> 0.054919701 | T17: =O17/F17 -> 0.056401248 | U17: =O17/J17 -> 0.081071711 | V17: =O17/L17 -> 0.064452476 | W17: =(P17/K17)/Q17 -> 0 | X17: =P17/O17 -> 0 | Y17: =Q17/(O17/K17) -> 20.446576 | Z17: =Q17/(J17/K17) -> 1.6576389 | AA17: 2
A18: 2019 | B18: SRSN | C18: Indo Acidatama Tbk | D18: 537425364 | E18: 228818788000 | F18: 779246858000 | G18: =I18-H18 -> 217673718000 | H18: 46972577000 | I18: 264646295000 | J18: 514600563000 | K18: 12000000000 | L18: 684464392000 | M18: 511519472000 | N18: =102044774000+1425442000 -> 103470216000 | O18: 42829128000 | P18: 6017384000 | Q18: 68 | R18: =D18/G18 -> 0.0024689493 | S18: =H18/J18 -> 0.091279684 | T18: =O18/F18 -> 0.054962208 | U18: =O18/J18 -> 0.083227907 | V18: =O18/L18 -> 0.062573201 | W18: =(P18/K18)/Q18 -> 0.0073742451 | X18: =P18/O18 -> 0.14049747 | Y18: =Q18/(O18/K18) -> 19.052454 | Z18: =Q18/(J18/K18) -> 1.5856959 | AA18: 2
A19: 2020 | B19: SRSN | C19: Indo Acidatama Tbk | D19: 579393962 | E19: 319819738000 | F19: 906846895000 | G19: =I19-H19 -> 266837335000 | H19: 52122162000 | I19: 318959497000 | J19: 587887398000 | K19: 12000000000 | L19: 890996866000 | M19: 699831445000 | N19: =111840300000+341413000 -> 112181713000 | O19: 44152245000 | P19: 12034736000 | Q19: 58 | R19: =D19/G19 -> 0.0021713377 | S19: =H19/J19 -> 0.088660111 | T19: =O19/F19 -> 0.048687651 | U19: =O19/J19 -> 0.075103234 | V19: =O19/L19 -> 0.04955376 | W19: =(P19/K19)/Q19 -> 0.017291287 | X19: =P19/O19 -> 0.27257359 | Y19: =Q19/(O19/K19) -> 15.763638 | Z19: =Q19/(J19/K19) -> 1.1839002 | AA19: 2
A20: 2018 | B20: BIPI | C20: Benakat Integra Tbk | D20: 4089272082471 | E20: 1399191392727 | F20: 17634327314985 | G20: 6994044023535 | H20: 5328040524390 | I20: 12322084547925 | J20: 5312242767060 | K20: 92000000000 | L20: 393305654277 | M20: 128270496888 | N20: 1426748344740 | O20: 316519688385 | P20: 0 | Q20: 50 | R20: =D20/G20 -> 0.5846792 | S20: =H20/J20 -> 1.0029738 | T20: =O20/F20 -> 0.017949065 | U20: =O20/J20 -> 0.059583062 | V20: =O20/L20 -> 0.8047677 | W20: =(P20/K20)/Q20 -> 0 | X20: =P20/O20 -> 0 | Y20: =Q20/(O20/K20) -> 14.533061 | Z20: =Q20/(J20/K20) -> 0.86592428 | AA20: 2
A21: 2019 | B21: BIPI | C21: Benakat Integra Tbk | D21: 4871941173051 | E21: 1270778472835 | F21: 17425618108707 | G21: 4174579395048 | H21: 8198421378258 | I21: 12373000773306 | J21: 5052617335401 | K21: 92000000000 | L21: 985413740475 | M21: 177307046485 | N21: 950520923781 | O21: 381395703966 | P21: 0 | Q21: 50 | R21: =D21/G21 -> 1.1670496 | S21: =H21/J21 -> 1.6226088 | T21: =O21/F21 -> 0.021887069 | U21: =O21/J21 -> 0.075484779 | V21: =O21/L21 -> 0.38704119 | W21: =(P21/K21)/Q21 -> 0 | X21: =P21/O21 -> 0 | Y21: =Q21/(O21/K21) -> 12.060964 | Z21: =Q21/(J21/K21) -> 0.91041923 | AA21: 2
A22: 2020 | B22: BIPI | C22: Benakat Integra Tbk | D22: 2743346826675 | E22: 1759004633295 | F22: 18952683723610 | G22: 7215807323270 | H22: 6298449154270 | I22: 13514256477540 | J22: 5438427246070 | K22: 92000000000 | L22: 1107410335395 | M22: 187898445735 | N22: 929563916645 | O22: 381477285280 | P22: 0 | Q22: 50 | R22: =D22/G22 -> 0.38018571 | S22: =H22/J22 -> 1.158138 | T22: =O22/F22 -> 0.020127877 | U22: =O22/J22 -> 0.07014478 | V22: =O22/L22 -> 0.34447691 | W22: =(P22/K22)/Q22 -> 0 | X22: =P22/O22 -> 0 | Y22: =Q22/(O22/K22) -> 12.058385 | Z22: =Q22/(J22/K22) -> 0.84583277 | AA22: 2
A23: 2018 | B23: ELSA | C23: Elnusa Tbk | D23: 5657327000000 | E23: 1735854000000 | F23: 5657327000000 | G23: =I23-H23 -> 2116898000000 | H23: 240229000000 | I23: 2357127000000 | J23: 3300200000000 | K23: 22500000000 | L23: 6624774000000 | M23: 5972680000000 | N23: =2579000000+268740000000+90092000000 -> 361411000000 | O23: 276316000000 | P23: 37071000000 | Q23: 360 | R23: =D23/G23 -> 2.6724608 | S23: =H23/J23 -> 0.072792255 | T23: =O23/F23 -> 0.048842148 | U23: =O23/J23 -> 0.083727047 | V23: =O23/L23 -> 0.041709498 | W23: =(P23/K23)/Q23 -> 0.0045766667 | X23: =P23/O23 -> 0.13416161 | Y23: =Q23/(O23/K23) -> 29.314263 | Z23: =Q23/(J23/K23) -> 2.4543967 | AA23: 2
A24: 2019 | B24: ELSA | C24: Elnusa Tbk | D24: 6805037000000 | E24: 1819321000000 | F24: 6805037000000 | G24: =I24-H24 -> 2504335000000 | H24: 724004000000 | I24: 3228339000000 | J24: 3576698000000 | K24: 22500000000 | L24: 8385122000000 | M24: 7514040000000 | N24: =4180000000+333221000000+40490000000+15705000000 -> 393596000000 | O24: 356477000000 | P24: 69079000000 | Q24: 306 | R24: =D24/G24 -> 2.717303 | S24: =H24/J24 -> 0.20242246 | T24: =O24/F24 -> 0.052384285 | U24: =O24/J24 -> 0.099666508 | V24: =O24/L24 -> 0.042513037 | W24: =(P24/K24)/Q24 -> 0.010033261 | X24: =P24/O24 -> 0.19378249 | Y24: =Q24/(O24/K24) -> 19.314009 | Z24: =Q24/(J24/K24) -> 1.9249598 | AA24: 2
A25: 2020 | B25: ELSA | C25: Elnusa Tbk | D25: 4217325000000 | E25: 1811979000000 | F25: 7562822000000 | G25: =I25-H25 -> 2573467000000 | H25: 1248409000000 | I25: 3821876000000 | J25: 3740946000000 | K25: 22500000000 | L25: 7726945000000 | M25: 7726945000000 | N25: =2744000000+302482000000+132199000000 -> 437425000000 | O25: 249085000000 | P25: 69079000000 | Q25: 352 | R25: =D25/G25 -> 1.6387717 | S25: =H25/J25 -> 0.33371479 | T25: =O25/F25 -> 0.032935457 | U25: =O25/J25 -> 0.066583426 | V25: =O25/L25 -> 0.032235897 | W25: =(P25/K25)/Q25 -> 0.008722096 | X25: =P25/O25 -> 0.27733103 | Y25: =Q25/(O25/K25) -> 31.796375 | Z25: =Q25/(J25/K25) -> 2.1171116 | AA25: 2
A26: 2018 | B26: INDY | C26: Indika Energy Tbk | D26: 53144584947333 | E26: 9078886611954 | F26: 53144584947333 | G26: 9708395825025 | H26: 27113435866107 | I26: 36821831691132 | J26: 16322753256201 | K26: 17000000000 | L26: 42905188707381 | M26: 33619749716385 | N26: 3376167922827 | O26: 1417142358909 | P26: 0 | Q26: 2130 | R26: =D26/G26 -> 5.4740851 | S26: =H26/J26 -> 1.6610823 | T26: =O26/F26 -> 0.02666579 | U26: =O26/J26 -> 0.086820056 | V26: =O26/L26 -> 0.033029627 | W26: =(P26/K26)/Q26 -> 0 | X26: =P26/O26 -> 0 | Y26: =Q26/(O26/K26) -> 25.55142 | Z26: =Q26/(J26/K26) -> 2.2183758 | AA26: 2
A27: 2019 | B27: INDY | C27: Indika Energy Tbk | D27: 50268282766565 | E27: 9490045651683 | F27: 50268282766565 | G27: 9889326201536 | H27: 25841649160611 | I27: 35730975362147 | J27: 14537307404418 | K27: 17000000000 | L27: 38681984914420 | M27: 32750407793851 | N27: 3428721170543 | O27: 69399825034 | P27: 0 | Q27: 1195 | R27: =D27/G27 -> 5.0830847 | S27: =H27/J27 -> 1.777609 | T27: =O27/F27 -> 0.0013805887 | U27: =O27/J27 -> 0.0047739119 | V27: =O27/L27 -> 0.0017941123 | W27: =(P27/K27)/Q27 -> 0 | X27: =P27/O27 -> 0 | Y27: =Q27/(O27/K27) -> 292.72408 | Z27: =Q27/(J27/K27) -> 1.397439 | AA27: 2
A28: 2020 | B28: INDY | C28: Indika Energy Tbk | D28: 49278678797985 | E28: 8660333505915 | F28: 49278678797985 | G28: 9982303924775 | H28: 27063145130840 | I28: 37045449055615 | J28: 12233229742370 | K28: 17000000000 | L28: 29299080126225 | M28: 25718122628380 | N28: 3632451919005 | O28: -1459130852270 | P28: 0 | Q28: 1730 | R28: =D28/G28 -> 4.9366037 | S28: =H28/J28 -> 2.2122649 | T28: =O28/F28 -> -0.02960978 | U28: =O28/J28 -> -0.11927601 | V28: =O28/L28 -> -0.049801251 | W28: =(P28/K28)/Q28 -> 0 | X28: =P28/O28 -> 0 | Y28: =Q28/(O28/K28) -> -20.155835 | Z28: =Q28/(J28/K28) -> 2.4041076 | AA28: 2

Sheet consumer
A1: Year | B1: Code | C1: Company Name | D1: Current assets | E1: Fixed Assets | F1: Total Assets | G1: Current Liabilites | H1: Long-Term Liabilities | I1: Total Liabilities | J1: Total Equity | K1: Total outstanding shares | L1: Total Sales/ Revenue | M1: COGS/ Cost of Revenues | N1: Expenses (Income) | O1: Net Income | P1: Dividend | Q1: Price | R1: CR | S1: DER | T1: ROA | U1: ROE | V1: NPM | W1: DY | X1: DPR | Y1: PER | Z1: PBV | AA1: Industri | AB1: Klasifikasi
A2: 2018 | B2: ADES | C2: Akasha Wira International Tbk | D2: 364138000000 | E2: 447249000000 | F2: 881275000000 | G2: =I2-H2 -> 262397000000 | H2: 136964000000 | I2: 399361000000 | J2: 481914000000 | K2: 2359587200 | L2: 804302000000 | M2: 415212000000 | N2: 201877000000 | O2: 58903000000 | P2: 0 | Q2: 895 | R2: =D2/G2 -> 1.3877369 | S2: =H2/J2 -> 0.28420839 | T2: =O2/F2 -> 0.066838388 | U2: =O2/J2 -> 0.1222272 | V2: =O2/L2 -> 0.073234929 | W2: =(P2/K2)/Q2 -> 0 | X2: =P2/O2 -> 0 | Y2: =Q2/(O2/K2) -> 35.852682 | Z2: =Q2/(J2/K2) -> 4.3821731 | AA2: 3 | AB2: 0
A3: 2019 | B3: ADES | C3: Akasha Wira International Tbk | D3: 351120000000 | E3: 405448000000 | F3: 822375000000 | G3: =I3-H3 -> 175191000000 | H3: 79247000000 | I3: 254438000000 | J3: 567937000000 | K3: 2359587200 | L3: 834330000000 | M3: 417281000000 | N3: 182396000000 | O3: 86023000000 | P3: 0 | Q3: 1045 | R3: =D3/G3 -> 2.0042125 | S3: =H3/J3 -> 0.13953484 | T3: =O3/F3 -> 0.10460313 | U3: =O3/J3 -> 0.15146574 | V3: =O3/L3 -> 0.10310429 | W3: =(P3/K3)/Q3 -> 0 | X3: =P3/O3 -> 0 | Y3: =Q3/(O3/K3) -> 28.664062 | Z3: =Q3/(J3/K3) -> 4.3416235 | AA3: 3 | AB3: 0
A4: 2020 | B4: ADES | C4: Akasha Wira International Tbk | D4: 545239000000 | E4: 351626000000 | F4: 958791000000 | G4: =I4-H4 -> 183559000000 | H4: 74724000000 | I4: 258283000000 | J4: 700508000000 | K4: 2359587200 | L4: 673364000000 | M4: 330799000000 | N4: 96707000000 | O4: 135765000000 | P4: 0 | Q4: 1460 | R4: =D4/G4 -> 2.9703746 | S4: =H4/J4 -> 0.10667116 | T4: =O4/F4 -> 0.1416002 | U4: =O4/J4 -> 0.19380935 | V4: =O4/L4 -> 0.20162201 | W4: =(P4/K4)/Q4 -> 0 | X4: =P4/O4 -> 0 | Y4: =Q4/(O4/K4) -> 25.374709 | Z4: =Q4/(J4/K4) -> 4.9178558 | AA4: 3 | AB4: 0
A5: 2018 | B5: TCID | C5: Mandom Indonesia Tbk | D5: 1333428311186 | E5: 998708967039 | F5: 2445143511801 | G5: =I5-H5 -> 231533842787 | H5: 241146503875 | I5: 472680346662 | J5: 1972463165139 | K5: 804266668 | L5: 2648754344347 | M5: 1685791739001 | N5: 722004701096 | O5: 173049442756 | P5: 82362154537 | Q5: 17200 | R5: =D5/G5 -> 5.7591076 | S5: =H5/J5 -> 0.12225653 | T5: =O5/F5 -> 0.070772714 | U5: =O5/J5 -> 0.087732661 | V5: =O5/L5 -> 0.065332387 | W5: =(P5/K5)/Q5 -> 0.0059538677 | X5: =P5/O5 -> 0.47594579 | Y5: =Q5/(O5/K5) -> 79.938927 | Z5: =Q5/(J5/K5) -> 7.0132548 | AA5: 3 | AB5: 0
A6: 2019 | B6: TCID | C6: Mandom Indonesia Tbk | D6: 1428191709308 | E6: 938300134590 | F6: 2551192620939 | G6: =I6-H6 -> 260244280265 | H6: 271804523512 | I6: 532048803777 | J6: 2019143817162 | K6: 804266668 | L6: 2804151670769 | M6: 1873937759675 | N6: =739420214230+1218605208 -> 740638819438 | O6: 145149344561 | P6: 84653428243 | Q6: 11000 | R6: =D6/G6 -> 5.4878889 | S6: =H6/J6 -> 0.13461375 | T6: =O6/F6 -> 0.056894702 | U6: =O6/J6 -> 0.071886581 | V6: =O6/L6 -> 0.051762302 | W6: =(P6/K6)/Q6 -> 0.0095686748 | X6: =P6/O6 -> 0.58321606 | Y6: =Q6/(O6/K6) -> 60.950557 | Z6: =Q6/(J6/K6) -> 4.3815271 | AA6: 3 | AB6: 0
A7: 2020 | B7: TCID | C7: Mandom Indonesia Tbk | D7: 1343961709769 | E7: 822015923646 | F7: 2314790056002 | G7: =I7-H7 -> 131087175475 | H7: 317715961088 | I7: 448803136563 | J7: 1865986919439 | K7: 804266668 | L7: 1989005993587 | M7: 1534276464935 | N7: 523339628164 | O7: -54776587213 | P7: 84393872136 | Q7: 6475 | R7: =D7/G7 -> 10.252427 | S7: =H7/J7 -> 0.17026698 | T7: =O7/F7 -> -0.023663739 | U7: =O7/J7 -> -0.02935529 | V7: =O7/L7 -> -0.027539679 | W7: =(P7/K7)/Q7 -> 0.016205822 | X7: =P7/O7 -> -1.5406924 | Y7: =Q7/(O7/K7) -> -95.070302 | Z7: =Q7/(J7/K7) -> 2.7908163 | AA7: 3 | AB7: 0
A8: 2018 | B8: UNVR | C8: Unilever Indonesia Tbk | D8: 8257910000000 | E8: 10627387000000 | F8: 19522970000000 | G8: =I8-H8 -> 11134786000000 | H8: 810051000000 | I8: 11944837000000 | J8: 7578133000000 | K8: 7630000000 | L8: 41802073000000 | M8: 20709800000000 | N8: =7678122000000+3925110000000 -> 11603232000000 | O8: 9081187000000 | P8: 6926201000000 | Q8: 44500 | R8: =D8/G8 -> 0.74163168 | S8: =H8/J8 -> 0.10689321 | T8: =O8/F8 -> 0.46515397 | U8: =O8/J8 -> 1.1983409 | V8: =O8/L8 -> 0.2172425 | W8: =(P8/K8)/Q8 -> 0.020399078 | X8: =P8/O8 -> 0.76269776 | Y8: =Q8/(O8/K8) -> 37.388835 | Z8: =Q8/(J8/K8) -> 44.804571 | AA8: 3 | AB8: 1
A9: 2019 | B9: UNVR | C9: Unilever Indonesia Tbk | D9: 8530334000000 | E9: 10715376000000 | F9: 20649371000000 | G9: =I9-H9 -> 13065308000000 | H9: 2302201000000 | I9: 15367509000000 | J9: 5281862000000 | K9: 7630000000 | L9: 42922563000000 | M9: 20893870000000 | N9: =8049388000000+3861481000000 -> 11910869000000 | O9: 7392837000000 | P9: 9176417000000 | Q9: 42000 | R9: =D9/G9 -> 0.65289957 | S9: =H9/J9 -> 0.43586921 | T9: =O9/F9 -> 0.35801754 | U9: =O9/J9 -> 1.3996649 | V9: =O9/L9 -> 0.17223662 | W9: =(P9/K9)/Q9 -> 0.02863514 | X9: =P9/O9 -> 1.2412579 | Y9: =Q9/(O9/K9) -> 43.347364 | Z9: =Q9/(J9/K9) -> 60.671786 | AA9: 3 | AB9: 1
A10: 2020 | B10: UNVR | C10: Unilever Indonesia Tbk | D10: 8828360000000 | E10: 10419902000000 | F10: 20534632000000 | G10: =I10-H10 -> 13357536000000 | H10: 2239728000000 | I10: 15597264000000 | J10: 4937368000000 | K10: 7630000000 | L10: 42972474000000 | M10: 20515484000000 | N10: =8628647000000+4357209000000+20122000000 -> 13005978000000 | O10: 7163536000000 | P10: 7371069000000 | Q10: 7350 | R10: =D10/G10 -> 0.66092728 | S10: =H10/J10 -> 0.45362792 | T10: =O10/F10 -> 0.34885144 | U10: =O10/J10 -> 1.4508815 | V10: =O10/L10 -> 0.16670057 | W10: =(P10/K10)/Q10 -> 0.13143729 | X10: =P10/O10 -> 1.0289707 | Y10: =Q10/(O10/K10) -> 7.8286059 | Z10: =Q10/(J10/K10) -> 11.35838 | AA10: 3 | AB10: 1
A11: 2018 | B11: JPFA | C11: Japfa Comfeed Indonesia Tbk | D11: 13334804000000 | E11: 8647396000000 | F11: 24827355000000 | G11: =I11-H11 -> 7689521000000 | H11: 6372157000000 | I11: 14061678000000 | J11: 10765677000000 | K11: 100000000000 | L11: 36228261000000 | M11: 28342636000000 | N11: =836629000000+2647489000000+164095000000 -> 3648213000000 | O11: 2253201000000 | P11: 1205915000000 | Q11: 2000 | R11: =D11/G11 -> 1.7341528 | S11: =H11/J11 -> 0.59189561 | T11: =O11/F11 -> 0.090754774 | U11: =O11/J11 -> 0.20929487 | V11: =O11/L11 -> 0.062194567 | W11: =(P11/K11)/Q11 -> 0.006029575 | X11: =P11/O11 -> 0.53520081 | Y11: =Q11/(O11/K11) -> 88.762609 | Z11: =Q11/(J11/K11) -> 18.577559 | AA11: 3 | AB11: 0
A12: 2019 | B12: JPFA | C12: Japfa Comfeed Indonesia Tbk | D12: 12873148000000 | E12: 10707724000000 | F12: 26650895000000 | G12: =I12-H12 -> 7741958000000 | H12: 7012123000000 | I12: 14754081000000 | J12: 11896814000000 | K12: 100000000000 | L12: 38872084000000 | M12: 31000234000000 | N12: =1048302000000+2895713000000+160828000000 -> 4104843000000 | O12: 1883857000000 | P12: 638281000000 | Q12: 1535 | R12: =D12/G12 -> 1.6627768 | S12: =H12/J12 -> 0.58941184 | T12: =O12/F12 -> 0.070686444 | U12: =O12/J12 -> 0.15834971 | V12: =O12/L12 -> 0.048462979 | W12: =(P12/K12)/Q12 -> 0.0041581824 | X12: =P12/O12 -> 0.33881606 | Y12: =Q12/(O12/K12) -> 81.481769 | Z12: =Q12/(J12/K12) -> 12.902614 | AA12: 3 | AB12: 0
A13: 2020 | B13: JPFA | C13: Japfa Comfeed Indonesia Tbk | D13: 11745138000000 | E13: 11143803000000 | F13: 25951760000000 | G13: =I13-H13 -> 6007679000000 | H13: 8532111000000 | I13: 14539790000000 | J13: 11411970000000 | K13: 100000000000 | L13: 36964948000000 | M13: 29535739000000 | N13: =1549972000000+3244208000000+236681000000 -> 5030861000000 | O13: 1002376000000 | P13: 258375000000 | Q13: 1465 | R13: =D13/G13 -> 1.9550209 | S13: =H13/J13 -> 0.74764576 | T13: =O13/F13 -> 0.038624587 | U13: =O13/J13 -> 0.087835492 | V13: =O13/L13 -> 0.027116933 | W13: =(P13/K13)/Q13 -> 0.0017636519 | X13: =P13/O13 -> 0.25776256 | Y13: =Q13/(O13/K13) -> 146.15274 | Z13: =Q13/(J13/K13) -> 12.837398 | AA13: 3 | AB13: 0
A14: 2018 | B14: CINT | C14: Chitose International Tbk | D14: 219577845340 | E14: 256898006885 | F14: 491382035136 | G14: =I14-H14 -> 81075913501 | H14: 21627543807 | I14: 102703457308 | J14: 388678577828 | K14: 2000000000 | L14: 370390736433 | M14: 256947701878 | N14: =58584770961+3331144467+33706922995 -> 95622838423 | O14: 13554152161 | P14: 8000000000 | Q14: 284 | R14: =D14/G14 -> 2.7082994 | S14: =H14/J14 -> 0.055643776 | T14: =O14/F14 -> 0.027583736 | U14: =O14/J14 -> 0.034872393 | V14: =O14/L14 -> 0.036594199 | W14: =(P14/K14)/Q14 -> 0.014084507 | X14: =P14/O14 -> 0.59022504 | Y14: =Q14/(O14/K14) -> 41.905978 | Z14: =Q14/(J14/K14) -> 1.4613617 | AA14: 3 | AB14: 0
A15: 2019 | B15: CINT | C15: Chitose International Tbk | D15: 250724734274 | E15: 249614390323 | F15: 521493784876 | G15: =I15-H15 -> 105476752401 | H15: 26345627806 | I15: 131822380207 | J15: 389671404669 | K15: 2000000000 | L15: 407452029013 | M15: 292192033789 | N15: =60822934424+4618458062+38111785637 -> 103553178123 | O15: 7221065916 | P15: 3300000000 | Q15: 302 | R15: =D15/G15 -> 2.3770616 | S15: =H15/J15 -> 0.067609857 | T15: =O15/F15 -> 0.013846888 | U15: =O15/J15 -> 0.018531167 | V15: =O15/L15 -> 0.017722493 | W15: =(P15/K15)/Q15 -> 0.0054635762 | X15: =P15/O15 -> 0.45699624 | Y15: =Q15/(O15/K15) -> 83.644161 | Z15: =Q15/(J15/K15) -> 1.5500239 | AA15: 3 | AB15: 0
A16: 2020 | B16: CINT | C16: Chitose International Tbk | D16: 235891593162 | E16: 239840874085 | F16: 498020612974 | G16: =I16-H16 -> 94587795350 | H16: 18075450551 | I16: 112663245901 | J16: 385357367073 | K16: 2000000000 | L16: 330675687019 | M16: 233761111651 | N16: =30572099655+56246224164+6860466956 -> 93678790775 | O16: 249076655 | P16: 2000000000 | Q16: 240 | R16: =D16/G16 -> 2.4938904 | S16: =H16/J16 -> 0.046905683 | T16: =O16/F16 -> 0.00050013322 | U16: =O16/J16 -> 0.00064635239 | V16: =O16/L16 -> 0.00075323547 | W16: =(P16/K16)/Q16 -> 0.0041666667 | X16: =P16/O16 -> 8.0296566 | Y16: =Q16/(O16/K16) -> 1927.1176 | Z16: =Q16/(J16/K16) -> 1.2455971 | AA16: 3 | AB16: 1
A17: 2018 | B17: EPMT | C17: Enseval Putera Megatrading Tbk | D17: 6960395955329 | E17: 1215546692942 | F17: 8322960974230 | G17: =I17-H17 -> 2442855705213 | H17: 92250390844 | I17: 2535106096057 | J17: 5787854878173 | K17: 9120000000 | L17: 20604487293751 | M17: 18207487072775 | N17: =1362204479737+206695250349+22161406875+5391026594 -> 1596452163555 | O17: 653250886056 | P17: 13543200000 | Q17: 2100 | R17: =D17/G17 -> 2.8492866 | S17: =H17/J17 -> 0.015938615 | T17: =O17/F17 -> 0.078487799 | U17: =O17/J17 -> 0.1128658 | V17: =O17/L17 -> 0.031704302 | W17: =(P17/K17)/Q17 -> 0.00070714286 | X17: =P17/O17 -> 0.020732004 | Y17: =Q17/(O17/K17) -> 29.317985 | Z17: =Q17/(J17/K17) -> 3.308998 | AA17: 3 | AB17: 0
A18: 2019 | B18: EPMT | C18: Enseval Putera Megatrading Tbk | D18: 7120602478197 | E18: 1433166129304 | F18: 8704958834283 | G18: =I18-H18 -> 2463953517223 | H18: 111696870012 | I18: 2575650387235 | J18: 6129308447048 | K18: 9120000000 | L18: 22226912485948 | M18: 19771990916170 | N18: =1504815891702+222490672344+6161028189+2683149488 -> 1736150741723 | O18: 580814677453 | P18: 243777600000 | Q18: 2050 | R18: =D18/G18 -> 2.8899094 | S18: =H18/J18 -> 0.018223405 | T18: =O18/F18 -> 0.066722277 | U18: =O18/J18 -> 0.09476023 | V18: =O18/L18 -> 0.026131145 | W18: =(P18/K18)/Q18 -> 0.013039024 | X18: =P18/O18 -> 0.41971667 | Y18: =Q18/(O18/K18) -> 32.189269 | Z18: =Q18/(J18/K18) -> 3.0502625 | AA18: 3 | AB18: 0
A19: 2020 | B19: EPMT | C19: Enseval Putera Megatrading Tbk | D19: 7540695065075 | E19: 1531423663540 | F19: 9211731059218 | G19: =I19-H19 -> 2533986369290 | H19: 118288329421 | I19: 2652274698711 | J19: 6559456360507 | K19: 9120000000 | L19: 22545419368639 | M19: 20086788571564 | N19: =1478722246303+231348697736+10852235264+12082117088 -> 1733005296391 | O19: 679870547997 | P19: 243777600000 | Q19: 2110 | R19: =D19/G19 -> 2.9758231 | S19: =H19/J19 -> 0.018033252 | T19: =O19/F19 -> 0.073804863 | U19: =O19/J19 -> 0.10364739 | V19: =O19/L19 -> 0.030155596 | W19: =(P19/K19)/Q19 -> 0.012668246 | X19: =P19/O19 -> 0.35856473 | Y19: =Q19/(O19/K19) -> 28.304212 | Z19: =Q19/(J19/K19) -> 2.9336578 | AA19: 3 | AB19: 0
A20: 2018 | B20: HEXA | C20: Hexindo Adiperkasa Tbk | D20: =303730658*14481 -> 4398323658498 | E20: =33931351*14481 -> 491359893831 | F20: =283350512*14481 -> 4103198764272 | G20: =(I20-H20)*14481 -> 2.5826131e+16 | H20: =9889254*14481 -> 143206287174 | I20: =133047144*14481 -> 1926655692264 | J20: =150303368*14481 -> 2176543072008 | K20: =1680000000*14481 -> 24328080000000 | L20: =343228140*14481 -> 4970286695340 | M20: =272719324*14481 -> 3949248530844 | N20: =(24818529+14936978+1642242)*14481 -> 599480803269 | O20: =22549481*14481 -> 326539034361 | P20: =17932883*14481 -> 259686078723 | Q20: 2850 | R20: =D20/G20 -> 0.00017030517 | S20: =H20/J20 -> 0.065795292 | T20: =O20/F20 -> 0.079581578 | U20: =O20/J20 -> 0.15002645 | V20: =O20/L20 -> 0.065698229 | W20: =(P20/K20)/Q20 -> 3.7453807e-06 | X20: =P20/O20 -> 0.7952681 | Y20: =Q20/(O20/K20) -> 212333.05 | Z20: =Q20/(J20/K20) -> 31855.574 | AA20: 3 | AB20: 0
A21: 2019 | B21: HEXA | C21: Hexindo Adiperkasa Tbk | D21: =224442718*13901 -> 3119978222918 | E21: =32395945*13901 -> 450336031445 | F21: =346312450*13901 -> 4814089367450 | G21: =(I21-H21)*13901 -> 3.2053038e+16 | H21: =11149711*13901 -> 154992132611 | I21: =177023250*13901 -> 2460800198250 | J21: =169289200*13901 -> 2353289169200 | K21: =1680000000*13901 -> 23353680000000 | L21: =461333111*13901 -> 6412991576011 | M21: =364810934*13901 -> 5071236793534 | N21: =(28314962+15621674+3812225)*13901 -> 663756916761 | O21: =37600177*13901 -> 522680060477 | P21: =30165579*13901 -> 419331713679 | Q21: 3470 | R21: =D21/G21 -> 9.7337988e-05 | S21: =H21/J21 -> 0.065861916 | T21: =O21/F21 -> 0.10857299 | U21: =O21/J21 -> 0.22210618 | V21: =O21/L21 -> 0.081503313 | W21: =(P21/K21)/Q21 -> 5.1745538e-06 | X21: =P21/O21 -> 0.80227226 | Y21: =Q21/(O21/K21) -> 155041.82 | Z21: =Q21/(J21/K21) -> 34435.747 | AA21: 3 | AB21: 0
A22: 2020 | B22: HEXA | C22: Hexindo Adiperkasa Tbk | D22: =214359738*14105 -> 3023544104490 | E22: =32253909*14105 -> 454941386445 | F22: =266022591*14105 -> 3752248646055 | G22: =(I22-H22)*14105 -> 1.5449806e+16 | H22: =10039504*14105 -> 141607203920 | I22: =87695831*14105 -> 1236949696255 | J22: =178326760*14105 -> 2515298949800 | K22: =1680000000*14105 -> 23696400000000 | L22: =424431271*14105 -> 5986603077455 | M22: =316530893*14105 -> 4464668245765 | N22: =(28766111+19868641+9990238)*14105 -> 826905483950 | O22: =38436806*14105 -> 542151148630 | P22: =30851443*14105 -> 435159603515 | Q22: 3290 | R22: =D22/G22 -> 0.00019570111 | S22: =H22/J22 -> 0.056298359 | T22: =O22/F22 -> 0.144487 | U22: =O22/J22 -> 0.21554144 | V22: =O22/L22 -> 0.090560731 | W22: =(P22/K22)/Q22 -> 5.581749e-06 | X22: =P22/O22 -> 0.80265366 | Y22: =Q22/(O22/K22) -> 143799.67 | Z22: =Q22/(J22/K22) -> 30994.787 | AA22: 3 | AB22: 0
A23: 2018 | B23: LTLS | C23: Lautan Luas Tbk | D23: 2842640000000 | E23: 1901953000000 | F23: 6318441000000 | G23: =I23-H23 -> 2987480000000 | H23: 1205919000000 | I23: 4193399000000 | J23: 2125042000000 | K23: 4800000000 | L23: 7076493000000 | M23: 5787390000000 | N23: =838800000000+57067000000 -> 895867000000 | O23: 233141000000 | P23: 45380000000 | Q23: 615 | R23: =D23/G23 -> 0.95151767 | S23: =H23/J23 -> 0.56748008 | T23: =O23/F23 -> 0.036898501 | U23: =O23/J23 -> 0.10971124 | V23: =O23/L23 -> 0.032945839 | W23: =(P23/K23)/Q23 -> 0.015372629 | X23: =P23/O23 -> 0.19464616 | Y23: =Q23/(O23/K23) -> 12.661866 | Z23: =Q23/(J23/K23) -> 1.389149 | AA23: 3 | AB23: 0
A24: 2019 | B24: LTLS | C24: Lautan Luas Tbk | D24: 2508089000000 | E24: 1880861000000 | F24: 5863204000000 | G24: =I24-H24 -> 2971594000000 | H24: 731430000000 | I24: 3703024000000 | J24: 2160180000000 | K24: 4800000000 | L24: 6534734000000 | M24: 5253452000000 | N24: =873976000000+5811000000 -> 879787000000 | O24: 225747000000 | P24: 61647000000 | Q24: 610 | R24: =D24/G24 -> 0.84402142 | S24: =H24/J24 -> 0.33859678 | T24: =O24/F24 -> 0.038502327 | U24: =O24/J24 -> 0.10450379 | V24: =O24/L24 -> 0.034545706 | W24: =(P24/K24)/Q24 -> 0.021054303 | X24: =P24/O24 -> 0.27308004 | Y24: =Q24/(O24/K24) -> 12.970272 | Z24: =Q24/(J24/K24) -> 1.3554426 | AA24: 3 | AB24: 0
A25: 2020 | B25: LTLS | C25: Lautan Luas Tbk | D25: 2138024000000 | E25: 1828809000000 | F25: 5524302000000 | G25: =I25-H25 -> 2189930000000 | H25: 1091250000000 | I25: 3281180000000 | J25: 2243122000000 | K25: 4800000000 | L25: 5592338000000 | M25: 4417520000000 | N25: =775644000000+87519000000 -> 863163000000 | O25: 118196000000 | P25: 53603000000 | Q25: 490 | R25: =D25/G25 -> 0.97629787 | S25: =H25/J25 -> 0.48648714 | T25: =O25/F25 -> 0.021395644 | U25: =O25/J25 -> 0.052692631 | V25: =O25/L25 -> 0.021135346 | W25: =(P25/K25)/Q25 -> 0.022790391 | X25: =P25/O25 -> 0.45350943 | Y25: =Q25/(O25/K25) -> 19.899151 | Z25: =Q25/(J25/K25) -> 1.0485386 | AA25: 3 | AB25: 0
A26: 2018 | B26: MICE | C26: Multi Indocitra Tbk | D26: 426630096664 | E26: 396613573360 | F26: 928832007829 | G26: =I26-H26 -> 218195329431 | H26: 72924681977 | I26: 291120011408 | J26: 637711996421 | K26: 2000000000 | L26: 28935125276 | M26: 23917401115 | N26: =314144918983+1364477909 -> 315509396892 | O26: 32997196204 | P26: 5954230000 | Q26: 370 | R26: =D26/G26 -> 1.9552669 | S26: =H26/J26 -> 0.11435363 | T26: =O26/F26 -> 0.035525473 | U26: =O26/J26 -> 0.051743101 | V26: =O26/L26 -> 1.1403855 | W26: =(P26/K26)/Q26 -> 0.0080462568 | X26: =P26/O26 -> 0.18044654 | Y26: =Q26/(O26/K26) -> 22.426148 | Z26: =Q26/(J26/K26) -> 1.1603984 | AA26: 3 | AB26: 0
A27: 2019 | B27: MICE | C27: Multi Indocitra Tbk | D27: 471241593838 | E27: 441663263719 | F27: 1044252437786 | G27: =I27-H27 -> 303796823069 | H27: 61600581292 | I27: 365397404361 | J27: 678855033425 | K27: 2000000000 | L27: 704897521423 | M27: 325702387052 | N27: =359462091901+4452173918 -> 363914265819 | O27: 34333566183 | P27: 5954230000 | Q27: 346 | R27: =D27/G27 -> 1.5511735 | S27: =H27/J27 -> 0.090741879 | T27: =O27/F27 -> 0.032878608 | U27: =O27/J27 -> 0.050575697 | V27: =O27/L27 -> 0.048707174 | W27: =(P27/K27)/Q27 -> 0.0086043786 | X27: =P27/O27 -> 0.173423 | Y27: =Q27/(O27/K27) -> 20.155203 | Z27: =Q27/(J27/K27) -> 1.0193634 | AA27: 3 | AB27: 0
A28: 2020 | B28: MICE | C28: Multi Indocitra Tbk | D28: 451410867230 | E28: 425497809009 | F28: 1000283894657 | G28: =I28-H28 -> 265301685348 | H28: 54270499572 | I28: 319572184920 | J28: 680711709737 | K28: 2000000000 | L28: 654285313569 | M28: 282419815086 | N28: =339163629799+26439740478 -> 365603370277 | O28: 2701416962 | P28: 2959520000 | Q28: 298 | R28: =D28/G28 -> 1.7015002 | S28: =H28/J28 -> 0.079726114 | T28: =O28/F28 -> 0.0027006503 | U28: =O28/J28 -> 0.0039685184 | V28: =O28/L28 -> 0.0041288057 | W28: =(P28/K28)/Q28 -> 0.0049656376 | X28: =P28/O28 -> 1.0955436 | Y28: =Q28/(O28/K28) -> 220.62496 | Z28: =Q28/(J28/K28) -> 0.87555421 | AA28: 3 | AB28: 0
A29: 2018 | B29: SDPC | C29: Millennium Pharmacon International Tbk | D29: 1093923908933 | E29: 19895955091 | F29: 1192891220453 | G29: =I29-H29 -> 935926818869 | H29: 24856461000 | I29: 960783279869 | J29: 232107940584 | K29: 2184000000 | L29: 2376182739151 | M29: 2166026999864 | N29: =42305260589+102159744732+2830832908 -> 147295838229 | O29: 19444262069 | P29: 2548000000 | Q29: 95 | R29: =D29/G29 -> 1.1688135 | S29: =H29/J29 -> 0.10709009 | T29: =O29/F29 -> 0.016300113 | U29: =O29/J29 -> 0.083772498 | V29: =O29/L29 -> 0.0081829826 | W29: =(P29/K29)/Q29 -> 0.012280702 | X29: =P29/O29 -> 0.13104123 | Y29: =Q29/(O29/K29) -> 10.6705 | Z29: =Q29/(J29/K29) -> 0.89389445 | AA29: 3 | AB29: 0
A30: 2019 | B30: SDPC | C30: Millennium Pharmacon International Tbk | D30: 1110540241160 | E30: 24821572603 | F30: 1230844175984 | G30: =I30-H30 -> 966343568608 | H30: 29062791000 | I30: 995406359608 | J30: 235437816376 | K30: 2184000000 | L30: 2726755413484 | M30: 2497998546107 | N30: =50968036953+113057481128+1343858926 -> 165369377007 | O30: 7880007292 | P30: 3822000000 | Q30: 95 | R30: =D30/G30 -> 1.1492188 | S30: =H30/J30 -> 0.12344147 | T30: =O30/F30 -> 0.0064021161 | U30: =O30/J30 -> 0.03346959 | V30: =O30/L30 -> 0.0028898842 | W30: =(P30/K30)/Q30 -> 0.018421053 | X30: =P30/O30 -> 0.48502493 | Y30: =Q30/(O30/K30) -> 26.329925 | Z30: =Q30/(J30/K30) -> 0.8812518 | AA30: 3 | AB30: 0
A31: 2020 | B31: SDPC | C31: Millennium Pharmacon International Tbk | D31: 1028893089973 | E31: 21788531959 | F31: 1164826486522 | G31: =I31-H31 -> 903258283864 | H31: 32371714072 | I31: 935629997936 | J31: 229196488586 | K31: 2184000000 | L31: 2643626505412 | M31: 2421934897535 | N31: =50801392553+113456884154+4661838637 -> 168920115344 | O31: 2804331066 | P31: 1274000000 | Q31: 104 | R31: =D31/G31 -> 1.1390907 | S31: =H31/J31 -> 0.14124001 | T31: =O31/F31 -> 0.0024075097 | U31: =O31/J31 -> 0.012235489 | V31: =O31/L31 -> 0.0010607894 | W31: =(P31/K31)/Q31 -> 0.0056089744 | X31: =P31/O31 -> 0.45429729 | Y31: =Q31/(O31/K31) -> 80.994717 | Z31: =Q31/(J31/K31) -> 0.99100995 | AA31: 3 | AB31: 0
A32: 2018 | B32: TGKA | C32: Tigaraksa Satria Tbk | D32: 3293438978537 | E32: 94064002067 | F32: 3485510411961 | G32: =I32-H32 -> 1928698918596 | H32: 308958990481 | I32: 2237657909077 | J32: 1247852502884 | K32: 2000000000 | L32: 12940108219350 | M32: 11524839503101 | N32: =791086675772+190832440112 -> 981919115884 | O32: 318607055495 | P32: 146958840000 | Q32: 3350 | R32: =D32/G32 -> 1.7075962 | S32: =H32/J32 -> 0.24759256 | T32: =O32/F32 -> 0.09140901 | U32: =O32/J32 -> 0.25532429 | V32: =O32/L32 -> 0.024621669 | W32: =(P32/K32)/Q32 -> 0.021934155 | X32: =P32/O32 -> 0.46125419 | Y32: =Q32/(O32/K32) -> 21.029038 | Z32: =Q32/(J32/K32) -> 5.3692243 | AA32: 3 | AB32: 0
A33: 2019 | B33: TGKA | C33: Tigaraksa Satria Tbk | D33: 2761095717618 | E33: 86888676915 | F33: 2995872438975 | G33: =I33-H33 -> 1281093781950 | H33: 322779610313 | I33: 1603873392263 | J33: 1391999046712 | K33: 2000000000 | L33: 13372043554341 | M33: 11691107341759 | N33: =927876755512+212932735867 -> 1140809491379 | O33: 428418484105 | P33: 219519767250 | Q33: 4850 | R33: =D33/G33 -> 2.1552643 | S33: =H33/J33 -> 0.23188206 | T33: =O33/F33 -> 0.14300291 | U33: =O33/J33 -> 0.30777211 | V33: =O33/L33 -> 0.03203837 | W33: =(P33/K33)/Q33 -> 0.022630904 | X33: =P33/O33 -> 0.51239565 | Y33: =Q33/(O33/K33) -> 22.641413 | Z33: =Q33/(J33/K33) -> 6.9683956 | AA33: 3 | AB33: 0
A34: 2020 | B34: TGKA | C34: Tigaraksa Satria Tbk | D34: 3067116650845 | E34: 75635303975 | F34: 3361956197960 | G34: =I34-H34 -> 1406291340510 | H34: 356992629183 | I34: 1763283969693 | J34: 1598672228267 | K34: 2000000000 | L34: 12488883541697 | M34: 10806684751704 | N34: =782823289521+242980385483 -> 1025803675004 | O34: 478561152411 | P34: 261770433750 | Q34: 7275 | R34: =D34/G34 -> 2.1809966 | S34: =H34/J34 -> 0.22330571 | T34: =O34/F34 -> 0.14234604 | U34: =O34/J34 -> 0.29934914 | V34: =O34/L34 -> 0.03831897 | W34: =(P34/K34)/Q34 -> 0.017991095 | X34: =P34/O34 -> 0.54699474 | Y34: =Q34/(O34/K34) -> 30.403638 | Z34: =Q34/(J34/K34) -> 9.1013028 | AA34: 3 | AB34: 0
A35: 2018 | B35: WICO | C35: Wicaksana Overseas International Tbk | D35: 333578357832 | E35: 48379981073 | F35: 386108236920 | G35: =I35-H35 -> 82000239837 | H35: 26423708521 | I35: 108423948358 | J35: 277684288562 | K35: 1800000000 | L35: 972305391346 | M35: 872653118697 | N35: =35555045193+98161336450 -> 133716381643 | O35: -21172048346 | P35: 0 | Q35: 600 | R35: =D35/G35 -> 4.0680169 | S35: =H35/J35 -> 0.095157377 | T35: =O35/F35 -> -0.05483449 | U35: =O35/J35 -> -0.076245035 | V35: =O35/L35 -> -0.021775101 | W35: =(P35/K35)/Q35 -> 0 | X35: =P35/O35 -> 0 | Y35: =Q35/(O35/K35) -> -51.010652 | Z35: =Q35/(J35/K35) -> 3.889309 | AA35: 3 | AB35: 0
A36: 2019 | B36: WICO | C36: Wicaksana Overseas International Tbk | D36: 643568004520 | E36: 47881444521 | F36: 695853450844 | G36: =I36-H36 -> 421129759476 | H36: 27188829231 | I36: 448318588707 | J36: 247534862137 | K36: 1800000000 | L36: 1855354419901 | M36: 1693554680390 | N36: =49620223178+151316722585 -> 200936945763 | O36: -27568919425 | P36: 0 | Q36: 535 | R36: =D36/G36 -> 1.5281941 | S36: =H36/J36 -> 0.10983838 | T36: =O36/F36 -> -0.039618859 | U36: =O36/J36 -> -0.11137389 | V36: =O36/L36 -> -0.014859112 | W36: =(P36/K36)/Q36 -> 0 | X36: =P36/O36 -> 0 | Y36: =Q36/(O36/K36) -> -34.93064 | Z36: =Q36/(J36/K36) -> 3.8903611 | AA36: 3 | AB36: 0
A37: 2020 | B37: WICO | C37: Wicaksana Overseas International Tbk | D37: 594790929582 | E37: 61258028492 | F37: 677619067915 | G37: =I37-H37 -> 446454025409 | H37: 22494563659 | I37: 468948589068 | J37: 208670478847 | K37: 1800000000 | L37: 3097194461934 | M37: 2842951459588 | N37: =85221384316+226404617260 -> 311626001576 | O37: -41008773290 | P37: 0 | Q37: 446 | R37: =D37/G37 -> 1.3322557 | S37: =H37/J37 -> 0.10779945 | T37: =O37/F37 -> -0.060518919 | U37: =O37/J37 -> -0.19652408 | V37: =O37/L37 -> -0.013240619 | W37: =(P37/K37)/Q37 -> 0 | X37: =P37/O37 -> 0 | Y37: =Q37/(O37/K37) -> -19.576299 | Z37: =Q37/(J37/K37) -> 3.8472141 | AA37: 3 | AB37: 0
A38: 2018 | B38: ACES | C38: Ace Hardware Indonesia Tbk | D38: 3906136917474 | E38: 413836506054 | F38: 5857570698119 | G38: =I38-H38 -> 778853385563 | H38: 896465230114 | I38: 1675318615677 | J38: 4182252082442 | K38: 48000000000 | L38: 7239754268263 | M38: 3796596070656 | N38: =2370738606721+1280358948 -> 2372018965669 | O38: 1044485235597 | P38: 389343686991 | Q38: 1490 | R38: =D38/G38 -> 5.0152403 | S38: =H38/J38 -> 0.21434988 | T38: =O38/F38 -> 0.17831372 | U38: =O38/J38 -> 0.2497423 | V38: =O38/L38 -> 0.14427081 | W38: =(P38/K38)/Q38 -> 0.0054438435 | X38: =P38/O38 -> 0.37276131 | Y38: =Q38/(O38/K38) -> 68.473921 | Z38: =Q38/(J38/K38) -> 17.100834 | AA38: 3 | AB38: 0
A39: 2019 | B39: ACES | C39: Ace Hardware Indonesia Tbk | D39: 4369550647718 | E39: 471979028144 | F39: 6641808005145 | G39: =I39-H39 -> 783375432849 | H39: 1182131278030 | I39: 1965506710879 | J39: 4676301294266 | K39: 48000000000 | L39: 8142717045655 | M39: 4255626726811 | N39: =2724515688299+17528968515 -> 2742044656814 | O39: 990585488760 | P39: 483562258825 | Q39: 1495 | R39: =D39/G39 -> 5.57785 | S39: =H39/J39 -> 0.25279194 | T39: =O39/F39 -> 0.14914395 | U39: =O39/J39 -> 0.21183098 | V39: =O39/L39 -> 0.12165294 | W39: =(P39/K39)/Q39 -> 0.0067386045 | X39: =P39/O39 -> 0.48815803 | Y39: =Q39/(O39/K39) -> 72.442006 | Z39: =Q39/(J39/K39) -> 15.345461 | AA39: 3 | AB39: 0
A40: 2020 | B40: ACES | C40: Ace Hardware Indonesia Tbk | D40: 5034737166320 | E40: 511639035778 | F40: 7247063894294 | G40: =I40-H40 -> 844928054206 | H40: 1179893285690 | I40: 2024821339896 | J40: 5222242554398 | K40: 48000000000 | L40: 7412766872302 | M40: 3753585066580 | N40: =2806097154344+5423065820 -> 2811520220164 | O40: 833806976851 | P40: 309286244180 | Q40: 1715 | R40: =D40/G40 -> 5.9587762 | S40: =H40/J40 -> 0.22593613 | T40: =O40/F40 -> 0.11505445 | U40: =O40/J40 -> 0.15966454 | V40: =O40/L40 -> 0.11248256 | W40: =(P40/K40)/Q40 -> 0.0037571215 | X40: =P40/O40 -> 0.37093267 | Y40: =Q40/(O40/K40) -> 98.727886 | Z40: =Q40/(J40/K40) -> 15.763343 | AA40: 3 | AB40: 0
A41: 2018 | B41: CENT | C41: Centratama Telekomunikasi Indonesia Tbk | D41: 940154000000 | E41: 2601811000000 | F41: 5207342000000 | G41: =I41-H41 -> 778970000000 | H41: 1389948000000 | I41: 2168918000000 | J41: 3038424000000 | K41: 35000000000 | L41: 801161000000 | M41: 398416000000 | N41: =216629000000+168708000000 -> 385337000000 | O41: 35637000000 | P41: 0 | Q41: 86 | R41: =D41/G41 -> 1.2069194 | S41: =H41/J41 -> 0.45745689 | T41: =O41/F41 -> 0.0068436066 | U41: =O41/J41 -> 0.011728778 | V41: =O41/L41 -> 0.044481696 | W41: =(P41/K41)/Q41 -> 0 | X41: =P41/O41 -> 0 | Y41: =Q41/(O41/K41) -> 84.462777 | Z41: =Q41/(J41/K41) -> 0.99064515 | AA41: 3 | AB41: 0
A42: 2019 | B42: CENT | C42: Centratama Telekomunikasi Indonesia Tbk | D42: 1285023000000 | E42: 2896487000000 | F42: 5729085000000 | G42: =I42-H42 -> 1255977000000 | H42: 1458216000000 | I42: 2714193000000 | J42: 3014892000000 | K42: 35000000000 | L42: 831777000000 | M42: 400255000000 | N42: =153353000000+230643000000 -> 383996000000 | O42: 8912000000 | P42: 0 | Q42: 73 | R42: =D42/G42 -> 1.0231262 | S42: =H42/J42 -> 0.48367106 | T42: =O42/F42 -> 0.0015555713 | U42: =O42/J42 -> 0.0029559931 | V42: =O42/L42 -> 0.01071441 | W42: =(P42/K42)/Q42 -> 0 | X42: =P42/O42 -> 0 | Y42: =Q42/(O42/K42) -> 286.6921 | Z42: =Q42/(J42/K42) -> 0.84745988 | AA42: 3 | AB42: 0
A43: 2020 | B43: CENT | C43: Centratama Telekomunikasi Indonesia Tbk | D43: 1116644000000 | E43: 4540432000000 | F43: 7629153000000 | G43: =I43-H43 -> 4983388000000 | H43: 174026000000 | I43: 5157414000000 | J43: 2471739000000 | K43: 35000000000 | L43: 1096044000000 | M43: 518577000000 | N43: =512197000000+495354000000 -> 1007551000000 | O43: -509181000000 | P43: 0 | Q43: 142 | R43: =D43/G43 -> 0.22407326 | S43: =H43/J43 -> 0.070406301 | T43: =O43/F43 -> -0.066741485 | U43: =O43/J43 -> -0.20600112 | V43: =O43/L43 -> -0.46456255 | W43: =(P43/K43)/Q43 -> 0 | X43: =P43/O43 -> 0 | Y43: =Q43/(O43/K43) -> -9.7607727 | Z43: =Q43/(J43/K43) -> 2.0107301 | AA43: 3 | AB43: 0
A44: 2018 | B44: ECII | C44: Electronic City Indonesia Tbk | D44: 752676010865 | E44: 595947250015 | F44: 1751622687179 | G44: =I44-H44 -> 353191107837 | H44: 51884263504 | I44: 405075371341 | J44: 1346547315838 | K44: 1334333000 | L44: 2003208506432 | M44: 1680758856692 | N44: 311685274501 | O44: 9325792298 | P44: 0 | Q44: 1130 | R44: =D44/G44 -> 2.1310729 | S44: =H44/J44 -> 0.038531333 | T44: =O44/F44 -> 0.0053240874 | U44: =O44/J44 -> 0.0069257071 | V44: =O44/L44 -> 0.0046554277 | W44: =(P44/K44)/Q44 -> 0 | X44: =P44/O44 -> 0 | Y44: =Q44/(O44/K44) -> 161.68023 | Z44: =Q44/(J44/K44) -> 1.11975 | AA44: 3 | AB44: 0
A45: 2019 | B45: ECII | C45: Electronic City Indonesia Tbk | D45: 831937034323 | E45: 635301490253 | F45: 1845324374750 | G45: =I45-H45 -> 399844207730 | H45: 65484325206 | I45: 465328532936 | J45: 1379995841814 | K45: 1334333000 | L45: 1978631967708 | M45: 1631941216390 | N45: 336739921456 | O45: 33269247689 | P45: 0 | Q45: 1010 | R45: =D45/G45 -> 2.080653 | S45: =H45/J45 -> 0.047452553 | T45: =O45/F45 -> 0.018028943 | U45: =O45/J45 -> 0.024108223 | V45: =O45/L45 -> 0.016814268 | W45: =(P45/K45)/Q45 -> 0 | X45: =P45/O45 -> 0 | Y45: =Q45/(O45/K45) -> 40.50817 | Z45: =Q45/(J45/K45) -> 0.97657999 | AA45: 3 | AB45: 0
A46: 2020 | B46: ECII | C46: Electronic City Indonesia Tbk | D46: 953327437749 | E46: 649791168201 | F46: 1730596456562 | G46: =I46-H46 -> 397514035472 | H46: 80268968169 | I46: 477783003641 | J46: 1252813452921 | K46: 1334333000 | L46: 1618490505399 | M46: 1340438220353 | N46: =307355207331+3439979352+725615310 -> 311520801993 | O46: -20502166781 | P46: 0 | Q46: 655 | R46: =D46/G46 -> 2.3982233 | S46: =H46/J46 -> 0.064070966 | T46: =O46/F46 -> -0.011846879 | U46: =O46/J46 -> -0.0163649 | V46: =O46/L46 -> -0.012667462 | W46: =(P46/K46)/Q46 -> 0 | X46: =P46/O46 -> 0 | Y46: =Q46/(O46/K46) -> -42.629061 | Z46: =Q46/(J46/K46) -> 0.69762031 | AA46: 3 | AB46: 0
A47: 2018 | B47: ERAA | C47: Erajaya Swasembada Tbk | D47: 10053691913000 | E47: 553675716000 | F47: 12682902626000 | G47: =I47-H47 -> 7740591920000 | H47: 116692469000 | I47: 7857284389000 | J47: 4825618237000 | K47: 7800000000 | L47: 34744177481000 | M47: 31574695864000 | N47: =1080320007000+771635051000+6170369000 -> 1858125427000 | O47: 889340783000 | P47: 110200000 | Q47: 2200 | R47: =D47/G47 -> 1.2988273 | S47: =H47/J47 -> 0.024181869 | T47: =O47/F47 -> 0.070121234 | U47: =O47/J47 -> 0.18429572 | V47: =O47/L47 -> 0.025596829 | W47: =(P47/K47)/Q47 -> 6.4219114e-06 | X47: =P47/O47 -> 0.00012391201 | Y47: =Q47/(O47/K47) -> 19.295191 | Z47: =Q47/(J47/K47) -> 3.556021 | AA47: 3 | AB47: 0
A48: 2019 | B48: ERAA | C48: Erajaya Swasembada Tbk | D48: 6944525743000 | E48: 614540334000 | F48: 9747703198000 | G48: =I48-H48 -> 4615531135000 | H48: 153455511000 | I48: 4768986646000 | J48: 4978716552000 | K48: 7800000000 | L48: 32944902671000 | M48: 30095879138000 | N48: =1363502575000+972931223000+7228447000 -> 2343662245000 | O48: 325583191000 | P48: 159500000 | Q48: 1795 | R48: =D48/G48 -> 1.5045995 | S48: =H48/J48 -> 0.030822303 | T48: =O48/F48 -> 0.033401016 | U48: =O48/J48 -> 0.065395004 | V48: =O48/L48 -> 0.0098826575 | W48: =(P48/K48)/Q48 -> 1.1392043e-05 | X48: =P48/O48 -> 0.00048989016 | Y48: =Q48/(O48/K48) -> 43.002834 | Z48: =Q48/(J48/K48) -> 2.8121705 | AA48: 3 | AB48: 0
A49: 2020 | B49: ERAA | C49: Erajaya Swasembada Tbk | D49: 7546995255000 | E49: 716457366000 | F49: 11211369042000 | G49: =I49-H49 -> 5142950705000 | H49: 380422147000 | I49: 5523372852000 | J49: 5687996190000 | K49: 7800000000 | L49: 34113454845000 | M49: 30703442235000 | N49: =1473722276000+1078462146000+47152494000 -> 2599336916000 | O49: 671172137000 | P49: 0 | Q49: 2200 | R49: =D49/G49 -> 1.4674446 | S49: =H49/J49 -> 0.066881576 | T49: =O49/F49 -> 0.059865315 | U49: =O49/J49 -> 0.11799799 | V49: =O49/L49 -> 0.019674704 | W49: =(P49/K49)/Q49 -> 0 | X49: =P49/O49 -> 0 | Y49: =Q49/(O49/K49) -> 25.567212 | Z49: =Q49/(J49/K49) -> 3.0168797 | AA49: 3 | AB49: 0
A50: 2018 | B50: HERO | C50: Hero Supermarket Tbk | D50: 2845304000000 | E50: 2782800000000 | F50: 6271858000000 | G50: =I50-H50 -> 2167159000000 | H50: 163211000000 | I50: 2330370000000 | J50: 3941488000000 | K50: 9000000000 | L50: 12970389000000 | M50: 9275890000000 | N50: =3844363000000+1380487000000 -> 5224850000000 | O50: -1250189000000 | P50: 0 | Q50: 790 | R50: =D50/G50 -> 1.3129189 | S50: =H50/J50 -> 0.041408473 | T50: =O50/F50 -> -0.19933312 | U50: =O50/J50 -> -0.31718706 | V50: =O50/L50 -> -0.096387934 | W50: =(P50/K50)/Q50 -> 0 | X50: =P50/O50 -> 0 | Y50: =Q50/(O50/K50) -> -5.6871401 | Z50: =Q50/(J50/K50) -> 1.8038873 | AA50: 3 | AB50: 0
A51: 2019 | B51: HERO | C51: Hero Supermarket Tbk | D51: 2417001000000 | E51: 2782800000000 | F51: 6054384000000 | G51: =I51-H51 -> 2261663000000 | H51: 126159000000 | I51: 2387822000000 | J51: 3666562000000 | K51: 9000000000 | L51: 12181025000000 | M51: 8733377000000 | N51: =3488590000000+239351000000 -> 3727941000000 | O51: -28216000000 | P51: 0 | Q51: 890 | R51: =D51/G51 -> 1.0686831 | S51: =H51/J51 -> 0.034407982 | T51: =O51/F51 -> -0.0046604246 | U51: =O51/J51 -> -0.0076954924 | V51: =O51/L51 -> -0.0023163896 | W51: =(P51/K51)/Q51 -> 0 | X51: =P51/O51 -> 0 | Y51: =Q51/(O51/K51) -> -283.88149 | Z51: =Q51/(J51/K51) -> 2.1846078 | AA51: 3 | AB51: 0
A52: 2020 | B52: HERO | C52: Hero Supermarket Tbk | D52: 1540143000000 | E52: 2933236000000 | F52: 4838417000000 | G52: =I52-H52 -> 2278042000000 | H52: 705687000000 | I52: 2983729000000 | J52: 1854688000000 | K52: 9000000000 | L52: 8893785000000 | M52: 6493920000000 | N52: =3554440000000 -> 3554440000000 | O52: -1214602000000 | P52: 0 | Q52: 830 | R52: =D52/G52 -> 0.67608192 | S52: =H52/J52 -> 0.38048825 | T52: =O52/F52 -> -0.25103293 | U52: =O52/J52 -> -0.65488211 | V52: =O52/L52 -> -0.1365675 | W52: =(P52/K52)/Q52 -> 0 | X52: =P52/O52 -> 0 | Y52: =Q52/(O52/K52) -> -6.1501628 | Z52: =Q52/(J52/K52) -> 4.0276316 | AA52: 3 | AB52: 0
A53: 2018 | B53: KOIN | C53: Kokoh Inti Arebama Tbk | D53: 803042816102 | E53: 23434425176 | F53: 855572807455 | G53: =I53-H53 -> 734503822439 | H53: 17989355076 | I53: 752493177515 | J53: 103079629940 | K53: 2400000000 | L53: 1750649236912 | M53: 1506613211796 | N53: =154436007434+91582145434+3045332990 -> 249063485858 | O53: -9993012908 | P53: 0 | Q53: 232 | R53: =D53/G53 -> 1.0933133 | S53: =H53/J53 -> 0.17451901 | T53: =O53/F53 -> -0.011679909 | U53: =O53/J53 -> -0.096944594 | V53: =O53/L53 -> -0.0057081754 | W53: =(P53/K53)/Q53 -> 0 | X53: =P53/O53 -> 0 | Y53: =Q53/(O53/K53) -> -55.718931 | Z53: =Q53/(J53/K53) -> 5.4016492 | AA53: 3 | AB53: 0
A54: 2019 | B54: KOIN | C54: Kokoh Inti Arebama Tbk | D54: 592578908193 | E54: 28228320173 | F54: 652346214673 | G54: =I54-H54 -> 553865665830 | H54: 12452213573 | I54: 566317879403 | J54: 86028335270 | K54: 2400000000 | L54: 1618048001660 | M54: 1437005463891 | N54: =94135654872+568970135+6512798532 -> 101217423539 | O54: -18643690989 | P54: 0 | Q54: 110 | R54: =D54/G54 -> 1.0698964 | S54: =H54/J54 -> 0.14474549 | T54: =O54/F54 -> -0.028579442 | U54: =O54/J54 -> -0.2167157 | V54: =O54/L54 -> -0.011522335 | W54: =(P54/K54)/Q54 -> 0 | X54: =P54/O54 -> 0 | Y54: =Q54/(O54/K54) -> -14.160286 | Z54: =Q54/(J54/K54) -> 3.0687563 | AA54: 3 | AB54: 0
A55: 2020 | B55: KOIN | C55: Kokoh Inti Arebama Tbk | D55: 606903824102 | E55: 32005744503 | F55: 675863759206 | G55: =I55-H55 -> 529614198284 | H55: 19653074898 | I55: 549267273182 | J55: 126596486024 | K55: 2400000000 | L55: 1446474839632 | M55: 1283821135165 | N55: =69372687390+80714831225+2457853119 -> 152545371734 | O55: 41124681020 | P55: 0 | Q55: 101 | R55: =D55/G55 -> 1.1459357 | S55: =H55/J55 -> 0.15524187 | T55: =O55/F55 -> 0.06084759 | U55: =O55/J55 -> 0.32484852 | V55: =O55/L55 -> 0.028430969 | W55: =(P55/K55)/Q55 -> 0 | X55: =P55/O55 -> 0 | Y55: =Q55/(O55/K55) -> 5.8942706 | Z55: =Q55/(J55/K55) -> 1.9147451 | AA55: 3 | AB55: 0
A56: 2018 | B56: MPPA | C56: Matahari Putra Prima Tbk | D56: 2472849000000 | E56: 1097913000000 | F56: 4808545000000 | G56: =I56-H56 -> 2887516000000 | H56: 771786000000 | I56: 3659302000000 | J56: 1149243000000 | K56: 10800000000 | L56: 10692363000000 | M56: 9210950000000 | N56: =419089000000+1672033000000+431072000000 -> 2522194000000 | O56: -826004000000 | P56: 0 | Q56: 152 | R56: =D56/G56 -> 0.85639318 | S56: =H56/J56 -> 0.67156032 | T56: =O56/F56 -> -0.17177837 | U56: =O56/J56 -> -0.71873746 | V56: =O56/L56 -> -0.077251773 | W56: =(P56/K56)/Q56 -> 0 | X56: =P56/O56 -> 0 | Y56: =Q56/(O56/K56) -> -1.9873996 | Z56: =Q56/(J56/K56) -> 1.4284185 | AA56: 3 | AB56: 0
A57: 2019 | B57: MPPA | C57: Matahari Putra Prima Tbk | D57: 1904047000000 | E57: 926287000000 | F57: 3820809000000 | G57: =I57-H57 -> 2618390000000 | H57: 671738000000 | I57: 3290128000000 | J57: 530681000000 | K57: 10800000000 | L57: 8654646000000 | M57: 7074249000000 | N57: =359499000000+1432633000000+88573000000 -> 1880705000000 | O57: -618562000000 | P57: 0 | Q57: 140 | R57: =D57/G57 -> 0.72718235 | S57: =H57/J57 -> 1.2658038 | T57: =O57/F57 -> -0.16189294 | U57: =O57/J57 -> -1.1656004 | V57: =O57/L57 -> -0.07147167 | W57: =(P57/K57)/Q57 -> 0 | X57: =P57/O57 -> 0 | Y57: =Q57/(O57/K57) -> -2.4443791 | Z57: =Q57/(J57/K57) -> 2.8491693 | AA57: 3 | AB57: 0
A58: 2020 | B58: MPPA | C58: Matahari Putra Prima Tbk | D58: 1535266000000 | E58: 789871000000 | F58: 4510511000000 | G58: =I58-H58 -> 2763099000000 | H58: 1562678000000 | I58: 4325777000000 | J58: 184734000000 | K58: 10800000000 | L58: 6746594000000 | M58: 5439936000000 | N58: =279376000000+1239746000000+5841000000 -> 1524963000000 | O58: 405307000000 | P58: 0 | Q58: 105 | R58: =D58/G58 -> 0.55563192 | S58: =H58/J58 -> 8.4590709 | T58: =O58/F58 -> 0.089858333 | U58: =O58/J58 -> 2.1940033 | V58: =O58/L58 -> 0.060075795 | W58: =(P58/K58)/Q58 -> 0 | X58: =P58/O58 -> 0 | Y58: =Q58/(O58/K58) -> 2.7978791 | Z58: =Q58/(J58/K58) -> 6.138556 | AA58: 3 | AB58: 1
A59: 2018 | B59: RALS | C59: Ramayana Lestari Sentosa Tbk | D59: 3557488000000 | E59: 1164225000000 | F59: 5243047000000 | G59: =I59-H59 -> 1093095000000 | H59: 322487000000 | I59: 1415582000000 | J59: 3827465000000 | K59: 28000000000 | L59: 5739553000000 | M59: 3232948000000 | N59: =425171000000+1473612000000+19295000000 -> 1918078000000 | O59: 587105000000 | P59: 268913000000 | Q59: 1420 | R59: =D59/G59 -> 3.2545094 | S59: =H59/J59 -> 0.084256028 | T59: =O59/F59 -> 0.11197783 | U59: =O59/J59 -> 0.15339265 | V59: =O59/L59 -> 0.10229107 | W59: =(P59/K59)/Q59 -> 0.0067634054 | X59: =P59/O59 -> 0.45803221 | Y59: =Q59/(O59/K59) -> 67.722128 | Z59: =Q59/(J59/K59) -> 10.388077 | AA59: 3 | AB59: 0
A60: 2019 | B60: RALS | C60: Ramayana Lestari Sentosa Tbk | D60: 4017659000000 | E60: 1107325000000 | F60: 5649823000000 | G60: =I60-H60 -> 1135638000000 | H60: 345255000000 | I60: 1480893000000 | J60: 4168930000000 | K60: 28000000000 | L60: 5596398000000 | M60: 3102317000000 | N60: =405125000000+1571474000000+7316000000 -> 1983915000000 | O60: 647898000000 | P60: 337141000000 | Q60: 1065 | R60: =D60/G60 -> 3.537799 | S60: =H60/J60 -> 0.082816214 | T60: =O60/F60 -> 0.1146758 | U60: =O60/J60 -> 0.1554111 | V60: =O60/L60 -> 0.11577054 | W60: =(P60/K60)/Q60 -> 0.011305869 | X60: =P60/O60 -> 0.52036123 | Y60: =Q60/(O60/K60) -> 46.025763 | Z60: =Q60/(J60/K60) -> 7.1529145 | AA60: 3 | AB60: 0
A61: 2020 | B61: RALS | C61: Ramayana Lestari Sentosa Tbk | D61: 3200854000000 | E61: 1002168000000 | F61: 5285218000000 | G61: =I61-H61 -> 925658000000 | H61: 640816000000 | I61: 1566474000000 | J61: 3718744000000 | K61: 28000000000 | L61: 2527951000000 | M61: 1450362000000 | N61: =106968000000+1266663000000+36303000000 -> 1409934000000 | O61: 138874000000 | P61: 337124000000 | Q61: 775 | R61: =D61/G61 -> 3.4579229 | S61: =H61/J61 -> 0.17232055 | T61: =O61/F61 -> 0.026275927 | U61: =O61/J61 -> 0.037344329 | V61: =O61/L61 -> 0.0549354 | W61: =(P61/K61)/Q61 -> 0.015535668 | X61: =P61/O61 -> 2.427553 | Y61: =Q61/(O61/K61) -> 156.25675 | Z61: =Q61/(J61/K61) -> 5.8353035 | AA61: 3 | AB61: 0
A62: 2018 | B62: RANC | C62: Supra Boga Lestari Tbk | D62: 544178319988 | E62: 255260217838 | F62: 904003739438 | G62: =I62-H62 -> 348666837381 | H62: 51292877616 | I62: 399959714997 | J62: 504044024441 | K62: 5000000000 | L62: 2355625271907 | M62: 1760399334375 | N62: =350121343001+234627546530 -> 584748889531 | O62: 49966984744 | P62: 7822437500 | Q62: 314 | R62: =D62/G62 -> 1.5607401 | S62: =H62/J62 -> 0.10176269 | T62: =O62/F62 -> 0.055272985 | U62: =O62/J62 -> 0.099132184 | V62: =O62/L62 -> 0.021211771 | W62: =(P62/K62)/Q62 -> 0.0049824443 | X62: =P62/O62 -> 0.15655212 | Y62: =Q62/(O62/K62) -> 31.420747 | Z62: =Q62/(J62/K62) -> 3.1148073 | AA62: 3 | AB62: 0
A63: 2019 | B63: RANC | C63: Supra Boga Lestari Tbk | D63: 570849048409 | E63: 257452233884 | F63: 952496300846 | G63: =I63-H63 -> 348625244359 | H63: 56067821742 | I63: 404693066101 | J63: 547803234745 | K63: 5000000000 | L63: 2397792415330 | M63: 1748429029000 | N63: =382756148310+266706597134 -> 649462745444 | O63: 55464434251 | P63: 10951412500 | Q63: 334 | R63: =D63/G63 -> 1.6374289 | S63: =H63/J63 -> 0.10235029 | T63: =O63/F63 -> 0.058230603 | U63: =O63/J63 -> 0.10124883 | V63: =O63/L63 -> 0.023131458 | W63: =(P63/K63)/Q63 -> 0.006557732 | X63: =P63/O63 -> 0.19744928 | Y63: =Q63/(O63/K63) -> 30.109385 | Z63: =Q63/(J63/K63) -> 3.0485399 | AA63: 3 | AB63: 0
A64: 2020 | B64: RANC | C64: Supra Boga Lestari Tbk | D64: 625866677394 | E64: 329542756308 | F64: 1319134443995 | G64: =I64-H64 -> 512965592357 | H64: 261664232698 | I64: 774629825055 | J64: 544504618940 | K64: 5000000000 | L64: 3011422750334 | M64: 2225048462226 | N64: =428548630896+295584403379 -> 724133034275 | O64: 76002689458 | P64: 43805650000 | Q64: 436 | R64: =D64/G64 -> 1.2200948 | S64: =H64/J64 -> 0.48055466 | T64: =O64/F64 -> 0.057615575 | U64: =O64/J64 -> 0.13958135 | V64: =O64/L64 -> 0.025238134 | W64: =(P64/K64)/Q64 -> 0.020094335 | X64: =P64/O64 -> 0.57636974 | Y64: =Q64/(O64/K64) -> 28.683195 | Z64: =Q64/(J64/K64) -> 4.0036391 | AA64: 3 | AB64: 0
A65: 2018 | B65: FPNI | C65: Lotte Chemical Titan Tbk | D65: 92279000 | E65: 85121000 | F65: 195826000 | G65: =I65-H65 -> 79199000 | H65: 14092000 | I65: 93291000 | J65: 102535000 | K65: 8000000000 | L65: 433868000 | M65: 415763000 | N65: =4837000+4316000+64000 -> 9217000 | O65: 6125000 | P65: 0 | Q65: 160 | R65: =D65/G65 -> 1.1651536 | S65: =H65/J65 -> 0.137436 | T65: =O65/F65 -> 0.031277767 | U65: =O65/J65 -> 0.0597357 | V65: =O65/L65 -> 0.014117197 | W65: =(P65/K65)/Q65 -> 0 | X65: =P65/O65 -> 0 | Y65: =Q65/(O65/K65) -> 208979.59 | Z65: =Q65/(J65/K65) -> 12483.542 | AA65: 3 | AB65: 0
A66: 2019 | B66: FPNI | C66: Lotte Chemical Titan Tbk | D66: 71356000 | E66: 69087000 | F66: 165728000 | G66: =I66-H66 -> 54106000 | H66: 12426000 | I66: 66532000 | J66: 99196000 | K66: 8000000000 | L66: 331945000 | M66: 327289000 | N66: =5420000+4761000+52000+256000 -> 10489000 | O66: -3286000 | P66: 0 | Q66: 119 | R66: =D66/G66 -> 1.3188186 | S66: =H66/J66 -> 0.12526715 | T66: =O66/F66 -> -0.019827669 | U66: =O66/J66 -> -0.033126336 | V66: =O66/L66 -> -0.0098992303 | W66: =(P66/K66)/Q66 -> 0 | X66: =P66/O66 -> 0 | Y66: =Q66/(O66/K66) -> -289713.94 | Z66: =Q66/(J66/K66) -> 9597.1612 | AA66: 3 | AB66: 0
A67: 2020 | B67: FPNI | C67: Lotte Chemical Titan Tbk | D67: 71563000 | E67: 60206000 | F67: 149377000 | G67: =I67-H67 -> 45164000 | H67: 9051000 | I67: 54215000 | J67: 95162000 | K67: 8000000000 | L67: 309367000 | M67: 307424000 | N67: =5961000+4955000+101000+12665000 -> 23682000 | O67: -4172000 | P67: 0 | Q67: 362 | R67: =D67/G67 -> 1.5845142 | S67: =H67/J67 -> 0.095111494 | T67: =O67/F67 -> -0.027929333 | U67: =O67/J67 -> -0.043841029 | V67: =O67/L67 -> -0.013485601 | W67: =(P67/K67)/Q67 -> 0 | X67: =P67/O67 -> 0 | Y67: =Q67/(O67/K67) -> -694151.49 | Z67: =Q67/(J67/K67) -> 30432.315 | AA67: 3 | AB67: 0
A68: 2018 | B68: IGAR | C68: Champion Pacific Indonesia Tbk | D68: 416191470230 | E68: 129189294974 | F68: 570197810698 | G68: =I68-H68 -> 72223978098 | H68: 15059589263 | I68: 87283567361 | J68: 482914243337 | K68: 1750000000 | L68: 777316506801 | M68: 676188716685 | N68: =49302815633+3829961076 -> 53132776709 | O68: 44672438405 | P68: =3782065060+5070489666 -> 8852554726 | Q68: 384 | R68: =D68/G68 -> 5.762511 | S68: =H68/J68 -> 0.031184811 | T68: =O68/F68 -> 0.07834551 | U68: =O68/J68 -> 0.092505945 | V68: =O68/L68 -> 0.057470076 | W68: =(P68/K68)/Q68 -> 0.013173445 | X68: =P68/O68 -> 0.19816592 | Y68: =Q68/(O68/K68) -> 15.042832 | Z68: =Q68/(J68/K68) -> 1.3915514 | AA68: 3 | AB68: 0
A69: 2019 | B69: IGAR | C69: Champion Pacific Indonesia Tbk | D69: 446573796440 | E69: 144745920744 | F69: 617594780669 | G69: =I69-H69 -> 57853674597 | H69: 22815734567 | I69: 80669409164 | J69: 536295371505 | K69: 1750000000 | L69: 776541441414 | M69: 652946761824 | N69: =53355998377+806685924 -> 54162684301 | O69: 60836752751 | P69: =5070489666+1777225450 -> 6847715116 | Q69: 340 | R69: =D69/G69 -> 7.7190222 | S69: =H69/J69 -> 0.042543225 | T69: =O69/F69 -> 0.098505937 | U69: =O69/J69 -> 0.11343889 | V69: =O69/L69 -> 0.078343215 | W69: =(P69/K69)/Q69 -> 0.011508765 | X69: =P69/O69 -> 0.11255885 | Y69: =Q69/(O69/K69) -> 9.7802722 | Z69: =Q69/(J69/K69) -> 1.1094632 | AA69: 3 | AB69: 0
A70: 2020 | B70: IGAR | C70: Champion Pacific Indonesia Tbk | D70: 509735319690 | E70: 140087552996 | F70: 665586417235 | G70: =I70-H70 -> 48639860198 | H70: 23641182035 | I70: 72281042233 | J70: 593582375012 | K70: 1750000000 | L70: 739402296030 | M70: 610537250674 | N70: =16696318068+35104646560+1722272231+3440944756 -> 56964181615 | O70: 60770710445 | P70: =4727523825+1777225450 -> 6504749275 | Q70: 354 | R70: =D70/G70 -> 10.479786 | S70: =H70/J70 -> 0.039827972 | T70: =O70/F70 -> 0.091304012 | U70: =O70/J70 -> 0.10237957 | V70: =O70/L70 -> 0.082188966 | W70: =(P70/K70)/Q70 -> 0.010499999 | X70: =P70/O70 -> 0.10703757 | Y70: =Q70/(O70/K70) -> 10.194056 | Z70: =Q70/(J70/K70) -> 1.0436631 | AA70: 3 | AB70: 0
A71: 2018 | B71: IMPC | C71: Impack Pratama Industri Tbk | D71: 1220137554014 | E71: 757379485281 | F71: 2370198817803 | G71: =I71-H71 -> 342328901816 | H71: 655646584965 | I71: 997975486781 | J71: 1372223331022 | K71: 17000000000 | L71: 1395298815177 | M71: 978652263708 | N71: =257005280578+15979424352 -> 272984704930 | O71: 105523929164 | P71: 43598000000 | Q71: 940 | R71: =D71/G71 -> 3.5642259 | S71: =H71/J71 -> 0.47779874 | T71: =O71/F71 -> 0.04452113 | U71: =O71/J71 -> 0.076899967 | V71: =O71/L71 -> 0.075628194 | W71: =(P71/K71)/Q71 -> 0.0027282854 | X71: =P71/O71 -> 0.41315747 | Y71: =Q71/(O71/K71) -> 151.43485 | Z71: =Q71/(J71/K71) -> 11.645335 | AA71: 3 | AB71: 0
A72: 2019 | B72: IMPC | C72: Impack Pratama Industri Tbk | D72: 1174699544323 | E72: 851624396191 | F72: 2501132856219 | G72: =I72-H72 -> 479079545266 | H72: 613765478165 | I72: 1092845023431 | J72: 1408287832788 | K72: 17000000000 | L72: 1495759701262 | M72: 1001042927237 | N72: =279134329437+70965395209+23904990387 -> 374004715033 | O72: 93145200039 | P72: 77775000000 | Q72: 1050 | R72: =D72/G72 -> 2.4519927 | S72: =H72/J72 -> 0.43582389 | T72: =O72/F72 -> 0.037241204 | U72: =O72/J72 -> 0.06614074 | V72: =O72/L72 -> 0.062272837 | W72: =(P72/K72)/Q72 -> 0.0043571429 | X72: =P72/O72 -> 0.83498667 | Y72: =Q72/(O72/K72) -> 191.63628 | Z72: =Q72/(J72/K72) -> 12.674966 | AA72: 3 | AB72: 0
A73: 2020 | B73: IMPC | C73: Impack Pratama Industri Tbk | D73: 1261952159927 | E73: 907748683255 | F73: 2697100062756 | G73: =I73-H73 -> 608353619395 | H73: 622838614595 | I73: 1231192233990 | J73: 1465907828766 | K73: 17000000000 | L73: 1797514877242 | M73: 1146328782026 | N73: =413457936700+66391570721+25729951405 -> 505579458826 | O73: 115805324362 | P73: 53280000000 | Q73: 1325 | R73: =D73/G73 -> 2.0743727 | S73: =H73/J73 -> 0.42488252 | T73: =O73/F73 -> 0.042936977 | U73: =O73/J73 -> 0.078999049 | V73: =O73/L73 -> 0.064425238 | W73: =(P73/K73)/Q73 -> 0.0023653718 | X73: =P73/O73 -> 0.46008247 | Y73: =Q73/(O73/K73) -> 194.50746 | Z73: =Q73/(J73/K73) -> 15.365905 | AA73: 3 | AB73: 0
A74: 2018 | B74: WIIM | C74: Wismilak Inti Makmur Tbk | D74: 888979741744 | E74: 319990859164 | F74: 1255573914558 | G74: =I74-H74 -> 150202377711 | H74: 100134734182 | I74: 250337111893 | J74: 1005236802665 | K74: 4050000000 | L74: 1405384153405 | M74: 963851587401 | N74: 389346287885 | O74: 51142850919 | P74: 0 | Q74: 141 | R74: =D74/G74 -> 5.9185464 | S74: =H74/J74 -> 0.09961308 | T74: =O74/F74 -> 0.040732648 | U74: =O74/J74 -> 0.050876421 | V74: =O74/L74 -> 0.036390656 | W74: =(P74/K74)/Q74 -> 0 | X74: =P74/O74 -> 0 | Y74: =Q74/(O74/K74) -> 11.165783 | Z74: =Q74/(J74/K74) -> 0.5680751 | AA74: 3 | AB74: 0
A75: 2019 | B75: WIIM | C75: Wismilak Inti Makmur Tbk | D75: 948430163983 | E75: 329061638626 | F75: 1299521608556 | G75: =I75-H75 -> 157443942631 | H75: 108907088448 | I75: 266351031079 | J75: 1033170577477 | K75: 4050000000 | L75: 1393574099760 | M75: 962040733573 | N75: 402885126126 | O75: 27328091481 | P75: =5249684400+12366950 -> 5262051350 | Q75: 168 | R75: =D75/G75 -> 6.0239229 | S75: =H75/J75 -> 0.10541056 | T75: =O75/F75 -> 0.021029347 | U75: =O75/J75 -> 0.026450706 | V75: =O75/L75 -> 0.019610074 | W75: =(P75/K75)/Q75 -> 0.0077337615 | X75: =P75/O75 -> 0.192551 | Y75: =Q75/(O75/K75) -> 24.897458 | Z75: =Q75/(J75/K75) -> 0.65855534 | AA75: 3 | AB75: 0
A76: 2020 | B76: WIIM | C76: Wismilak Inti Makmur Tbk | D76: 1288718539539 | E76: 298904982008 | F76: 1614442007528 | G76: =I76-H76 -> 351790782502 | H76: 76799383517 | I76: 428590166019 | J76: 1185851841509 | K76: 4050000000 | L76: 1994066771177 | M76: 1368626457514 | N76: 420569492780 | O76: 172506562986 | P76: =7349558160+47082300 -> 7396640460 | Q76: 540 | R76: =D76/G76 -> 3.6633096 | S76: =H76/J76 -> 0.064763051 | T76: =O76/F76 -> 0.10685213 | U76: =O76/J76 -> 0.14547059 | V76: =O76/L76 -> 0.086509923 | W76: =(P76/K76)/Q76 -> 0.0033820944 | X76: =P76/O76 -> 0.042877444 | Y76: =Q76/(O76/K76) -> 12.677779 | Z76: =Q76/(J76/K76) -> 1.8442439 | AA76: 3 | AB76: 0
A77: 2018 | B77: MRAT | C77: Mustika Ratu Tbk | D77: 382330851179 | E77: 59744095869 | F77: 511887783867 | G77: =I77-H77 -> 122929175890 | H77: 20984611197 | I77: 143913787087 | J77: 367973996780 | K77: 428000000 | L77: 300572751733 | M77: 126237236215 | N77: =121854966846+43793006242 -> 165647973088 | O77: 1242582777 | P77: 0 | Q77: 179 | R77: =D77/G77 -> 3.1101718 | S77: =H77/J77 -> 0.05702743 | T77: =O77/F77 -> 0.0024274515 | U77: =O77/J77 -> 0.0033768222 | V77: =O77/L77 -> 0.00413405 | W77: =(P77/K77)/Q77 -> 0 | X77: =P77/O77 -> 0 | Y77: =Q77/(O77/K77) -> 61.65545 | Z77: =Q77/(J77/K77) -> 0.20819949 | AA77: 3 | AB77: 0
A78: 2019 | B78: MRAT | C78: Mustika Ratu Tbk | D78: 412707718061 | E78: 54872479523 | F78: 532762947995 | G78: =I78-H78 -> 142931525716 | H78: 21189897229 | I78: 164121422945 | J78: 368641525050 | K78: 428000000 | L78: 305224577860 | M78: 120805351025 | N78: =127264471191+48192315737 -> 175456786928 | O78: 667528270 | P78: 0 | Q78: 153 | R78: =D78/G78 -> 2.8874506 | S78: =H78/J78 -> 0.057481037 | T78: =O78/F78 -> 0.0012529555 | U78: =O78/J78 -> 0.0018107788 | V78: =O78/L78 -> 0.0021870069 | W78: =(P78/K78)/Q78 -> 0 | X78: =P78/O78 -> 0 | Y78: =Q78/(O78/K78) -> 98.099216 | Z78: =Q78/(J78/K78) -> 0.17763598 | AA78: 3 | AB78: 0
A79: 2020 | B79: MRAT | C79: Mustika Ratu Tbk | D79: 432576455286 | E79: 55965014371 | F79: 559795937451 | G79: =I79-H79 -> 195801413331 | H79: 21575918643 | I79: 217377331974 | J79: 342418605477 | K79: 428000000 | L79: 318408499475 | M79: 113949955107 | N79: =132164370165+58327364740 -> 190491734905 | O79: 7263926826 | P79: 0 | Q79: 169 | R79: =D79/G79 -> 2.2092611 | S79: =H79/J79 -> 0.063010357 | T79: =O79/F79 -> 0.012976026 | U79: =O79/J79 -> 0.021213587 | V79: =O79/L79 -> 0.022813232 | W79: =(P79/K79)/Q79 -> 0 | X79: =P79/O79 -> 0 | Y79: =Q79/(O79/K79) -> 9.9576994 | Z79: =Q79/(J79/K79) -> 0.21123852 | AA79: 3 | AB79: 0
A80: 2018 | B80: DLTA | C80: Delta Djakarta Tbk | D80: 1384227944 | E80: 90191394000 | F80: 1523517170000 | G80: =I80-H80 -> 192299843000 | H80: 47053513000 | I80: 239353356000 | J80: 1284163814000 | K80: 800659050 | L80: 893006350000 | M80: 241721111000 | N80: =166486011000+68361970000 -> 234847981000 | O80: 338129985000 | P80: 207667269000 | Q80: 5500 | R80: =D80/G80 -> 0.0071982791 | S80: =H80/J80 -> 0.036641363 | T80: =O80/F80 -> 0.22194038 | U80: =O80/J80 -> 0.26330752 | V80: =O80/L80 -> 0.37864231 | W80: =(P80/K80)/Q80 -> 0.047158257 | X80: =P80/O80 -> 0.61416401 | Y80: =Q80/(O80/K80) -> 13.023467 | Z80: =Q80/(J80/K80) -> 3.4291768 | AA80: 3 | AB80: 1
A81: 2019 | B81: DLTA | C81: Delta Djakarta Tbk | D81: 1292805083 | E81: 85234517000 | F81: 1425983722000 | G81: =I81-H81 -> 160587363000 | H81: 51833027000 | I81: 212420390000 | J81: 1213563332000 | K81: 800659050 | L81: 827136727000 | M81: 230440697000 | N81: =175692185000+79000788000 -> 254692973000 | O81: 317815177000 | P81: 382134244000 | Q81: 6800 | R81: =D81/G81 -> 0.0080504783 | S81: =H81/J81 -> 0.042711431 | T81: =O81/F81 -> 0.22287434 | U81: =O81/J81 -> 0.26188594 | V81: =O81/L81 -> 0.38423536 | W81: =(P81/K81)/Q81 -> 0.070187444 | X81: =P81/O81 -> 1.2023788 | Y81: =Q81/(O81/K81) -> 17.130968 | Z81: =Q81/(J81/K81) -> 4.4863596 | AA81: 3 | AB81: 1
A82: 2020 | B82: DLTA | C82: Delta Djakarta Tbk | D82: 1103831856 | E82: 79117279000 | F82: 1225580913000 | G82: =I82-H82 -> 147207676000 | H82: 58474274000 | I82: 205681950000 | J82: 1019898963000 | K82: 800659050 | L82: 546336411000 | M82: 179156903000 | N82: =156629572000+78513510000 -> 235143082000 | O82: 123465762000 | P82: 311711537000 | Q82: 4400 | R82: =D82/G82 -> 0.0074984667 | S82: =H82/J82 -> 0.057333399 | T82: =O82/F82 -> 0.1007406 | U82: =O82/J82 -> 0.12105686 | V82: =O82/L82 -> 0.22598853 | W82: =(P82/K82)/Q82 -> 0.088481522 | X82: =P82/O82 -> 2.52468 | Y82: =Q82/(O82/K82) -> 28.533415 | Z82: =Q82/(J82/K82) -> 3.4541655 | AA82: 3 | AB82: 1
A83: 2018 | B83: GOOD | C83: Garudafood Putra Putri Jaya Tbk | D83: 1570545769306 | E83: 2280734909765 | F83: 4212408305683 | G83: =I83-H83 -> 1329358276278 | H83: 393641552725 | I83: 1722999829003 | J83: 2489408476680 | K83: 7130087567 | L83: 8048946664266 | M83: 5495794976776 | N83: =1361526966344+574981609169+48046719655 -> 1984555295168 | O83: 425481597110 | P83: 183082141237 | Q83: 1875 | R83: =D83/G83 -> 1.1814315 | S83: =H83/J83 -> 0.15812654 | T83: =O83/F83 -> 0.10100673 | U83: =O83/J83 -> 0.17091675 | V83: =O83/L83 -> 0.052861774 | W83: =(P83/K83)/Q83 -> 0.013694616 | X83: =P83/O83 -> 0.43029391 | Y83: =Q83/(O83/K83) -> 31.420664 | Z83: =Q83/(J83/K83) -> 5.3703176 | AA83: 3 | AB83: 0
A84: 2019 | B84: GOOD | C84: Garudafood Putra Putri Jaya Tbk | D84: 1999886108743 | E84: 2715366689138 | F84: 5063067672414 | G84: =I84-H84 -> 1303881731637 | H84: 993665175862 | I84: 2297546907499 | J84: 2765520764915 | K84: 7379580291 | L84: 8438631355699 | M84: 5910489349236 | N84: =1355631464428+554177456534+57788727828 -> 1967597648790 | O84: 435766359480 | P84: 132379748022 | Q84: 1510 | R84: =D84/G84 -> 1.5337941 | S84: =H84/J84 -> 0.35930491 | T84: =O84/F84 -> 0.086067655 | U84: =O84/J84 -> 0.15757118 | V84: =O84/L84 -> 0.051639459 | W84: =(P84/K84)/Q84 -> 0.011879904 | X84: =P84/O84 -> 0.30378607 | Y84: =Q84/(O84/K84) -> 25.571424 | Z84: =Q84/(J84/K84) -> 4.0293193 | AA84: 3 | AB84: 0
A85: 2020 | B85: GOOD | C85: Garudafood Putra Putri Jaya Tbk | D85: 2314323530275 | E85: 3217662289685 | F85: 6570969641033 | G85: =I85-H85 -> 1321529767664 | H85: 2355003084216 | I85: 3676532851880 | J85: 2894436789153 | K85: 7369648898 | L85: 7711334590144 | M85: 5568907814506 | N85: =1111326412293+603575877329+97215317609 -> 1812117607231 | O85: 245103761907 | P85: 213786027325 | Q85: 1270 | R85: =D85/G85 -> 1.7512459 | S85: =H85/J85 -> 0.81363086 | T85: =O85/F85 -> 0.037301004 | U85: =O85/J85 -> 0.084680986 | V85: =O85/L85 -> 0.031784869 | W85: =(P85/K85)/Q85 -> 0.02284172 | X85: =P85/O85 -> 0.87222663 | Y85: =Q85/(O85/K85) -> 38.185681 | Z85: =Q85/(J85/K85) -> 3.2336011 | AA85: 3 | AB85: 0
A86: 2018 | B86: INDF | C86: Indofood Sukses Makmur Tbk | D86: 33272618000000 | E86: 42388236000000 | F86: 96537796000000 | G86: =I86-H86 -> 31204102000000 | H86: 15416894000000 | I86: 46620996000000 | J86: 49916800000000 | K86: 8780426500 | L86: 73394728000000 | M86: 53182723000000 | N86: =7817444000000+4466279000000+278450000000 -> 12562173000000 | O86: 4961851000000 | P86: 2651689000000 | Q86: 7450 | R86: =D86/G86 -> 1.0662899 | S86: =H86/J86 -> 0.30885181 | T86: =O86/F86 -> 0.051398014 | U86: =O86/J86 -> 0.099402426 | V86: =O86/L86 -> 0.067605006 | W86: =(P86/K86)/Q86 -> 0.040536916 | X86: =P86/O86 -> 0.53441528 | Y86: =Q86/(O86/K86) -> 13.183422 | Z86: =Q86/(J86/K86) -> 1.3104642 | AA86: 3 | AB86: 0
A87: 2019 | B87: INDF | C87: Indofood Sukses Makmur Tbk | D87: 31403445000000 | E87: 43072504000000 | F87: 96198559000000 | G87: =I87-H87 -> 24686862000000 | H87: 17309209000000 | I87: 41996071000000 | J87: 54202488000000 | K87: 8780426500 | L87: 76592955000000 | M87: 53876594000000 | N87: =8489356000000+4697173000000+759131000000 -> 13945660000000 | O87: 5902729000000 | P87: 1501453000000 | Q87: 7925 | R87: =D87/G87 -> 1.2720712 | S87: =H87/J87 -> 0.31934344 | T87: =O87/F87 -> 0.061359848 | U87: =O87/J87 -> 0.10890144 | V87: =O87/L87 -> 0.077066213 | W87: =(P87/K87)/Q87 -> 0.021577288 | X87: =P87/O87 -> 0.2543659 | Y87: =Q87/(O87/K87) -> 11.788595 | Z87: =Q87/(J87/K87) -> 1.2837949 | AA87: 3 | AB87: 0
A88: 2020 | B88: INDF | C88: Indofood Sukses Makmur Tbk | D88: 38418238000000 | E88: 45862919000000 | F88: 163136516000000 | G88: =I88-H88 -> 27975875000000 | H88: 56022597000000 | I88: 83998472000000 | J88: 79138044000000 | K88: 8780426500 | L88: 81731469000000 | M88: 54979425000000 | N88: =9077860000000+5087140000000+563315000000 -> 14728315000000 | O88: 8752066000000 | P88: 2440959000000 | Q88: 6850 | R88: =D88/G88 -> 1.3732631 | S88: =H88/J88 -> 0.7079098 | T88: =O88/F88 -> 0.053648724 | U88: =O88/J88 -> 0.1105924 | V88: =O88/L88 -> 0.10708318 | W88: =(P88/K88)/Q88 -> 0.040583949 | X88: =P88/O88 -> 0.27890089 | Y88: =Q88/(O88/K88) -> 6.872197 | Z88: =Q88/(J88/K88) -> 0.76001274 | AA88: 3 | AB88: 0
A89: 2018 | B89: MYOR | C89: Mayora Indah Tbk | D89: 12647858727872 | E89: 4258300525120 | F89: 17591706426634 | G89: =I89-H89 -> 4764510387113 | H89: 4284651557827 | I89: 9049161944940 | J89: 8542544481694 | K89: 22358699725 | L89: 24060802395725 | M89: 17664148865078 | N89: 3768761522641 | O89: 1760434280304 | P89: 603684892575 | Q89: 2620 | R89: =D89/G89 -> 2.6545978 | S89: =H89/J89 -> 0.5015662 | T89: =O89/F89 -> 0.10007183 | U89: =O89/J89 -> 0.20607844 | V89: =O89/L89 -> 0.073166067 | W89: =(P89/K89)/Q89 -> 0.010305344 | X89: =P89/O89 -> 0.34291816 | Y89: =Q89/(O89/K89) -> 33.275763 | Z89: =Q89/(J89/K89) -> 6.8574174 | AA89: 3 | AB89: 0
A90: 2019 | B90: MYOR | C90: Mayora Indah Tbk | D90: 12776102781513 | E90: 4674963819225 | F90: 19037918806473 | G90: =I90-H90 -> 3726359539201 | H90: 5411619071954 | I90: 9137978611155 | J90: 9899940195318 | K90: 22358699725 | L90: 25026739472547 | M90: 17109498526032 | N90: 4744976395481 | O90: 2039404206764 | P90: 648402292025 | Q90: 2050 | R90: =D90/G90 -> 3.4285749 | S90: =H90/J90 -> 0.54663149 | T90: =O90/F90 -> 0.10712327 | U90: =O90/J90 -> 0.20600167 | V90: =O90/L90 -> 0.081489009 | W90: =(P90/K90)/Q90 -> 0.014146341 | X90: =P90/O90 -> 0.31793712 | Y90: =Q90/(O90/K90) -> 22.474865 | Z90: =Q90/(J90/K90) -> 4.6298597 | AA90: 3 | AB90: 0
